Workbook
Name ________A100000: #REF!
Name ________A100000: #REF!
Name ________A99999: #REF!
Name ________A99999: #REF!
Name _______A100000: #REF!
Name _______A100000: #REF!
Name _______A99999: #REF!
Name _______A99999: #REF!
Name _______Man1: [1]PaintBreak!$M$55
Name _______Man22: [1]PaintBreak!$M$56
Name _______Mat1: [1]PaintBreak!$K$55
Name _______Mat2: [1]PaintBreak!$K$56
Name ______A100000: #REF!
Name ______A100000: #REF!
Name ______A99999: #REF!
Name ______A99999: #REF!
Name ______Man1: [1]PaintBreak!$M$55
Name ______Man22: [1]PaintBreak!$M$56
Name ______Mat1: [1]PaintBreak!$K$55
Name ______Mat2: [1]PaintBreak!$K$56
Name _____A100000: #REF!
Name _____A100000: #REF!
Name _____A99999: #REF!
Name _____A99999: #REF!
Name _____Man1: [2]PaintBreak!$M$55
Name _____Man22: [2]PaintBreak!$M$56
Name _____Mat1: [2]PaintBreak!$K$55
Name _____Mat2: [2]PaintBreak!$K$56
Name ____A100000: #REF!
Name ____A100000: #REF!
Name ____A99999: #REF!
Name ____A99999: #REF!
Name ____Man1: [2]PaintBreak!$M$55
Name ____Man22: [2]PaintBreak!$M$56
Name ____Mat1: [2]PaintBreak!$K$55
Name ____Mat2: [2]PaintBreak!$K$56
Name ____UPA100: '[3]GTS I PS'!#REF!
Name ____UPA100: '[3]GTS I PS'!#REF!
Name ___A100000: #REF!
Name ___A100000: #REF!
Name ___A99999: #REF!
Name ___A99999: #REF!
Name ___FIL1: 'Cover Report'!___FIL1
Name ___FIL1: 'Exe Sum'!___FIL1
Name ___FIL1: [0]!___FIL1
Name ___Man1: [2]PaintBreak!$M$55
Name ___Man22: [2]PaintBreak!$M$56
Name ___Mat1: [2]PaintBreak!$K$55
Name ___Mat2: [2]PaintBreak!$K$56
Name ___UPA100: '[3]GTS I PS'!#REF!
Name ___UPA100: '[3]GTS I PS'!#REF!
Name __A100000: #REF!
Name __A100000: #REF!
Name __A99999: #REF!
Name __A99999: #REF!
Name __FIL1: 'Cover Report'!__FIL1
Name __FIL1: 'Exe Sum'!__FIL1
Name __FIL1: [0]!__FIL1
Name __Man1: [2]PaintBreak!$M$55
Name __Man22: [2]PaintBreak!$M$56

Sheet Cover Report
X1: Project Title | Y1: : | Z1: Integrated Management Dashboard Production & Project Zona 13
I2: DOCUMENT REPORT | U2: Up Date Every Week | X2: Doc Name | Y2: : | Z2: W2026I-DNGF-EM-100-PRG-WLY
B3: Project Title Integrated Management Dashboard Production & Project Zona 13 | K3: Document No. | L3: : | M3: =Z5 -> W2026I-DNGF-EM-100-PRG-WLY-0012 | X3: Doc No | Y3: : | Z3: 12
B4: Contract Number 901407233 | K4: SPK/ CTR Title | L4: : | M4: - | X4: Doc-togle | Y4: : | Z4: 0000
B5: Author's Organization Project | K5: Period | L5: : | M5: =Z10 -> 29 Juni 2026 - 05 Juli 2026 | X5: Doc-Concate | Y5: : | Z5: =CONCATENATE(Z2,"-",TEXT(Z3,Z4)) -> W2026I-DNGF-EM-100-PRG-WLY-0012
K6: Revision No. | L6: : | M6: 0 | N6: Date | O6: : | P6: =Z9 -> 46208
X8: Start Period | Y8: : | Z8: =HLOOKUP((Z3-1),'Overall MDR_'!BM11:CH12,2,FALSE)+1 -> 46202
X9: End Period | Y9: : | Z9: =HLOOKUP(Z3,'Overall MDR_'!BM11:CH12,2,FALSE) -> 46208
X10: Period-Concate | Y10: : | Z10: =TEXT(Z8,"dd mmmm yyyy")&" - "&TEXT(Z9,"dd mmmm yyyy") -> 29 Juni 2026 - 05 Juli 2026
I11: WEEKLY REPORT
C12: Integrated Management Dashboard Production & Project Zona 13
C16: Approval Sheet
C17: Name | I17: Tittle | L17: Date | O17: Signature
C18: Wahyudi | I18: Manager Project PEP Zona 13
C19: Seno Widjojo | I19: Sr Engineer Project & Safety
C20: Andik Yuli Wahyono | I20: Sr Engineer Construction
C21: Erikson Juanda Panjaitan | I21: Sr Engineer Project Economics & Risk
C22: Nyoman Ading Widiartama | I22: Sr Project Budget & Cost Control PEP Zona 13
C23: Bambang Saefu | I23: Sr Engineering Project Planning & Schedulling
C24: Abdurahmman Hadiwijaya | I24: Sr. Engineer Project Contract Management PEP Zona 13
C29: Revision Status
C30: Rev | D30: Issue Date | H30: ITS PTN BH | L30: Issue Porpose
H31: Prepared | J31: Checked | K31: Approved
C32: 0 | D32: =P6 -> 46208 | H32: AR | J32: BS | K32: ES | L32: Issued for Information

Sheet TOC
E1: PERTAMINA EP
E3: Project Title : | K3: Document Number :
E4: ='Cover Report'!Z1 -> Integrated Management Dashboard Production & Project Zona 13 | K4: ='Cover Report'!Z5 -> W2026I-DNGF-EM-100-PRG-WLY-0012
E5: Document Title: | K5: Page ii
E6: Weekly Report
A9: Table of Content
B11: Cover | M11: i
B12: Table of Content | M12: ii
B13: Executive Summary | M13: iii
B14: Area of Concern / Issues and Mitigation Plan | M14: iii
B15: Master Deliverable Register | M15: iii
B16: Document Issued in This Week 01
B18: Appendices
B19: Appendix A | C19: Project S-Curve
B20: Appendix B | C20: Master Deliverable Register
B21: Appendix C | C21: Document Submitted in Week 01
B22: Appendix D | C22: Activity Documentation
G187: ELECTRICAL & INSTRUMENTATION ENGINEERING (as of 2 October)
O267: 0.9176 | P267: 0.8494
P268: 1
O274: 0.9121 | P274: 0.8934
P275: 0.685

Sheet Exe Sum
E1: =TOC!E1 -> PERTAMINA EP
E3: Project Title : | O3: Document Number : | Y3: Doc | Z3: : | AA3: ='Cover Report'!Z3 -> 12 | AL3: Previous | AQ3: This Week | AV3: To Date
E4: =TOC!E4 -> Integrated Management Dashboard Production & Project Zona 13 | O4: ='Cover Report'!Z5 -> W2026I-DNGF-EM-100-PRG-WLY-0012 | Y4: Project Name | Z4: : | AA4: ='Cover Report'!Z1 -> Integrated Management Dashboard Production & Project Zona 13 | AL4: Plan | AM4: Recovery | AN4: Actual | AO4: Variance | AP4: Variance to Recovery | AQ4: Plan | AR4: Recovery | AS4: Actual | AT4: Variance | AU4: Variance to Recovery | AV4: Plan | AW4: Recovery | AX4: Actual | AY4: Variance | AZ4: Variance to Recovery
E5: Document Title: | O5: Page iii | Y5: Start Date | Z5: : | AA5: ='Cover Report'!Z8 -> 46202 | AK5: 1 | AL5: {=_xlfn._xlws.FILTER('Overall MDR_'!BM50:CH50,'Overall MDR_'!BM$11:CH$11=('Exe Sum'!$AA$3-1))} -> 1 | AM5: {=_xlfn._xlws.FILTER('Overall MDR_'!CL50:DG50,'Overall MDR_'!CL$11:DG$11=('Exe Sum'!$AA$3-1))} -> 0 | AN5: {=_xlfn._xlws.FILTER('Overall MDR_'!DL50:EG50,'Overall MDR_'!DL$11:EG$11=('Exe Sum'!$AA$3-1))} -> 1 | AO5: =AN5-AL5 -> 0 | AP5: =AN5-AM5 -> 1 | AQ5: =AV5-AL5 -> 0 | AR5: =AW5-AM5 -> 0 | AS5: =AX5-AN5 -> 0 | AT5: =AS5-AQ5 -> 0 | AU5: =AS5-AR5 -> 0 | AV5: {=_xlfn._xlws.FILTER('Overall MDR_'!BM50:CH50,'Overall MDR_'!BM$11:CH$11=('Exe Sum'!$AA$3))} -> 1 | AW5: {=_xlfn._xlws.FILTER('Overall MDR_'!CL50:DG50,'Overall MDR_'!CL$11:DG$11=('Exe Sum'!$AA$3))} -> 0 | AX5: {=_xlfn._xlws.FILTER('Overall MDR_'!DL50:EG50,'Overall MDR_'!DL$11:EG$11=('Exe Sum'!$AA$3))} -> 1 | AY5: =AX5-AV5 -> 0 | AZ5: =AX5-AW5 -> 1
E6: =TOC!E6 -> Weekly Report | Y6: End Date | Z6: : | AA6: ='Cover Report'!Z9 -> 46208 | AK6: 2 | AL6: {=_xlfn._xlws.FILTER('Overall MDR_'!BM51:CH51,'Overall MDR_'!BM$11:CH$11=('Exe Sum'!$AA$3-1))} -> 1 | AM6: {=_xlfn._xlws.FILTER('Overall MDR_'!CL51:DG51,'Overall MDR_'!CL$11:DG$11=('Exe Sum'!$AA$3-1))} -> 0 | AN6: {=_xlfn._xlws.FILTER('Overall MDR_'!DL51:EG51,'Overall MDR_'!DL$11:EG$11=('Exe Sum'!$AA$3-1))} -> 0 | AO6: =AN6-AL6 -> -1 | AP6: =AN6-AM6 -> 0 | AQ6: =AV6-AL6 -> 0 | AR6: =AW6-AM6 -> 0 | AS6: =AX6-AN6 -> 0 | AT6: =AS6-AQ6 -> 0 | AU6: =AS6-AR6 -> 0 | AV6: {=_xlfn._xlws.FILTER('Overall MDR_'!BM51:CH51,'Overall MDR_'!BM$11:CH$11=('Exe Sum'!$AA$3))} -> 1 | AW6: {=_xlfn._xlws.FILTER('Overall MDR_'!CL51:DG51,'Overall MDR_'!CL$11:DG$11=('Exe Sum'!$AA$3))} -> 0 | AX6: {=_xlfn._xlws.FILTER('Overall MDR_'!DL51:EG51,'Overall MDR_'!DL$11:EG$11=('Exe Sum'!$AA$3))} -> 0 | AY6: =AX6-AV6 -> -1 | AZ6: =AX6-AW6 -> 0
Y7: Progress Plan | Z7: : | AA7: =O29 -> 0.85975 | AK7: 3 | AL7: {=_xlfn._xlws.FILTER('Overall MDR_'!BM52:CH52,'Overall MDR_'!BM$11:CH$11=('Exe Sum'!$AA$3-1))} -> 0.97475476 | AM7: {=_xlfn._xlws.FILTER('Overall MDR_'!CL52:DG52,'Overall MDR_'!CL$11:DG$11=('Exe Sum'!$AA$3-1))} -> 0 | AN7: {=_xlfn._xlws.FILTER('Overall MDR_'!DL52:EG52,'Overall MDR_'!DL$11:EG$11=('Exe Sum'!$AA$3-1))} -> 1 | AO7: =AN7-AL7 -> 0.025245239 | AP7: =AN7-AM7 -> 1 | AQ7: =AV7-AL7 -> 0.025245239 | AR7: =AW7-AM7 -> 0 | AS7: =AX7-AN7 -> 0 | AT7: =AS7-AQ7 -> -0.025245239 | AU7: =AS7-AR7 -> 0 | AV7: {=_xlfn._xlws.FILTER('Overall MDR_'!BM52:CH52,'Overall MDR_'!BM$11:CH$11=('Exe Sum'!$AA$3))} -> 1 | AW7: {=_xlfn._xlws.FILTER('Overall MDR_'!CL52:DG52,'Overall MDR_'!CL$11:DG$11=('Exe Sum'!$AA$3))} -> 0 | AX7: {=_xlfn._xlws.FILTER('Overall MDR_'!DL52:EG52,'Overall MDR_'!DL$11:EG$11=('Exe Sum'!$AA$3))} -> 1 | AY7: =AX7-AV7 -> 0 | AZ7: =AX7-AW7 -> 1
Y8: Actual Plan | Z8: : | AA8: =Q29 -> 0.8667 | AK8: 4 | AL8: {=_xlfn._xlws.FILTER('Overall MDR_'!BM53:CH53,'Overall MDR_'!BM$11:CH$11=('Exe Sum'!$AA$3-1))} -> 1 | AM8: {=_xlfn._xlws.FILTER('Overall MDR_'!CL53:DG53,'Overall MDR_'!CL$11:DG$11=('Exe Sum'!$AA$3-1))} -> 0 | AN8: {=_xlfn._xlws.FILTER('Overall MDR_'!DL53:EG53,'Overall MDR_'!DL$11:EG$11=('Exe Sum'!$AA$3-1))} -> 1 | AO8: =AN8-AL8 -> 0 | AP8: =AN8-AM8 -> 1 | AQ8: =AV8-AL8 -> 0 | AR8: =AW8-AM8 -> 0 | AS8: =AX8-AN8 -> 0 | AT8: =AS8-AQ8 -> 0 | AU8: =AS8-AR8 -> 0 | AV8: {=_xlfn._xlws.FILTER('Overall MDR_'!BM53:CH53,'Overall MDR_'!BM$11:CH$11=('Exe Sum'!$AA$3))} -> 1 | AW8: {=_xlfn._xlws.FILTER('Overall MDR_'!CL53:DG53,'Overall MDR_'!CL$11:DG$11=('Exe Sum'!$AA$3))} -> 0 | AX8: {=_xlfn._xlws.FILTER('Overall MDR_'!DL53:EG53,'Overall MDR_'!DL$11:EG$11=('Exe Sum'!$AA$3))} -> 1 | AY8: =AX8-AV8 -> 0 | AZ8: =AX8-AW8 -> 1
A9: Executive Summary | Y9: Variance | Z9: : | AA9: =R29 -> 0.00695 | AK9: 5 | AL9: {=_xlfn._xlws.FILTER('Overall MDR_'!BM54:CH54,'Overall MDR_'!BM$11:CH$11=('Exe Sum'!$AA$3-1))} -> 0.83333333 | AM9: {=_xlfn._xlws.FILTER('Overall MDR_'!CL54:DG54,'Overall MDR_'!CL$11:DG$11=('Exe Sum'!$AA$3-1))} -> 0.16666667 | AN9: {=_xlfn._xlws.FILTER('Overall MDR_'!DL54:EG54,'Overall MDR_'!DL$11:EG$11=('Exe Sum'!$AA$3-1))} -> 1 | AO9: =AN9-AL9 -> 0.16666667 | AP9: =AN9-AM9 -> 0.83333333 | AQ9: =AV9-AL9 -> 0.16666667 | AR9: =AW9-AM9 -> 0 | AS9: =AX9-AN9 -> 0 | AT9: =AS9-AQ9 -> -0.16666667 | AU9: =AS9-AR9 -> 0 | AV9: {=_xlfn._xlws.FILTER('Overall MDR_'!BM54:CH54,'Overall MDR_'!BM$11:CH$11=('Exe Sum'!$AA$3))} -> 1 | AW9: {=_xlfn._xlws.FILTER('Overall MDR_'!CL54:DG54,'Overall MDR_'!CL$11:DG$11=('Exe Sum'!$AA$3))} -> 0.16666667 | AX9: {=_xlfn._xlws.FILTER('Overall MDR_'!DL54:EG54,'Overall MDR_'!DL$11:EG$11=('Exe Sum'!$AA$3))} -> 1 | AY9: =AX9-AV9 -> 0 | AZ9: =AX9-AW9 -> 0.83333333
Y10: Recovery | Z10: : | AA10: ='Overall MDR_'!BJ38 -> 0.0309 | AK10: 6 | AL10: {=_xlfn._xlws.FILTER('Overall MDR_'!BM55:CH55,'Overall MDR_'!BM$11:CH$11=('Exe Sum'!$AA$3-1))} -> 0.3244145 | AM10: {=_xlfn._xlws.FILTER('Overall MDR_'!CL55:DG55,'Overall MDR_'!CL$11:DG$11=('Exe Sum'!$AA$3-1))} -> 0 | AN10: {=_xlfn._xlws.FILTER('Overall MDR_'!DL55:EG55,'Overall MDR_'!DL$11:EG$11=('Exe Sum'!$AA$3-1))} -> 0.55004812 | AO10: =AN10-AL10 -> 0.22563362 | AP10: =AN10-AM10 -> 0.55004812 | AQ10: =AV10-AL10 -> 0.22563362 | AR10: =AW10-AM10 -> 0 | AS10: =AX10-AN10 -> 0.18752005 | AT10: =AS10-AQ10 -> -0.038113571 | AU10: =AS10-AR10 -> 0.18752005 | AV10: {=_xlfn._xlws.FILTER('Overall MDR_'!BM55:CH55,'Overall MDR_'!BM$11:CH$11=('Exe Sum'!$AA$3))} -> 0.55004812 | AW10: {=_xlfn._xlws.FILTER('Overall MDR_'!CL55:DG55,'Overall MDR_'!CL$11:DG$11=('Exe Sum'!$AA$3))} -> 0 | AX10: {=_xlfn._xlws.FILTER('Overall MDR_'!DL55:EG55,'Overall MDR_'!DL$11:EG$11=('Exe Sum'!$AA$3))} -> 0.73756817 | AY10: =AX10-AV10 -> 0.18752005 | AZ10: =AX10-AW10 -> 0.73756817
A11: 1. | B11: Executive Summary
B12: =AA14&" "&AA15&" "&AA16&" "&AA17&" "&AA18 -> Integrated Management Dashboard Production & Project Zona 13 progress this week (cut-off date : 05 Juli 2026) : planned cumulative progress plan is 85.98% against the actual cumulative progress of 86.67%. The progress for this week is behind the schedule 3.09%
Y13: Exe sum
AA14: =AA4 -> Integrated Management Dashboard Production & Project Zona 13
B15: The detailed breakdown of the discipline weekly summary is presented in the following table. | AA15: ="progress this week (cut-off date : "&TEXT(AA6,"dd mmmm yyyy")&") : " -> progress this week (cut-off date : 05 Juli 2026) :
AA16: ="planned cumulative progress plan is "&TEXT(AA7,"0.00%") -> planned cumulative progress plan is 85.98%
B17: Table 1.1 Discipline Weekly Summary | AA17: ="against the actual cumulative progress of "&TEXT(AA8,"0.00%")&"." -> against the actual cumulative progress of 86.67%.
AA18: ="The progress for this week is behind the schedule "&TEXT(AA10,"0.00%") -> The progress for this week is behind the schedule 3.09%
B19: No | C19: Description | D19: WF | E19: Previous Week (Cumulative) | J19: This Week | O19: To Date (Cumulative) | T19: Remarks
E20: Plan | F20: Recovery | G20: Actual | H20: Variance | I20: Variance to Recovery | J20: Plan | K20: Recovery | L20: Actual | M20: Variance | N20: Variance to Recovery | O20: Plan | P20: Recovery | Q20: Actual | R20: Variance | S20: Variance to Recovery | Y20: MDR
AA21: ="See Appendix B for the full Master Deliverable Register (MDR) with updated dates as of "&TEXT(AA6,"dd mmmm yyyy") -> See Appendix B for the full Master Deliverable Register (MDR) with updated dates as of 05 Juli 2026
B22: 1 | C22: ='Overall MDR_'!C16 -> Analisis Kebutuhan | D22: ='Overall MDR_'!F16 -> 0.0927 | E22: =AL5 -> 1 | F22: =AM5 -> 0 | G22: =AN5 -> 1 | H22: =AO5 -> 0 | I22: 0 | J22: =AQ5 -> 0 | K22: =AR5 -> 0 | L22: =AS5 -> 0 | M22: =AT5 -> 0 | N22: =AU5 -> 0 | O22: =AV5 -> 1 | P22: =AW5 -> 0 | Q22: =AX5 -> 1 | R22: =AY5 -> 0 | S22: 0
B23: 2 | C23: ='Overall MDR_'!C19 -> Pengadaan | D23: ='Overall MDR_'!F19 -> 0.0515 | E23: =AL6 -> 1 | F23: =AM6 -> 0 | G23: =AN6 -> 0 | H23: =AO6 -> -1 | I23: =AP6 -> 0 | J23: =AQ6 -> 0 | K23: =AR6 -> 0 | L23: =AS6 -> 0 | ... R23: =AY6 -> -1 | S23: =Q23-P23 -> 0 | T23: Menunggu Keputsan dari Pertamina terkait dengan pengadaan Hardware
B24: 3 | C24: ='Overall MDR_'!C21 -> Desain UI/UX | D24: ='Overall MDR_'!F21 -> 0.1733 | E24: =AL7 -> 0.97475476 | F24: =AM7 -> 0 | G24: =AN7 -> 1 | H24: =AO7 -> 0.025245239 | I24: 0 | J24: =AQ7 -> 0.025245239 | K24: =AR7 -> 0 | L24: =AS7 -> 0 | M24: =AT7 -> -0.025245239 | N24: =AU7 -> 0 | O24: =AV7 -> 1 | P24: =AW7 -> 0 | Q24: =AX7 -> 1 | R24: =AY7 -> 0 | S24: 0
B25: 4 | C25: ='Overall MDR_'!C25 -> Integrasi Sumber Data; Konfigurasi database dengan sumber data; Data Connection Schema & Production Data Mapping | D25: ='Overall MDR_'!F25 -> 0.1854 | E25: =AL8 -> 1 | F25: =AM8 -> 0 | G25: =AN8 -> 1 | H25: =AO8 -> 0 | I25: 0 | J25: =AQ8 -> 0 | K25: =AR8 -> 0 | L25: =AS8 -> 0 | M25: =AT8 -> 0 | N25: =AU8 -> 0 | O25: =AV8 -> 1 | P25: =AW8 -> 0 | Q25: =AX8 -> 1 | R25: =AY8 -> 0 | S25: 0
B26: 5 | C26: ='Overall MDR_'!C29 -> Persiapan Data (ETL) | D26: ='Overall MDR_'!F29 -> 0.1854 | E26: =AL9 -> 0.83333333 | F26: 0 | G26: =AN9 -> 1 | H26: =AO9 -> 0.16666667 | I26: 0 | J26: =AQ9 -> 0.16666667 | K26: =AR9 -> 0 | L26: =AS9 -> 0 | M26: =AT9 -> -0.16666667 | N26: =AU9 -> 0 | O26: =AV9 -> 1 | P26: 0 | Q26: =AX9 -> 1 | R26: =AY9 -> 0 | S26: 0
B27: 6 | C27: ='Overall MDR_'!C32 -> Pengembangan Dashboard | D27: ='Overall MDR_'!F32 -> 0.3117 | E27: =AL10 -> 0.3244145 | F27: =AM10 -> 0 | G27: =AN10 -> 0.55004812 | H27: =AO10 -> 0.22563362 | I27: 0 | J27: =AQ10 -> 0.22563362 | K27: =AR10 -> 0 | L27: =AS10 -> 0.18752005 | M27: =AT10 -> -0.038113571 | N27: 0 | O27: =AV10 -> 0.55004812 | P27: =AW10 -> 0 | Q27: =AX10 -> 0.73756817 | R27: =AY10 -> 0.18752005 | S27: 0 | T27: Menunggu Keputsan dari Pertamina untuk kelanjutannya
C29: Overall | D29: =SUM(D22:D27) -> 1 | E29: {=SUMPRODUCT($D$22:$D$27*E$22:E$27)} -> 0.754145 | F29: {=SUMPRODUCT(D22:D27*F22:F27)} -> 0 | G29: {=SUMPRODUCT(D22:D27*G22:G27)} -> 0.80825 | H29: {=SUMPRODUCT($D$22:$D$27*H$22:H$27)} -> 0.054105 | I29: {=SUMPRODUCT(D22:D27*I22:I27)} -> 0 | J29: {=SUMPRODUCT($D$22:$D$27*J$22:J$27)} -> 0.105605 | K29: {=SUMPRODUCT(D22:D27*K22:K27)} -> 0 | L29: {=SUMPRODUCT($D$22:$D$27*L$22:L$27)} -> 0.05845 | M29: {=SUMPRODUCT($D$22:$D$27*M$22:M$27)} -> -0.047155 | N29: {=SUMPRODUCT(D22:D27*N22:N27)} -> 0 | O29: {=SUMPRODUCT($D$22:$D$27*O$22:O$27)} -> 0.85975 | P29: {=SUMPRODUCT(D22:D27*P22:P27)} -> 0 | Q29: {=SUMPRODUCT($D$22:$D$27*Q$22:Q$27)} -> 0.8667 | R29: {=SUMPRODUCT($D$22:$D$27*R$22:R$27)} -> 0.00695 | S29: {=SUMPRODUCT(D22:D27*S22:S27)} -> 0
B30: * | C30: The S-Curve can be seen in Appendix-A
A32: 2. | B32: Area of Concern / Issues and Mitigation Plan
B33: 1. Pertamina dapat mulai melakukan review terhadap dashboard yang telah dikembangkan oleh ITS 2. Dokumen 6d sedang dalam review oleh Pak Seno. 3. Data AIRMS dan I2AIMS yang digunakan di modul OSF adalah data dummy. Jika terdapat data yang baru disampaikan, dapat di lakukan pada fase berikutnya (Post Implementation). 4. Untuk modul Project, saat ini masih ada contoh NBD (Project dengan ITS), untuk contoh Project BD belum ada.
A35: 3. | B35: Master Deliverable Register
B36: =AA21 -> See Appendix B for the full Master Deliverable Register (MDR) with updated dates as of 05 Juli 2026
A38: 4. | B38: Document Issued in This Week
B39: Week | C39: =": "&AA3 -> : 12
B40: Start Date | C40: =": "&TEXT(AA5,"dd mmmm yyyy") -> : 29 Juni 2026
B41: End Date | C41: =": "&TEXT(AA6,"dd mmmm yyyy") -> : 05 Juli 2026
B42: The list submitted document is provided in Appendix C
H167: ELECTRICAL & INSTRUMENTATION ENGINEERING (as of 2 October)
U247: 0.9176 | V247: 0.8494
V248: 1
U254: 0.9121 | V254: 0.8934
V255: 0.685

Sheet Appendix A
D1: =TOC!E1 -> PERTAMINA EP
D3: Project Title : | L3: Document Number :
D4: ='Cover Report'!Z1 -> Integrated Management Dashboard Production & Project Zona 13 | L4: ='Cover Report'!Z5 -> W2026I-DNGF-EM-100-PRG-WLY-0012
D5: Document Title: | L5: Appendix A
D6: =TOC!E6 -> Weekly Report
A27: APPENDIX A
A29: PROJECT S-CURVE
R269: ELECTRICAL & INSTRUMENTATION ENGINEERING (as of 2 October)
J278: ELECTRICAL & INSTRUMENTATION ENGINEERING (as of 2 October)
AF349: 0.9176 | AG349: 0.8494
AG350: 1
AF356: 0.9121 | AG356: 0.8934
AG357: 0.685

Sheet S-Overall
A1: ITS PTN BH
A2: S - CURVE - OVERALL
A4: CLIENT | B4: : | C4: PT Pertamina EP
A5: PROJECT | B5: : | C5: ='Cover Report'!Z1 -> Integrated Management Dashboard Production & Project Zona 13
A6: WO Ttile. | B6: : | C6: ='Cover Report'!Z2 -> W2026I-DNGF-EM-100-PRG-WLY
A7: WO No. | B7: : | C7: ='Cover Report'!Z5 -> W2026I-DNGF-EM-100-PRG-WLY-0012
AP12: ='Overall MDR_'!BM11 -> 0 | AQ12: ='Overall MDR_'!BN11 -> 0 | AR12: ='Overall MDR_'!BO11 -> 1 | AS12: ='Overall MDR_'!BP11 -> 2 | AT12: ='Overall MDR_'!BQ11 -> 3 | AU12: ='Overall MDR_'!BR11 -> 4 | AV12: ='Overall MDR_'!BS11 -> 5 | AW12: ='Overall MDR_'!BT11 -> 6 | ... BK12: ='Overall MDR_'!CH11 -> 20
AP13: ='Overall MDR_'!BM12 -> 46113 | AQ13: ='Overall MDR_'!BN12 -> 46124 | AR13: ='Overall MDR_'!BO12 -> 46131 | AS13: ='Overall MDR_'!BP12 -> 46138 | AT13: ='Overall MDR_'!BQ12 -> 46145 | AU13: ='Overall MDR_'!BR12 -> 46152 | AV13: ='Overall MDR_'!BS12 -> 46159 | AW13: ='Overall MDR_'!BT12 -> 46166 | ... BK13: ='Overall MDR_'!CH12 -> 46265
AN14: =A64 -> ACTUAL THIS WEEK | AP14: =AP15 -> 0 | AQ14: =AQ15-AP15 -> 0.217725 | AR14: =AR15-AQ15 -> 0.144065 | AS14: =AS15-AR15 -> 0.05701 | AT14: =AT15-AS15 -> 0.01876 | AU14: =AU15-AT15 -> 0.01545 | AV14: =AV15-AU15 -> 0.05959 | AW14: =AW15-AV15 -> 0.009425 | AX14: =AX15-AW15 -> 0.030885 | ... BC14: =BC15-BB15 -> 0.05845
AN15: =A65 -> ACTUAL CUMMULATIVE | AP15: ='Overall MDR_'!DL47 -> 0 | AQ15: ='Overall MDR_'!DM47 -> 0.217725 | AR15: ='Overall MDR_'!DN47 -> 0.36179 | AS15: ='Overall MDR_'!DO47 -> 0.4188 | AT15: ='Overall MDR_'!DP47 -> 0.43756 | AU15: ='Overall MDR_'!DQ47 -> 0.45301 | AV15: ='Overall MDR_'!DR47 -> 0.5126 | AW15: ='Overall MDR_'!DS47 -> 0.522025 | ... BC15: ='Overall MDR_'!DY47 -> 0.8667
AN16: =A66 -> PLAN THIS WEEK | AP16: =AP17 -> 0 | AQ16: =AQ17-AP17 -> 0.063355 | AR16: =AR17-AQ17 -> 0.03709 | AS16: =AS17-AR17 -> 0.07108 | AT16: =AT17-AS17 -> 0.042595 | AU16: =AU17-AT17 -> 0.04895 | AV16: =AV17-AU17 -> 0.12258 | AW16: =AW17-AV17 -> 0.088225 | AX16: =AX17-AW17 -> 0.084175 | ... BK16: =BK17-BJ17 -> 0
AN17: =A67 -> PLAN CUMMULATIVE | AP17: ='Overall MDR_'!BM47 -> 0 | AQ17: ='Overall MDR_'!BN47 -> 0.063355 | AR17: ='Overall MDR_'!BO47 -> 0.100445 | AS17: ='Overall MDR_'!BP47 -> 0.171525 | AT17: ='Overall MDR_'!BQ47 -> 0.21412 | AU17: ='Overall MDR_'!BR47 -> 0.26307 | AV17: ='Overall MDR_'!BS47 -> 0.38565 | AW17: ='Overall MDR_'!BT47 -> 0.473875 | ... BK17: ='Overall MDR_'!CH47 -> 1
AN18: =A68 -> Recovery | AP18: ='Overall MDR_'!CL47 -> 0 | AQ18: ='Overall MDR_'!CM47 -> 0 | AR18: ='Overall MDR_'!CN47 -> 0 | AS18: ='Overall MDR_'!CO47 -> 0.0309 | AT18: ='Overall MDR_'!CP47 -> 0.0309 | AU18: ='Overall MDR_'!CQ47 -> 0.0309 | AV18: ='Overall MDR_'!CR47 -> 0.0309 | AW18: ='Overall MDR_'!CS47 -> 0.0309 | ... BC18: ='Overall MDR_'!CY47 -> 0.0309
AN19: =A69 -> VARIANCE TO Recovery | AP19: =AP15-AP18 -> 0 | AQ19: =AQ15-AQ18 -> 0.217725 | AR19: =AR15-AR18 -> 0.36179 | AS19: =AS15-AS18 -> 0.3879 | AT19: =AT15-AT18 -> 0.40666 | AU19: =AU15-AU18 -> 0.42211 | AV19: =AV15-AV18 -> 0.4817 | AW19: =AW15-AW18 -> 0.491125 | ... BC19: =BC15-BC18 -> 0.8358
AN20: =A70 -> VARIANCE TO PLAN | AP20: =AP15-AP17 -> 0 | AQ20: =AQ15-AQ17 -> 0.15437 | AR20: =AR15-AR17 -> 0.261345 | AS20: =AS15-AS17 -> 0.247275 | AT20: =AT15-AT17 -> 0.22344 | AU20: =AU15-AU17 -> 0.18994 | AV20: =AV15-AV17 -> 0.12695 | AW20: =AW15-AW17 -> 0.04815 | ... BC20: =BC15-BC17 -> 0.00695
D24: OPF Balongan - Adequacy Check
A58: DESCRIPTION | C58: =AP12 -> 0 | D58: =AQ12 -> 0 | E58: =AR12 -> 1 | F58: =AS12 -> 2 | G58: =AT12 -> 3 | H58: =AU12 -> 4 | I58: =AV12 -> 5 | J58: =AW12 -> 6 | ... X58: =BK12 -> 20
C59: =AP13 -> 46113 | D59: =AQ13 -> 46124 | E59: =AR13 -> 46131 | F59: =AS13 -> 46138 | G59: =AT13 -> 46145 | H59: =AU13 -> 46152 | I59: =AV13 -> 46159 | J59: =AW13 -> 46166 | ... X59: =BK13 -> 46265
A63: PLANNED | C63: 0 | D63: 0 | E63: 0 | F63: 0.03949962 | G63: 1.0394996 | H63: 1.0394996 | I63: 1.0394996 | J63: 1.0394996 | K63: 1.0394996 | L63: 1.0394996 | M63: 1.0394996 | N63: 1.0394996 | O63: 1.0394996 | P63: 1.0394996 | Q63: 1.0394996 | R63: 1.0394996 | S63: 1.0394996 | T63: 1.0394996 | U63: 1.0394996 | V63: 1.0394996 | W63: 1.0394996 | X63: 1.0394996
A64: ACTUAL THIS WEEK | C64: =AP14 -> 0 | D64: =AQ14 -> 0.217725 | E64: =AR14 -> 0.144065 | F64: =AS14 -> 0.05701 | G64: =AT14 -> 0.01876 | H64: =AU14 -> 0.01545 | I64: =AV14 -> 0.05959 | J64: =AW14 -> 0.009425 | ... P64: =BC14 -> 0.05845
A65: ACTUAL CUMMULATIVE | C65: =AP15 -> 0 | D65: =AQ15 -> 0.217725 | E65: =AR15 -> 0.36179 | F65: =AS15 -> 0.4188 | G65: =AT15 -> 0.43756 | H65: =AU15 -> 0.45301 | I65: =AV15 -> 0.5126 | J65: =AW15 -> 0.522025 | ... P65: =BC15 -> 0.8667
A66: PLAN THIS WEEK | C66: =AP16 -> 0 | D66: =AQ16 -> 0.063355 | E66: =AR16 -> 0.03709 | F66: =AS16 -> 0.07108 | G66: =AT16 -> 0.042595 | H66: =AU16 -> 0.04895 | I66: =AV16 -> 0.12258 | J66: =AW16 -> 0.088225 | ... X66: =BK16 -> 0
A67: PLAN CUMMULATIVE | C67: =AP17 -> 0 | D67: =AQ17 -> 0.063355 | E67: =AR17 -> 0.100445 | F67: =AS17 -> 0.171525 | G67: =AT17 -> 0.21412 | H67: =AU17 -> 0.26307 | I67: =AV17 -> 0.38565 | J67: =AW17 -> 0.473875 | ... X67: =BK17 -> 1
A68: Recovery | C68: =AP18 -> 0 | D68: 0 | E68: 0 | F68: 0 | G68: 0 | H68: 0 | I68: 0 | J68: 0 | K68: 0 | L68: 0 | M68: 0 | N68: 0 | O68: 0 | P68: 0
A69: VARIANCE TO Recovery | C69: =AP19 -> 0 | D69: 0 | E69: 0 | F69: 0 | G69: 0 | H69: 0 | I69: 0 | J69: 0 | K69: 0 | L69: 0 | M69: 0 | N69: 0 | O69: 0 | P69: 0
A70: VARIANCE TO PLAN | C70: =AP20 -> 0 | D70: =AQ20 -> 0.15437 | E70: =AR20 -> 0.261345 | F70: =AS20 -> 0.247275 | G70: =AT20 -> 0.22344 | H70: =AU20 -> 0.18994 | I70: =AV20 -> 0.12695 | J70: =AW20 -> 0.04815 | ... P70: =BC20 -> 0.00695

Sheet Check
B3: Exe Sum | C3: S-Curve
A4: Previous (Cummulative)
A5: Plan | B5: ='Exe Sum'!E29 -> 0.754145 | C5: ='S-Overall'!O67 -> 0.754145 | D5: =IF(B5=C5,"Sesuai","Tidak Sesuai") -> Sesuai
A6: Aktual | B6: ='Exe Sum'!G29 -> 0.80825 | C6: ='S-Overall'!O65 -> 0.80825 | D6: =IF(B6=C6,"Sesuai","Tidak Sesuai") -> Sesuai
A7: Variance | B7: ='Exe Sum'!H29 -> 0.054105 | C7: ='S-Overall'!O70 -> 0.054105 | D7: =IF(ROUND(B7,6)=ROUND(C7,6),"Sesuai","Tidak Sesuai") -> Sesuai
A9: This Week
A10: Plan | B10: ='Exe Sum'!J29 -> 0.105605 | C10: ='S-Overall'!P66 -> 0.105605 | D10: =IF(ROUND(B10,6)=ROUND(C10,6),"Sesuai","Tidak Sesuai") -> Sesuai
A11: Aktual | B11: ='Exe Sum'!L29 -> 0.05845 | C11: ='S-Overall'!P64 -> 0.05845 | D11: =IF(ROUND(B11,6)=ROUND(C11,6),"Sesuai","Tidak Sesuai") -> Sesuai
A12: Variance | B12: ='Exe Sum'!M29 -> -0.047155 | C12: =C11-C10 -> -0.047155 | D12: =IF(ROUND(B12,6)=ROUND(C12,6),"Sesuai","Tidak Sesuai") -> Sesuai
A14: To Date (Cummulative)
A15: Plan | B15: ='Exe Sum'!O29 -> 0.85975 | C15: ='S-Overall'!P67 -> 0.85975 | D15: =IF(B15=C15,"Sesuai","Tidak Sesuai") -> Sesuai
A16: Aktual | B16: ='Exe Sum'!Q29 -> 0.8667 | C16: ='S-Overall'!P65 -> 0.8667 | D16: =IF(B16=C16,"Sesuai","Tidak Sesuai") -> Sesuai
A17: Variance | B17: ='Exe Sum'!R29 -> 0.00695 | C17: ='S-Overall'!P70 -> 0.00695 | D17: =IF(ROUND(B17,6)=ROUND(C17,6),"Sesuai","Tidak Sesuai") -> Sesuai

Sheet Appendix B
D1: =TOC!E1 -> PERTAMINA EP
D3: Project Title : | L3: Document Number :
D4: ='Cover Report'!Z1 -> Integrated Management Dashboard Production & Project Zona 13 | L4: ='Cover Report'!Z5 -> W2026I-DNGF-EM-100-PRG-WLY-0012
D5: Document Title: | L5: Appendix B
D6: =TOC!E6 -> Weekly Report
A27: APPENDIX B
A29: MASTER DELIVERABLE REGISTER (MDR)
R268: ELECTRICAL & INSTRUMENTATION ENGINEERING (as of 2 October)
J277: ELECTRICAL & INSTRUMENTATION ENGINEERING (as of 2 October)
AF348: 0.9176 | AG348: 0.8494
AG349: 1
AF355: 0.9121 | AG355: 0.8934
AG356: 0.685

Sheet Overall MDR_
J2: ENGINEERING DOCUMENTS REGISTER
B4: CLIENT | C4: : | D4: PT Pertamina EP | AN4: Rev. No. : | AO4: 0
B5: PROJECT | C5: : | D5: ='Cover Report'!Z1 -> Integrated Management Dashboard Production & Project Zona 13 | AN5: Week No. : | AO5: =BN5 -> 12 | BL5: =HLOOKUP(BN5,$BM$11:$CH$12,2,FALSE) -> 46208 | BM5: Report No. | BN5: ='Cover Report'!Z3 -> 12 | DK5: =BL5 -> 46208 | DL5: Report No. | DM5: =BN5 -> 12
B6: WO Title | C6: : | AN6: Cut-off Date : | AO6: =BL5 -> 46208 | BL6: =(HLOOKUP(BN6,$BM$11:$CH$12,2,FALSE))+1 -> 46202 | BN6: =BN5-1 -> 11 | DK6: =BL6 -> 46202 | DM6: =BN6 -> 11
B7: WO No. | C7: :
BL8: ESTIMATE PLAN CUMULATIVE REV.0 | CK8: ESTIMATE FORECAST CUMULATIVE REV.0 | DK8: ACTUAL CUMULATIVE REV.0
E9: REVISION | F9: WEIGHT FACTOR | H9: Inter-Discipline Review | K9: Rev A | O9: Rev A | S9: Rev 0 | AB9: APPROVED | AG9: PHYSICAL PROGRESS | BD9: Activity | BE9: ACTUAL | BG9: PLAN | BI9: FORECAST
K10: IFR (Issued for Review) | O10: IFR (Issued for Review) | S10: IFD (Issued for Design) | W10: Close Out Report | AE10: Progress Overall | AR10: PAYMENT PROGRESS
A11: Deliverables | H11: 0.05 | K11: 0.25 | O11: 0.5 | S11: 0.75 | W11: 1 | AG11: EACH DELIVERABLE | AN11: OVERALL | AR11: OVERALL | BE11: LAST | BF11: TODATE | BG11: LAST | BH11: TODATE | BI11: LAST | BJ11: TODATE | BN11: 0 | BO11: 1 | BP11: 2 | BQ11: 3 | BR11: 4 | BS11: 5 | BT11: 6 | BU11: 7 | BV11: 8 | BW11: 9 | BX11: 10 | BY11: 11 | BZ11: 12 | CA11: 13 | CB11: 14 | CC11: 15 | CD11: 16 | CE11: 17 | CF11: 18 | CG11: 19 | CH11: 20 | CM11: 0 | CN11: 1 | CO11: 2 | CP11: 3 | CQ11: 4 | CR11: 5 | CS11: 6 | CT11: 7 | CU11: 8 | CV11: 9 | CW11: 10 | CX11: 11 | CY11: 12 | CZ11: 13 | DA11: 14 | DB11: 15 | DC11: 16 | DD11: 17 | DE11: 18 | DF11: 19 | DG11: 20 | DM11: 0 | DN11: 1 | DO11: 2 | DP11: 3 | DQ11: 4 | DR11: 5 | DS11: 6 | DT11: 7 | DU11: 8 | DV11: 9 | DW11: 10 | DX11: 11 | DY11: 12 | DZ11: 13 | EA11: 14 | EB11: 15 | EC11: 16 | ED11: 17 | EE11: 18 | EF11: 19 | EG11: 20
H12: =H11 -> 0.05 | I12: =H11 -> 0.05 | J12: =H11 -> 0.05 | K12: =K11 -> 0.25 | L12: =K11 -> 0.25 | M12: =K11 -> 0.25 | N12: =K11 -> 0.25 | O12: =O11 -> 0.5 | P12: =O11 -> 0.5 | Q12: =O11 -> 0.5 | R12: =O11 -> 0.5 | S12: =S11 -> 0.75 | T12: =S11 -> 0.75 | U12: =S11 -> 0.75 | V12: =S11 -> 0.75 | W12: =W11 -> 1 | X12: =W11 -> 1 | Y12: =W11 -> 1 | Z12: =W11 -> 1 | AA12: =W11 -> 1 | AF12: Doc Impact | AG12: ACTUAL | AJ12: PLAN | AK12: Re-baseline | AL12: VARIANCE PLAN | AM12: VARIANCE Re-baseline | AN12: ACTUAL | AO12: PLAN | AP12: Re-baseline | AQ12: VAR | AR12: LAST WEEK | AS12: THIS WEEK | AT12: TODATE | BM12: 46113 | BN12: =BM12+11 -> 46124 | BO12: =BN12+7 -> 46131 | BP12: =BO12+7 -> 46138 | BQ12: =BP12+7 -> 46145 | BR12: =BQ12+7 -> 46152 | BS12: =BR12+7 -> 46159 | BT12: =BS12+7 -> 46166 | BU12: =BT12+7 -> 46173 | BV12: =BU12+7 -> 46180 | ... CG12: =CF12+7 -> 46257 | CH12: =CG12+8 -> 46265 | CL12: 46113 | CM12: =CL12+12 -> 46125 | CN12: =CM12+6 -> 46131 | CO12: =CN12+7 -> 46138 | CP12: =CO12+7 -> 46145 | CQ12: =CP12+7 -> 46152 | CR12: =CQ12+7 -> 46159 | CS12: =CR12+7 -> 46166 | CT12: =CS12+7 -> 46173 | CU12: =CT12+7 -> 46180 | CV12: =CU12+7 -> 46187 | ... DF12: =DE12+7 -> 46257 | DG12: =DF12+8 -> 46265 | DL12: 46113 | DM12: =DL12+12 -> 46125 | DN12: =DM12+6 -> 46131 | DO12: =DN12+7 -> 46138 | DP12: =DO12+7 -> 46145 | DQ12: =DP12+7 -> 46152 | DR12: =DQ12+7 -> 46159 | DS12: =DR12+7 -> 46166 | DT12: =DS12+7 -> 46173 | DU12: =DT12+7 -> 46180 | DV12: =DU12+7 -> 46187 | ... EF12: =EE12+7 -> 46257 | EG12: =EF12+8 -> 46265
H13: Plan | I13: Recovery | J13: Actual | K13: Plan | L13: Recovery | M13: Actual | N13: Return | O13: Plan | P13: Recovery | Q13: Actual | R13: Return | S13: Plan | T13: Recovery | U13: Actual | V13: Return | W13: Plan | X13: Recovery | Y13: Actual | Z13: Return | AA13: NOTE | AB13: Plan | AC13: Forecast | AD13: Actual | AG13: LAST | AH13: THIS WK | AI13: TODATE | AJ13: TODATE | AK13: TODATE | AL13: TODATE | AN13: TODATE | AO13: TODATE | AP13: TODATE | AQ13: TODATE | AT13: W. U .
A15: OVERALL | F15: =SUBTOTAL(9,F16:F37) -> 1 | AZ15: 0.77735 | BD15: OVERALL | BE15: =SUBTOTAL(9,BE16:BE36) -> 0.8316 | BF15: =SUBTOTAL(9,BF16:BF36) -> 0.8667 | BG15: =SUBTOTAL(9,BG16:BG36) -> 0.754145 | BH15: =SUBTOTAL(9,BH16:BH36) -> 0.85975 | BI15: =SUBTOTAL(9,BI16:BI36) -> 0.0309 | BJ15: =SUBTOTAL(9,BJ16:BJ36) -> 0.0309 | BM15: =SUBTOTAL(9,BM16:BM36) -> 0 | BN15: =SUBTOTAL(9,BN16:BN36) -> 0.063355 | BO15: =SUBTOTAL(9,BO16:BO36) -> 0.100445 | BP15: =SUBTOTAL(9,BP16:BP36) -> 0.171525 | BQ15: =SUBTOTAL(9,BQ16:BQ36) -> 0.21412 | BR15: =SUBTOTAL(9,BR16:BR36) -> 0.26307 | BS15: =SUBTOTAL(9,BS16:BS36) -> 0.38565 | BT15: =SUBTOTAL(9,BT16:BT36) -> 0.473875 | ... CH15: =SUBTOTAL(9,CH16:CH36) -> 1 | CL15: =SUBTOTAL(9,CL16:CL36) -> 0 | CM15: =SUBTOTAL(9,CM16:CM36) -> 0 | CN15: =SUBTOTAL(9,CN16:CN36) -> 0 | CO15: =SUBTOTAL(9,CO16:CO36) -> 0.0309 | CP15: =SUBTOTAL(9,CP16:CP36) -> 0.0309 | CQ15: =SUBTOTAL(9,CQ16:CQ36) -> 0.0309 | CR15: =SUBTOTAL(9,CR16:CR36) -> 0.0309 | CS15: =SUBTOTAL(9,CS16:CS36) -> 0.0309 | ... DG15: =SUBTOTAL(9,DG16:DG36) -> 0.069525 | DL15: =SUBTOTAL(9,DL16:DL36) -> 0 | DM15: =SUBTOTAL(9,DM16:DM36) -> 0.217725 | DN15: =SUBTOTAL(9,DN16:DN36) -> 0.36179 | DO15: =SUBTOTAL(9,DO16:DO36) -> 0.4188 | DP15: =SUBTOTAL(9,DP16:DP36) -> 0.43756 | DQ15: =SUBTOTAL(9,DQ16:DQ36) -> 0.45301 | DR15: =SUBTOTAL(9,DR16:DR36) -> 0.5126 | DS15: =SUBTOTAL(9,DS16:DS36) -> 0.522025 | ... EG15: =SUBTOTAL(9,EG16:EG36) -> 0.8667
A16: 1 | C16: Analisis Kebutuhan | F16: =SUBTOTAL(9,F17:F18) -> 0.0927 | AZ16: 0.0927 | BD16: 1 | BE16: =SUBTOTAL(9,BE17:BE18) -> 0.0927 | BF16: =SUBTOTAL(9,BF17:BF18) -> 0.0927 | BG16: =SUBTOTAL(9,BG17:BG18) -> 0.0927 | BH16: =SUBTOTAL(9,BH17:BH18) -> 0.0927 | BI16: =SUBTOTAL(9,BI17:BI18) -> 0 | BJ16: =SUBTOTAL(9,BJ17:BJ18) -> 0 | BM16: =SUBTOTAL(9,BM17:BM18) -> 0 | BN16: =SUBTOTAL(9,BN17:BN18) -> 0.04635 | BO16: =SUBTOTAL(9,BO17:BO18) -> 0.069525 | BP16: =SUBTOTAL(9,BP17:BP18) -> 0.0927 | BQ16: =SUBTOTAL(9,BQ17:BQ18) -> 0.0927 | BR16: =SUBTOTAL(9,BR17:BR18) -> 0.0927 | BS16: =SUBTOTAL(9,BS17:BS18) -> 0.0927 | BT16: =SUBTOTAL(9,BT17:BT18) -> 0.0927 | ... CH16: =SUBTOTAL(9,CH17:CH18) -> 0.0927 | CL16: =SUBTOTAL(9,CL17:CL18) -> 0 | CM16: =SUBTOTAL(9,CM17:CM18) -> 0 | CN16: =SUBTOTAL(9,CN17:CN18) -> 0 | CO16: =SUBTOTAL(9,CO17:CO18) -> 0 | CP16: =SUBTOTAL(9,CP17:CP18) -> 0 | CQ16: =SUBTOTAL(9,CQ17:CQ18) -> 0 | CR16: =SUBTOTAL(9,CR17:CR18) -> 0 | CS16: =SUBTOTAL(9,CS17:CS18) -> 0 | ... DG16: =SUBTOTAL(9,DG17:DG18) -> 0 | DL16: =SUBTOTAL(9,DL17:DL18) -> 0 | DM16: =SUBTOTAL(9,DM17:DM18) -> 0.069525 | DN16: =SUBTOTAL(9,DN17:DN18) -> 0.0927 | DO16: =SUBTOTAL(9,DO17:DO18) -> 0.0927 | DP16: =SUBTOTAL(9,DP17:DP18) -> 0.0927 | DQ16: =SUBTOTAL(9,DQ17:DQ18) -> 0.0927 | DR16: =SUBTOTAL(9,DR17:DR18) -> 0.0927 | DS16: =SUBTOTAL(9,DS17:DS18) -> 0.0927 | ... EG16: =SUBTOTAL(9,EG17:EG18) -> 0.0927
A17: 1.a | B17: W2026I-DNGF-EM-100-PRD-SPC-0001 | C17: Dokumentasi BRD | F17: 0.04 | H17: 46113 | J17: 46113 | K17: =H17+((O17-H17)*0.5) -> 46118 | M17: 46114 | O17: =H17+((W17-H17)*0.5) -> 46123 | Q17: 46118 | S17: =O17+((W17-O17)*0.5) -> 46128 | U17: 46125 | W17: 46133 | Y17: 46131 | AE17: =AN17 -> 0.04 | AG17: =IF(AND($Y17<>0,$Y17<=$BL$6),$Y$12,IF(AND($U17<>0,$U17<=$BL$6),$U$12,IF(AND($Q17<>0,$Q17<=$BL$6),$Q$12,IF(AND($M17<>0,$M17<=$BL$6),$M$12,IF(AND($J17<>0,$J17<=$BL$6),$J$12,0))))) -> 1 | AH17: =AI17-AG17 -> 0 | AI17: =IF(AND($Y17<>0,$Y17<=$BL$5),$Y$12,IF(AND($U17<>0,$U17<=$BL$5),$U$12,IF(AND($Q17<>0,$Q17<=$BL$5),$Q$12,IF(AND($M17<>0,$M17<=$BL$5),$M$12,IF(AND($J17<>0,$J17<=$BL$5),$J$12,0))))) -> 1 | AJ17: =IF(AND($W17<>0,$W17<=$BL$5),$W$12,IF(AND($S17<>0,$S17<=$BL$5),$S$12,IF(AND(#REF!<>0,#REF!<=$BL$5),$O$12,IF(AND($K17<>0,$K17<=$BL$5),$K$12,IF(AND($H17<>0,$H17<=$BL$5),$H$12,0))))) -> 1 | AK17: =IF(AND($X17<>0,$X17<=$BL$5),$X$12,IF(AND($T17<>0,$T17<=$BL$5),$T$12,IF(AND($P17<>0,$P17<=$BL$5),$P$12,IF(AND($L17<>0,$L17<=$BL$5),$L$12,IF(AND($I17<>0,$I17<=$BL$5),$I$12,0))))) -> 0 | AL17: =AI17-AJ17 -> 0 | AM17: =AI17-AK17 -> 1 | AN17: =AI17*F17 -> 0.04 | AO17: =AJ17*F17 -> 0.04 | AP17: =AK17*F17 -> 0 | AQ17: =AN17-AO17 -> 0 | AZ17: 0.04 | BD17: 1.a | BE17: =AG17*F17 -> 0.04 | BF17: =AI17*F17 -> 0.04 | BG17: =IF(AND($W17<>0,$W17<=$BL$6),$W$12,IF(AND($S17<>0,$S17<=$BL$6),$S$12,IF(AND($O17<>0,$O17<=$BL$6),$O$12,IF(AND($K17<>0,$K17<=$BL$6),$K$12,IF(AND($H17<>0,$H17<=$BL$6),$H$12,0)))))*$F17 -> 0.04 | BH17: =IF(AND($W17<>0,$W17<=$BL$5),$W$12,IF(AND($S17<>0,$S17<=$BL$5),$S$12,IF(AND($O17<>0,$O17<=$BL$5),$O$12,IF(AND($K17<>0,$K17<=$BL$5),$K$12,IF(AND($H17<>0,$H17<=$BL$5),$H$12,0)))))*$F17 -> 0.04 | BI17: =IF(AND($X17<>0,$X17<=$BL$6),$X$12,IF(AND($T17<>0,$T17<=$BL$6),$T$12,IF(AND($P17<>0,$P17<=$BL$6),$P$12,IF(AND($L17<>0,$L17<=$BL$6),$L$12,IF(AND($I17<>0,$I17<=$BL$6),$I$12,0)))))*$F17 -> 0 | BJ17: =IF(AND($X17<>0,$X17<=$BL$5),$X$12,IF(AND($T17<>0,$T17<=$BL$5),$T$12,IF(AND($P17<>0,$P17<=$BL$5),$P$12,IF(AND($L17<>0,$L17<=$BL$5),$L$12,IF(AND($I17<>0,$I17<=$BL$5),$I$12,0)))))*$F17 -> 0 | BM17: 0 | BN17: =IF(AND($W17<>0,$W17<=BN$12),$W$12*$F17,IF(AND($S17<>0,$S17<=BN$12),$S$12*$F17,IF(AND($O17<>0,$O17<=BN$12),$O$12*$F17,IF(AND($K17<>0,$K17<=BN$12),$K$12*$F17,IF(AND($H17<>0,$H17<=BN$12),$H$12*$F17,0))))) -> 0.02 | BO17: =IF(AND($W17<>0,$W17<=BO$12),$W$12*$F17,IF(AND($S17<>0,$S17<=BO$12),$S$12*$F17,IF(AND($O17<>0,$O17<=BO$12),$O$12*$F17,IF(AND($K17<>0,$K17<=BO$12),$K$12*$F17,IF(AND($H17<>0,$H17<=BO$12),$H$12*$F17,0))))) -> 0.03 | BP17: =IF(AND($W17<>0,$W17<=BP$12),$W$12*$F17,IF(AND($S17<>0,$S17<=BP$12),$S$12*$F17,IF(AND($O17<>0,$O17<=BP$12),$O$12*$F17,IF(AND($K17<>0,$K17<=BP$12),$K$12*$F17,IF(AND($H17<>0,$H17<=BP$12),$H$12*$F17,0))))) -> 0.04 | BQ17: =IF(AND($W17<>0,$W17<=BQ$12),$W$12*$F17,IF(AND($S17<>0,$S17<=BQ$12),$S$12*$F17,IF(AND($O17<>0,$O17<=BQ$12),$O$12*$F17,IF(AND($K17<>0,$K17<=BQ$12),$K$12*$F17,IF(AND($H17<>0,$H17<=BQ$12),$H$12*$F17,0))))) -> 0.04 | BR17: =IF(AND($W17<>0,$W17<=BR$12),$W$12*$F17,IF(AND($S17<>0,$S17<=BR$12),$S$12*$F17,IF(AND($O17<>0,$O17<=BR$12),$O$12*$F17,IF(AND($K17<>0,$K17<=BR$12),$K$12*$F17,IF(AND($H17<>0,$H17<=BR$12),$H$12*$F17,0))))) -> 0.04 | BS17: =IF(AND($W17<>0,$W17<=BS$12),$W$12*$F17,IF(AND($S17<>0,$S17<=BS$12),$S$12*$F17,IF(AND($O17<>0,$O17<=BS$12),$O$12*$F17,IF(AND($K17<>0,$K17<=BS$12),$K$12*$F17,IF(AND($H17<>0,$H17<=BS$12),$H$12*$F17,0))))) -> 0.04 | BT17: =IF(AND($W17<>0,$W17<=BT$12),$W$12*$F17,IF(AND($S17<>0,$S17<=BT$12),$S$12*$F17,IF(AND($O17<>0,$O17<=BT$12),$O$12*$F17,IF(AND($K17<>0,$K17<=BT$12),$K$12*$F17,IF(AND($H17<>0,$H17<=BT$12),$H$12*$F17,0))))) -> 0.04 | BU17: =IF(AND($W17<>0,$W17<=BU$12),$W$12*$F17,IF(AND($S17<>0,$S17<=BU$12),$S$12*$F17,IF(AND($O17<>0,$O17<=BU$12),$O$12*$F17,IF(AND($K17<>0,$K17<=BU$12),$K$12*$F17,IF(AND($H17<>0,$H17<=BU$12),$H$12*$F17,0))))) -> 0.04 | ... CH17: =IF(AND($W17<>0,$W17<=CH$12),$W$12*$F17,IF(AND($S17<>0,$S17<=CH$12),$S$12*$F17,IF(AND($O17<>0,$O17<=CH$12),$O$12*$F17,IF(AND($K17<>0,$K17<=CH$12),$K$12*$F17,IF(AND($H17<>0,$H17<=CH$12),$H$12*$F17,0))))) -> 0.04 | CL17: 0 | CM17: =IF(AND($X17<>0,$X17<=CM$12),$X$12*$F17,IF(AND($T17<>0,$T17<=CM$12),$T$12*$F17,IF(AND($P17<>0,$P17<=CM$12),$P$12*$F17,IF(AND($L17<>0,$L17<=CM$12),$L$12*$F17,IF(AND($I17<>0,$I17<=CM$12),$I$12*$F17,0))))) -> 0 | CN17: =IF(AND($X17<>0,$X17<=CN$12),$X$12*$F17,IF(AND($T17<>0,$T17<=CN$12),$T$12*$F17,IF(AND($P17<>0,$P17<=CN$12),$P$12*$F17,IF(AND($L17<>0,$L17<=CN$12),$L$12*$F17,IF(AND($I17<>0,$I17<=CN$12),$I$12*$F17,0))))) -> 0 | CO17: =IF(AND($X17<>0,$X17<=CO$12),$X$12*$F17,IF(AND($T17<>0,$T17<=CO$12),$T$12*$F17,IF(AND($P17<>0,$P17<=CO$12),$P$12*$F17,IF(AND($L17<>0,$L17<=CO$12),$L$12*$F17,IF(AND($I17<>0,$I17<=CO$12),$I$12*$F17,0))))) -> 0 | CP17: =IF(AND($X17<>0,$X17<=CP$12),$X$12*$F17,IF(AND($T17<>0,$T17<=CP$12),$T$12*$F17,IF(AND($P17<>0,$P17<=CP$12),$P$12*$F17,IF(AND($L17<>0,$L17<=CP$12),$L$12*$F17,IF(AND($I17<>0,$I17<=CP$12),$I$12*$F17,0))))) -> 0 | CQ17: =IF(AND($X17<>0,$X17<=CQ$12),$X$12*$F17,IF(AND($T17<>0,$T17<=CQ$12),$T$12*$F17,IF(AND($P17<>0,$P17<=CQ$12),$P$12*$F17,IF(AND($L17<>0,$L17<=CQ$12),$L$12*$F17,IF(AND($I17<>0,$I17<=CQ$12),$I$12*$F17,0))))) -> 0 | CR17: =IF(AND($X17<>0,$X17<=CR$12),$X$12*$F17,IF(AND($T17<>0,$T17<=CR$12),$T$12*$F17,IF(AND($P17<>0,$P17<=CR$12),$P$12*$F17,IF(AND($L17<>0,$L17<=CR$12),$L$12*$F17,IF(AND($I17<>0,$I17<=CR$12),$I$12*$F17,0))))) -> 0 | CS17: =IF(AND($X17<>0,$X17<=CS$12),$X$12*$F17,IF(AND($T17<>0,$T17<=CS$12),$T$12*$F17,IF(AND($P17<>0,$P17<=CS$12),$P$12*$F17,IF(AND($L17<>0,$L17<=CS$12),$L$12*$F17,IF(AND($I17<>0,$I17<=CS$12),$I$12*$F17,0))))) -> 0 | CT17: =IF(AND($X17<>0,$X17<=CT$12),$X$12*$F17,IF(AND($T17<>0,$T17<=CT$12),$T$12*$F17,IF(AND($P17<>0,$P17<=CT$12),$P$12*$F17,IF(AND($L17<>0,$L17<=CT$12),$L$12*$F17,IF(AND($I17<>0,$I17<=CT$12),$I$12*$F17,0))))) -> 0 | ... DG17: =IF(AND($X17<>0,$X17<=DG$12),$X$12*$F17,IF(AND($T17<>0,$T17<=DG$12),$T$12*$F17,IF(AND($P17<>0,$P17<=DG$12),$P$12*$F17,IF(AND($L17<>0,$L17<=DG$12),$L$12*$F17,IF(AND($I17<>0,$I17<=DG$12),$I$12*$F17,0))))) -> 0 | DL17: 0 | DM17: =IF(AND($Y17<>0,$Y17<=DM$12),$Y$12*$F17,IF(AND($U17<>0,$U17<=DM$12),$U$12*$F17,IF(AND($Q17<>0,$Q17<=DM$12),$Q$12*$F17,IF(AND($M17<>0,$M17<=DM$12),$M$12*$F17,IF(AND($J17<>0,$J17<=DM$12),$J$12*$F17,0))))) -> 0.03 | DN17: =IF(AND($Y17<>0,$Y17<=DN$12),$Y$12*$F17,IF(AND($U17<>0,$U17<=DN$12),$U$12*$F17,IF(AND($Q17<>0,$Q17<=DN$12),$Q$12*$F17,IF(AND($M17<>0,$M17<=DN$12),$M$12*$F17,IF(AND($J17<>0,$J17<=DN$12),$J$12*$F17,0))))) -> 0.04 | DO17: =IF(AND($Y17<>0,$Y17<=DO$12),$Y$12*$F17,IF(AND($U17<>0,$U17<=DO$12),$U$12*$F17,IF(AND($Q17<>0,$Q17<=DO$12),$Q$12*$F17,IF(AND($M17<>0,$M17<=DO$12),$M$12*$F17,IF(AND($J17<>0,$J17<=DO$12),$J$12*$F17,0))))) -> 0.04 | DP17: =IF(AND($Y17<>0,$Y17<=DP$12),$Y$12*$F17,IF(AND($U17<>0,$U17<=DP$12),$U$12*$F17,IF(AND($Q17<>0,$Q17<=DP$12),$Q$12*$F17,IF(AND($M17<>0,$M17<=DP$12),$M$12*$F17,IF(AND($J17<>0,$J17<=DP$12),$J$12*$F17,0))))) -> 0.04 | DQ17: =IF(AND($Y17<>0,$Y17<=DQ$12),$Y$12*$F17,IF(AND($U17<>0,$U17<=DQ$12),$U$12*$F17,IF(AND($Q17<>0,$Q17<=DQ$12),$Q$12*$F17,IF(AND($M17<>0,$M17<=DQ$12),$M$12*$F17,IF(AND($J17<>0,$J17<=DQ$12),$J$12*$F17,0))))) -> 0.04 | DR17: =IF(AND($Y17<>0,$Y17<=DR$12),$Y$12*$F17,IF(AND($U17<>0,$U17<=DR$12),$U$12*$F17,IF(AND($Q17<>0,$Q17<=DR$12),$Q$12*$F17,IF(AND($M17<>0,$M17<=DR$12),$M$12*$F17,IF(AND($J17<>0,$J17<=DR$12),$J$12*$F17,0))))) -> 0.04 | DS17: =IF(AND($Y17<>0,$Y17<=DS$12),$Y$12*$F17,IF(AND($U17<>0,$U17<=DS$12),$U$12*$F17,IF(AND($Q17<>0,$Q17<=DS$12),$Q$12*$F17,IF(AND($M17<>0,$M17<=DS$12),$M$12*$F17,IF(AND($J17<>0,$J17<=DS$12),$J$12*$F17,0))))) -> 0.04 | DT17: =IF(AND($Y17<>0,$Y17<=DT$12),$Y$12*$F17,IF(AND($U17<>0,$U17<=DT$12),$U$12*$F17,IF(AND($Q17<>0,$Q17<=DT$12),$Q$12*$F17,IF(AND($M17<>0,$M17<=DT$12),$M$12*$F17,IF(AND($J17<>0,$J17<=DT$12),$J$12*$F17,0))))) -> 0.04 | ... EG17: =IF(AND($Y17<>0,$Y17<=EG$12),$Y$12*$F17,IF(AND($U17<>0,$U17<=EG$12),$U$12*$F17,IF(AND($Q17<>0,$Q17<=EG$12),$Q$12*$F17,IF(AND($M17<>0,$M17<=EG$12),$M$12*$F17,IF(AND($J17<>0,$J17<=EG$12),$J$12*$F17,0))))) -> 0.04
A18: 1.b | B18: W2026I-DNGF-EM-100-PRD-SPC-0002 | C18: Dokumentasi Awal Hasil Wawancara | F18: 0.0527 | H18: 46113 | J18: 46113 | K18: =H18+((O18-H18)*0.5) -> 46118 | M18: 46114 | O18: =H18+((W18-H18)*0.5) -> 46123 | Q18: 46118 | S18: =O18+((W18-O18)*0.5) -> 46128 | U18: 46125 | W18: 46133 | Y18: 46131 | AE18: =AN18 -> 0.0527 | AG18: =IF(AND($Y18<>0,$Y18<=$BL$6),$Y$12,IF(AND($U18<>0,$U18<=$BL$6),$U$12,IF(AND($Q18<>0,$Q18<=$BL$6),$Q$12,IF(AND($M18<>0,$M18<=$BL$6),$M$12,IF(AND($J18<>0,$J18<=$BL$6),$J$12,0))))) -> 1 | AH18: =AI18-AG18 -> 0 | AI18: =IF(AND($Y18<>0,$Y18<=$BL$5),$Y$12,IF(AND($U18<>0,$U18<=$BL$5),$U$12,IF(AND($Q18<>0,$Q18<=$BL$5),$Q$12,IF(AND($M18<>0,$M18<=$BL$5),$M$12,IF(AND($J18<>0,$J18<=$BL$5),$J$12,0))))) -> 1 | AJ18: =IF(AND($W18<>0,$W18<=$BL$5),$W$12,IF(AND($S18<>0,$S18<=$BL$5),$S$12,IF(AND($O18<>0,$O18<=$BL$5),$O$12,IF(AND($K18<>0,$K18<=$BL$5),$K$12,IF(AND($H18<>0,$H18<=$BL$5),$H$12,0))))) -> 1 | AK18: =IF(AND($X18<>0,$X18<=$BL$5),$X$12,IF(AND($T18<>0,$T18<=$BL$5),$T$12,IF(AND($P18<>0,$P18<=$BL$5),$P$12,IF(AND($L18<>0,$L18<=$BL$5),$L$12,IF(AND($I18<>0,$I18<=$BL$5),$I$12,0))))) -> 0 | AL18: =AI18-AJ18 -> 0 | AM18: =AI18-AK18 -> 1 | AN18: =AI18*F18 -> 0.0527 | AO18: =AJ18*F18 -> 0.0527 | AP18: =AK18*F18 -> 0 | AQ18: =AN18-AO18 -> 0 | AZ18: 0.0527 | BD18: 1.b | BE18: =AG18*F18 -> 0.0527 | BF18: =AI18*F18 -> 0.0527 | BG18: =IF(AND($W18<>0,$W18<=$BL$6),$W$12,IF(AND($S18<>0,$S18<=$BL$6),$S$12,IF(AND($O18<>0,$O18<=$BL$6),$O$12,IF(AND($K18<>0,$K18<=$BL$6),$K$12,IF(AND($H18<>0,$H18<=$BL$6),$H$12,0)))))*$F18 -> 0.0527 | BH18: =IF(AND($W18<>0,$W18<=$BL$5),$W$12,IF(AND($S18<>0,$S18<=$BL$5),$S$12,IF(AND($O18<>0,$O18<=$BL$5),$O$12,IF(AND($K18<>0,$K18<=$BL$5),$K$12,IF(AND($H18<>0,$H18<=$BL$5),$H$12,0)))))*$F18 -> 0.0527 | BI18: =IF(AND($X18<>0,$X18<=$BL$6),$X$12,IF(AND($T18<>0,$T18<=$BL$6),$T$12,IF(AND($P18<>0,$P18<=$BL$6),$P$12,IF(AND($L18<>0,$L18<=$BL$6),$L$12,IF(AND($I18<>0,$I18<=$BL$6),$I$12,0)))))*$F18 -> 0 | BJ18: =IF(AND($X18<>0,$X18<=$BL$5),$X$12,IF(AND($T18<>0,$T18<=$BL$5),$T$12,IF(AND($P18<>0,$P18<=$BL$5),$P$12,IF(AND($L18<>0,$L18<=$BL$5),$L$12,IF(AND($I18<>0,$I18<=$BL$5),$I$12,0)))))*$F18 -> 0 | BM18: 0 | BN18: =IF(AND($W18<>0,$W18<=BN$12),$W$12*$F18,IF(AND($S18<>0,$S18<=BN$12),$S$12*$F18,IF(AND($O18<>0,$O18<=BN$12),$O$12*$F18,IF(AND($K18<>0,$K18<=BN$12),$K$12*$F18,IF(AND($H18<>0,$H18<=BN$12),$H$12*$F18,0))))) -> 0.02635 | BO18: =IF(AND($W18<>0,$W18<=BO$12),$W$12*$F18,IF(AND($S18<>0,$S18<=BO$12),$S$12*$F18,IF(AND($O18<>0,$O18<=BO$12),$O$12*$F18,IF(AND($K18<>0,$K18<=BO$12),$K$12*$F18,IF(AND($H18<>0,$H18<=BO$12),$H$12*$F18,0))))) -> 0.039525 | BP18: =IF(AND($W18<>0,$W18<=BP$12),$W$12*$F18,IF(AND($S18<>0,$S18<=BP$12),$S$12*$F18,IF(AND($O18<>0,$O18<=BP$12),$O$12*$F18,IF(AND($K18<>0,$K18<=BP$12),$K$12*$F18,IF(AND($H18<>0,$H18<=BP$12),$H$12*$F18,0))))) -> 0.0527 | BQ18: =IF(AND($W18<>0,$W18<=BQ$12),$W$12*$F18,IF(AND($S18<>0,$S18<=BQ$12),$S$12*$F18,IF(AND($O18<>0,$O18<=BQ$12),$O$12*$F18,IF(AND($K18<>0,$K18<=BQ$12),$K$12*$F18,IF(AND($H18<>0,$H18<=BQ$12),$H$12*$F18,0))))) -> 0.0527 | BR18: =IF(AND($W18<>0,$W18<=BR$12),$W$12*$F18,IF(AND($S18<>0,$S18<=BR$12),$S$12*$F18,IF(AND($O18<>0,$O18<=BR$12),$O$12*$F18,IF(AND($K18<>0,$K18<=BR$12),$K$12*$F18,IF(AND($H18<>0,$H18<=BR$12),$H$12*$F18,0))))) -> 0.0527 | BS18: =IF(AND($W18<>0,$W18<=BS$12),$W$12*$F18,IF(AND($S18<>0,$S18<=BS$12),$S$12*$F18,IF(AND($O18<>0,$O18<=BS$12),$O$12*$F18,IF(AND($K18<>0,$K18<=BS$12),$K$12*$F18,IF(AND($H18<>0,$H18<=BS$12),$H$12*$F18,0))))) -> 0.0527 | BT18: =IF(AND($W18<>0,$W18<=BT$12),$W$12*$F18,IF(AND($S18<>0,$S18<=BT$12),$S$12*$F18,IF(AND($O18<>0,$O18<=BT$12),$O$12*$F18,IF(AND($K18<>0,$K18<=BT$12),$K$12*$F18,IF(AND($H18<>0,$H18<=BT$12),$H$12*$F18,0))))) -> 0.0527 | BU18: =IF(AND($W18<>0,$W18<=BU$12),$W$12*$F18,IF(AND($S18<>0,$S18<=BU$12),$S$12*$F18,IF(AND($O18<>0,$O18<=BU$12),$O$12*$F18,IF(AND($K18<>0,$K18<=BU$12),$K$12*$F18,IF(AND($H18<>0,$H18<=BU$12),$H$12*$F18,0))))) -> 0.0527 | ... CH18: =IF(AND($W18<>0,$W18<=CH$12),$W$12*$F18,IF(AND($S18<>0,$S18<=CH$12),$S$12*$F18,IF(AND($O18<>0,$O18<=CH$12),$O$12*$F18,IF(AND($K18<>0,$K18<=CH$12),$K$12*$F18,IF(AND($H18<>0,$H18<=CH$12),$H$12*$F18,0))))) -> 0.0527 | CL18: 0 | CM18: =IF(AND($X18<>0,$X18<=CM$12),$X$12*$F18,IF(AND($T18<>0,$T18<=CM$12),$T$12*$F18,IF(AND($P18<>0,$P18<=CM$12),$P$12*$F18,IF(AND($L18<>0,$L18<=CM$12),$L$12*$F18,IF(AND($I18<>0,$I18<=CM$12),$I$12*$F18,0))))) -> 0 | CN18: =IF(AND($X18<>0,$X18<=CN$12),$X$12*$F18,IF(AND($T18<>0,$T18<=CN$12),$T$12*$F18,IF(AND($P18<>0,$P18<=CN$12),$P$12*$F18,IF(AND($L18<>0,$L18<=CN$12),$L$12*$F18,IF(AND($I18<>0,$I18<=CN$12),$I$12*$F18,0))))) -> 0 | CO18: =IF(AND($X18<>0,$X18<=CO$12),$X$12*$F18,IF(AND($T18<>0,$T18<=CO$12),$T$12*$F18,IF(AND($P18<>0,$P18<=CO$12),$P$12*$F18,IF(AND($L18<>0,$L18<=CO$12),$L$12*$F18,IF(AND($I18<>0,$I18<=CO$12),$I$12*$F18,0))))) -> 0 | CP18: =IF(AND($X18<>0,$X18<=CP$12),$X$12*$F18,IF(AND($T18<>0,$T18<=CP$12),$T$12*$F18,IF(AND($P18<>0,$P18<=CP$12),$P$12*$F18,IF(AND($L18<>0,$L18<=CP$12),$L$12*$F18,IF(AND($I18<>0,$I18<=CP$12),$I$12*$F18,0))))) -> 0 | CQ18: =IF(AND($X18<>0,$X18<=CQ$12),$X$12*$F18,IF(AND($T18<>0,$T18<=CQ$12),$T$12*$F18,IF(AND($P18<>0,$P18<=CQ$12),$P$12*$F18,IF(AND($L18<>0,$L18<=CQ$12),$L$12*$F18,IF(AND($I18<>0,$I18<=CQ$12),$I$12*$F18,0))))) -> 0 | CR18: =IF(AND($X18<>0,$X18<=CR$12),$X$12*$F18,IF(AND($T18<>0,$T18<=CR$12),$T$12*$F18,IF(AND($P18<>0,$P18<=CR$12),$P$12*$F18,IF(AND($L18<>0,$L18<=CR$12),$L$12*$F18,IF(AND($I18<>0,$I18<=CR$12),$I$12*$F18,0))))) -> 0 | CS18: =IF(AND($X18<>0,$X18<=CS$12),$X$12*$F18,IF(AND($T18<>0,$T18<=CS$12),$T$12*$F18,IF(AND($P18<>0,$P18<=CS$12),$P$12*$F18,IF(AND($L18<>0,$L18<=CS$12),$L$12*$F18,IF(AND($I18<>0,$I18<=CS$12),$I$12*$F18,0))))) -> 0 | CT18: =IF(AND($X18<>0,$X18<=CT$12),$X$12*$F18,IF(AND($T18<>0,$T18<=CT$12),$T$12*$F18,IF(AND($P18<>0,$P18<=CT$12),$P$12*$F18,IF(AND($L18<>0,$L18<=CT$12),$L$12*$F18,IF(AND($I18<>0,$I18<=CT$12),$I$12*$F18,0))))) -> 0 | ... DG18: =IF(AND($X18<>0,$X18<=DG$12),$X$12*$F18,IF(AND($T18<>0,$T18<=DG$12),$T$12*$F18,IF(AND($P18<>0,$P18<=DG$12),$P$12*$F18,IF(AND($L18<>0,$L18<=DG$12),$L$12*$F18,IF(AND($I18<>0,$I18<=DG$12),$I$12*$F18,0))))) -> 0 | DL18: 0 | DM18: =IF(AND($Y18<>0,$Y18<=DM$12),$Y$12*$F18,IF(AND($U18<>0,$U18<=DM$12),$U$12*$F18,IF(AND($Q18<>0,$Q18<=DM$12),$Q$12*$F18,IF(AND($M18<>0,$M18<=DM$12),$M$12*$F18,IF(AND($J18<>0,$J18<=DM$12),$J$12*$F18,0))))) -> 0.039525 | DN18: =IF(AND($Y18<>0,$Y18<=DN$12),$Y$12*$F18,IF(AND($U18<>0,$U18<=DN$12),$U$12*$F18,IF(AND($Q18<>0,$Q18<=DN$12),$Q$12*$F18,IF(AND($M18<>0,$M18<=DN$12),$M$12*$F18,IF(AND($J18<>0,$J18<=DN$12),$J$12*$F18,0))))) -> 0.0527 | DO18: =IF(AND($Y18<>0,$Y18<=DO$12),$Y$12*$F18,IF(AND($U18<>0,$U18<=DO$12),$U$12*$F18,IF(AND($Q18<>0,$Q18<=DO$12),$Q$12*$F18,IF(AND($M18<>0,$M18<=DO$12),$M$12*$F18,IF(AND($J18<>0,$J18<=DO$12),$J$12*$F18,0))))) -> 0.0527 | DP18: =IF(AND($Y18<>0,$Y18<=DP$12),$Y$12*$F18,IF(AND($U18<>0,$U18<=DP$12),$U$12*$F18,IF(AND($Q18<>0,$Q18<=DP$12),$Q$12*$F18,IF(AND($M18<>0,$M18<=DP$12),$M$12*$F18,IF(AND($J18<>0,$J18<=DP$12),$J$12*$F18,0))))) -> 0.0527 | DQ18: =IF(AND($Y18<>0,$Y18<=DQ$12),$Y$12*$F18,IF(AND($U18<>0,$U18<=DQ$12),$U$12*$F18,IF(AND($Q18<>0,$Q18<=DQ$12),$Q$12*$F18,IF(AND($M18<>0,$M18<=DQ$12),$M$12*$F18,IF(AND($J18<>0,$J18<=DQ$12),$J$12*$F18,0))))) -> 0.0527 | DR18: =IF(AND($Y18<>0,$Y18<=DR$12),$Y$12*$F18,IF(AND($U18<>0,$U18<=DR$12),$U$12*$F18,IF(AND($Q18<>0,$Q18<=DR$12),$Q$12*$F18,IF(AND($M18<>0,$M18<=DR$12),$M$12*$F18,IF(AND($J18<>0,$J18<=DR$12),$J$12*$F18,0))))) -> 0.0527 | DS18: =IF(AND($Y18<>0,$Y18<=DS$12),$Y$12*$F18,IF(AND($U18<>0,$U18<=DS$12),$U$12*$F18,IF(AND($Q18<>0,$Q18<=DS$12),$Q$12*$F18,IF(AND($M18<>0,$M18<=DS$12),$M$12*$F18,IF(AND($J18<>0,$J18<=DS$12),$J$12*$F18,0))))) -> 0.0527 | DT18: =IF(AND($Y18<>0,$Y18<=DT$12),$Y$12*$F18,IF(AND($U18<>0,$U18<=DT$12),$U$12*$F18,IF(AND($Q18<>0,$Q18<=DT$12),$Q$12*$F18,IF(AND($M18<>0,$M18<=DT$12),$M$12*$F18,IF(AND($J18<>0,$J18<=DT$12),$J$12*$F18,0))))) -> 0.0527 | ... EG18: =IF(AND($Y18<>0,$Y18<=EG$12),$Y$12*$F18,IF(AND($U18<>0,$U18<=EG$12),$U$12*$F18,IF(AND($Q18<>0,$Q18<=EG$12),$Q$12*$F18,IF(AND($M18<>0,$M18<=EG$12),$M$12*$F18,IF(AND($J18<>0,$J18<=EG$12),$J$12*$F18,0))))) -> 0.0527
A19: 2 | C19: Pengadaan | F19: =SUBTOTAL(9,F20) -> 0.0515 | AZ19: 0 | BD19: 2 | BE19: =SUBTOTAL(9,BE20) -> 0 | BF19: =SUBTOTAL(9,BF20) -> 0 | BG19: =SUBTOTAL(9,BG20) -> 0.0515 | BH19: =SUBTOTAL(9,BH20) -> 0.0515 | BI19: =SUBTOTAL(9,BI20) -> 0 | BJ19: =SUBTOTAL(9,BJ20) -> 0 | BM19: =SUBTOTAL(9,BM20) -> 0 | BN19: =SUBTOTAL(9,BN20) -> 0 | BO19: =SUBTOTAL(9,BO20) -> 0 | BP19: =SUBTOTAL(9,BP20) -> 0 | BQ19: =SUBTOTAL(9,BQ20) -> 0 | BR19: =SUBTOTAL(9,BR20) -> 0 | BS19: =SUBTOTAL(9,BS20) -> 0.002575 | BT19: =SUBTOTAL(9,BT20) -> 0.02575 | ... CH19: =SUBTOTAL(9,CH20) -> 0.0515 | CL19: =SUBTOTAL(9,CL20) -> 0 | CM19: =SUBTOTAL(9,CM20) -> 0 | CN19: =SUBTOTAL(9,CN20) -> 0 | CO19: =SUBTOTAL(9,CO20) -> 0 | CP19: =SUBTOTAL(9,CP20) -> 0 | CQ19: =SUBTOTAL(9,CQ20) -> 0 | CR19: =SUBTOTAL(9,CR20) -> 0 | CS19: =SUBTOTAL(9,CS20) -> 0 | ... DG19: =SUBTOTAL(9,DG20) -> 0.038625 | DL19: =SUBTOTAL(9,DL20) -> 0 | DM19: =SUBTOTAL(9,DM20) -> 0 | DN19: =SUBTOTAL(9,DN20) -> 0 | DO19: =SUBTOTAL(9,DO20) -> 0 | DP19: =SUBTOTAL(9,DP20) -> 0 | DQ19: =SUBTOTAL(9,DQ20) -> 0 | DR19: =SUBTOTAL(9,DR20) -> 0 | DS19: =SUBTOTAL(9,DS20) -> 0 | ... EG19: =SUBTOTAL(9,EG20) -> 0
A20: 2.a | C20: Pengadaan Hardware | F20: 0.0515 | H20: 46159 | I20: 46210 | K20: =H20+((O20-H20)*0.5) -> 46162.5 | L20: 46210 | O20: =H20+((W20-H20)*0.5) -> 46166 | P20: 46210 | S20: =O20+((W20-O20)*0.5) -> 46169.5 | T20: 46210 | W20: 46173 | AE20: =AN20 -> 0 | AG20: =IF(AND($Y20<>0,$Y20<=$BL$6),$Y$12,IF(AND($U20<>0,$U20<=$BL$6),$U$12,IF(AND($Q20<>0,$Q20<=$BL$6),$Q$12,IF(AND($M20<>0,$M20<=$BL$6),$M$12,IF(AND($J20<>0,$J20<=$BL$6),$J$12,0))))) -> 0 | AH20: =AI20-AG20 -> 0 | AI20: =IF(AND($Y20<>0,$Y20<=$BL$5),$Y$12,IF(AND($U20<>0,$U20<=$BL$5),$U$12,IF(AND($Q20<>0,$Q20<=$BL$5),$Q$12,IF(AND($M20<>0,$M20<=$BL$5),$M$12,IF(AND($J20<>0,$J20<=$BL$5),$J$12,0))))) -> 0 | AJ20: =IF(AND($W20<>0,$W20<=$BL$5),$W$12,IF(AND($S20<>0,$S20<=$BL$5),$S$12,IF(AND($O20<>0,$O20<=$BL$5),$O$12,IF(AND($K20<>0,$K20<=$BL$5),$K$12,IF(AND($H20<>0,$H20<=$BL$5),$H$12,0))))) -> 1 | AK20: =IF(AND($X20<>0,$X20<=$BL$5),$X$12,IF(AND($T20<>0,$T20<=$BL$5),$T$12,IF(AND($P20<>0,$P20<=$BL$5),$P$12,IF(AND($L20<>0,$L20<=$BL$5),$L$12,IF(AND($I20<>0,$I20<=$BL$5),$I$12,0))))) -> 0 | AL20: =AI20-AJ20 -> -1 | AM20: =AI20-AK20 -> 0 | AN20: =AI20*F20 -> 0 | AO20: =AJ20*F20 -> 0.0515 | AP20: =AK20*F20 -> 0 | AQ20: =AN20-AO20 -> -0.0515 | AZ20: 0 | BD20: 2.a | BE20: =AG20*F20 -> 0 | BF20: =AI20*F20 -> 0 | BG20: =IF(AND($W20<>0,$W20<=$BL$6),$W$12,IF(AND($S20<>0,$S20<=$BL$6),$S$12,IF(AND($O20<>0,$O20<=$BL$6),$O$12,IF(AND($K20<>0,$K20<=$BL$6),$K$12,IF(AND($H20<>0,$H20<=$BL$6),$H$12,0)))))*$F20 -> 0.0515 | BH20: =IF(AND($W20<>0,$W20<=$BL$5),$W$12,IF(AND($S20<>0,$S20<=$BL$5),$S$12,IF(AND($O20<>0,$O20<=$BL$5),$O$12,IF(AND($K20<>0,$K20<=$BL$5),$K$12,IF(AND($H20<>0,$H20<=$BL$5),$H$12,0)))))*$F20 -> 0.0515 | BI20: =IF(AND($X20<>0,$X20<=$BL$6),$X$12,IF(AND($T20<>0,$T20<=$BL$6),$T$12,IF(AND($P20<>0,$P20<=$BL$6),$P$12,IF(AND($L20<>0,$L20<=$BL$6),$L$12,IF(AND($I20<>0,$I20<=$BL$6),$I$12,0)))))*$F20 -> 0 | BJ20: =IF(AND($X20<>0,$X20<=$BL$5),$X$12,IF(AND($T20<>0,$T20<=$BL$5),$T$12,IF(AND($P20<>0,$P20<=$BL$5),$P$12,IF(AND($L20<>0,$L20<=$BL$5),$L$12,IF(AND($I20<>0,$I20<=$BL$5),$I$12,0)))))*$F20 -> 0 | BM20: 0 | BN20: =IF(AND($W20<>0,$W20<=BN$12),$W$12*$F20,IF(AND($S20<>0,$S20<=BN$12),$S$12*$F20,IF(AND($O20<>0,$O20<=BN$12),$O$12*$F20,IF(AND($K20<>0,$K20<=BN$12),$K$12*$F20,IF(AND($H20<>0,$H20<=BN$12),$H$12*$F20,0))))) -> 0 | BO20: =IF(AND($W20<>0,$W20<=BO$12),$W$12*$F20,IF(AND($S20<>0,$S20<=BO$12),$S$12*$F20,IF(AND($O20<>0,$O20<=BO$12),$O$12*$F20,IF(AND($K20<>0,$K20<=BO$12),$K$12*$F20,IF(AND($H20<>0,$H20<=BO$12),$H$12*$F20,0))))) -> 0 | BP20: =IF(AND($W20<>0,$W20<=BP$12),$W$12*$F20,IF(AND($S20<>0,$S20<=BP$12),$S$12*$F20,IF(AND($O20<>0,$O20<=BP$12),$O$12*$F20,IF(AND($K20<>0,$K20<=BP$12),$K$12*$F20,IF(AND($H20<>0,$H20<=BP$12),$H$12*$F20,0))))) -> 0 | BQ20: =IF(AND($W20<>0,$W20<=BQ$12),$W$12*$F20,IF(AND($S20<>0,$S20<=BQ$12),$S$12*$F20,IF(AND($O20<>0,$O20<=BQ$12),$O$12*$F20,IF(AND($K20<>0,$K20<=BQ$12),$K$12*$F20,IF(AND($H20<>0,$H20<=BQ$12),$H$12*$F20,0))))) -> 0 | BR20: =IF(AND($W20<>0,$W20<=BR$12),$W$12*$F20,IF(AND($S20<>0,$S20<=BR$12),$S$12*$F20,IF(AND($O20<>0,$O20<=BR$12),$O$12*$F20,IF(AND($K20<>0,$K20<=BR$12),$K$12*$F20,IF(AND($H20<>0,$H20<=BR$12),$H$12*$F20,0))))) -> 0 | BS20: =IF(AND($W20<>0,$W20<=BS$12),$W$12*$F20,IF(AND($S20<>0,$S20<=BS$12),$S$12*$F20,IF(AND($O20<>0,$O20<=BS$12),$O$12*$F20,IF(AND($K20<>0,$K20<=BS$12),$K$12*$F20,IF(AND($H20<>0,$H20<=BS$12),$H$12*$F20,0))))) -> 0.002575 | BT20: =IF(AND($W20<>0,$W20<=BT$12),$W$12*$F20,IF(AND($S20<>0,$S20<=BT$12),$S$12*$F20,IF(AND($O20<>0,$O20<=BT$12),$O$12*$F20,IF(AND($K20<>0,$K20<=BT$12),$K$12*$F20,IF(AND($H20<>0,$H20<=BT$12),$H$12*$F20,0))))) -> 0.02575 | BU20: =IF(AND($W20<>0,$W20<=BU$12),$W$12*$F20,IF(AND($S20<>0,$S20<=BU$12),$S$12*$F20,IF(AND($O20<>0,$O20<=BU$12),$O$12*$F20,IF(AND($K20<>0,$K20<=BU$12),$K$12*$F20,IF(AND($H20<>0,$H20<=BU$12),$H$12*$F20,0))))) -> 0.0515 | ... CH20: =IF(AND($W20<>0,$W20<=CH$12),$W$12*$F20,IF(AND($S20<>0,$S20<=CH$12),$S$12*$F20,IF(AND($O20<>0,$O20<=CH$12),$O$12*$F20,IF(AND($K20<>0,$K20<=CH$12),$K$12*$F20,IF(AND($H20<>0,$H20<=CH$12),$H$12*$F20,0))))) -> 0.0515 | CL20: 0 | CM20: =IF(AND($X20<>0,$X20<=CM$12),$X$12*$F20,IF(AND($T20<>0,$T20<=CM$12),$T$12*$F20,IF(AND($P20<>0,$P20<=CM$12),$P$12*$F20,IF(AND($L20<>0,$L20<=CM$12),$L$12*$F20,IF(AND($I20<>0,$I20<=CM$12),$I$12*$F20,0))))) -> 0 | CN20: =IF(AND($X20<>0,$X20<=CN$12),$X$12*$F20,IF(AND($T20<>0,$T20<=CN$12),$T$12*$F20,IF(AND($P20<>0,$P20<=CN$12),$P$12*$F20,IF(AND($L20<>0,$L20<=CN$12),$L$12*$F20,IF(AND($I20<>0,$I20<=CN$12),$I$12*$F20,0))))) -> 0 | CO20: =IF(AND($X20<>0,$X20<=CO$12),$X$12*$F20,IF(AND($T20<>0,$T20<=CO$12),$T$12*$F20,IF(AND($P20<>0,$P20<=CO$12),$P$12*$F20,IF(AND($L20<>0,$L20<=CO$12),$L$12*$F20,IF(AND($I20<>0,$I20<=CO$12),$I$12*$F20,0))))) -> 0 | CP20: =IF(AND($X20<>0,$X20<=CP$12),$X$12*$F20,IF(AND($T20<>0,$T20<=CP$12),$T$12*$F20,IF(AND($P20<>0,$P20<=CP$12),$P$12*$F20,IF(AND($L20<>0,$L20<=CP$12),$L$12*$F20,IF(AND($I20<>0,$I20<=CP$12),$I$12*$F20,0))))) -> 0 | CQ20: =IF(AND($X20<>0,$X20<=CQ$12),$X$12*$F20,IF(AND($T20<>0,$T20<=CQ$12),$T$12*$F20,IF(AND($P20<>0,$P20<=CQ$12),$P$12*$F20,IF(AND($L20<>0,$L20<=CQ$12),$L$12*$F20,IF(AND($I20<>0,$I20<=CQ$12),$I$12*$F20,0))))) -> 0 | CR20: =IF(AND($X20<>0,$X20<=CR$12),$X$12*$F20,IF(AND($T20<>0,$T20<=CR$12),$T$12*$F20,IF(AND($P20<>0,$P20<=CR$12),$P$12*$F20,IF(AND($L20<>0,$L20<=CR$12),$L$12*$F20,IF(AND($I20<>0,$I20<=CR$12),$I$12*$F20,0))))) -> 0 | CS20: =IF(AND($X20<>0,$X20<=CS$12),$X$12*$F20,IF(AND($T20<>0,$T20<=CS$12),$T$12*$F20,IF(AND($P20<>0,$P20<=CS$12),$P$12*$F20,IF(AND($L20<>0,$L20<=CS$12),$L$12*$F20,IF(AND($I20<>0,$I20<=CS$12),$I$12*$F20,0))))) -> 0 | CT20: =IF(AND($X20<>0,$X20<=CT$12),$X$12*$F20,IF(AND($T20<>0,$T20<=CT$12),$T$12*$F20,IF(AND($P20<>0,$P20<=CT$12),$P$12*$F20,IF(AND($L20<>0,$L20<=CT$12),$L$12*$F20,IF(AND($I20<>0,$I20<=CT$12),$I$12*$F20,0))))) -> 0 | ... DG20: =IF(AND($X20<>0,$X20<=DG$12),$X$12*$F20,IF(AND($T20<>0,$T20<=DG$12),$T$12*$F20,IF(AND($P20<>0,$P20<=DG$12),$P$12*$F20,IF(AND($L20<>0,$L20<=DG$12),$L$12*$F20,IF(AND($I20<>0,$I20<=DG$12),$I$12*$F20,0))))) -> 0.038625 | DL20: 0 | DM20: =IF(AND($Y20<>0,$Y20<=DM$12),$Y$12*$F20,IF(AND($U20<>0,$U20<=DM$12),$U$12*$F20,IF(AND($Q20<>0,$Q20<=DM$12),$Q$12*$F20,IF(AND($M20<>0,$M20<=DM$12),$M$12*$F20,IF(AND($J20<>0,$J20<=DM$12),$J$12*$F20,0))))) -> 0 | DN20: =IF(AND($Y20<>0,$Y20<=DN$12),$Y$12*$F20,IF(AND($U20<>0,$U20<=DN$12),$U$12*$F20,IF(AND($Q20<>0,$Q20<=DN$12),$Q$12*$F20,IF(AND($M20<>0,$M20<=DN$12),$M$12*$F20,IF(AND($J20<>0,$J20<=DN$12),$J$12*$F20,0))))) -> 0 | DO20: =IF(AND($Y20<>0,$Y20<=DO$12),$Y$12*$F20,IF(AND($U20<>0,$U20<=DO$12),$U$12*$F20,IF(AND($Q20<>0,$Q20<=DO$12),$Q$12*$F20,IF(AND($M20<>0,$M20<=DO$12),$M$12*$F20,IF(AND($J20<>0,$J20<=DO$12),$J$12*$F20,0))))) -> 0 | DP20: =IF(AND($Y20<>0,$Y20<=DP$12),$Y$12*$F20,IF(AND($U20<>0,$U20<=DP$12),$U$12*$F20,IF(AND($Q20<>0,$Q20<=DP$12),$Q$12*$F20,IF(AND($M20<>0,$M20<=DP$12),$M$12*$F20,IF(AND($J20<>0,$J20<=DP$12),$J$12*$F20,0))))) -> 0 | DQ20: =IF(AND($Y20<>0,$Y20<=DQ$12),$Y$12*$F20,IF(AND($U20<>0,$U20<=DQ$12),$U$12*$F20,IF(AND($Q20<>0,$Q20<=DQ$12),$Q$12*$F20,IF(AND($M20<>0,$M20<=DQ$12),$M$12*$F20,IF(AND($J20<>0,$J20<=DQ$12),$J$12*$F20,0))))) -> 0 | DR20: =IF(AND($Y20<>0,$Y20<=DR$12),$Y$12*$F20,IF(AND($U20<>0,$U20<=DR$12),$U$12*$F20,IF(AND($Q20<>0,$Q20<=DR$12),$Q$12*$F20,IF(AND($M20<>0,$M20<=DR$12),$M$12*$F20,IF(AND($J20<>0,$J20<=DR$12),$J$12*$F20,0))))) -> 0 | DS20: =IF(AND($Y20<>0,$Y20<=DS$12),$Y$12*$F20,IF(AND($U20<>0,$U20<=DS$12),$U$12*$F20,IF(AND($Q20<>0,$Q20<=DS$12),$Q$12*$F20,IF(AND($M20<>0,$M20<=DS$12),$M$12*$F20,IF(AND($J20<>0,$J20<=DS$12),$J$12*$F20,0))))) -> 0 | DT20: =IF(AND($Y20<>0,$Y20<=DT$12),$Y$12*$F20,IF(AND($U20<>0,$U20<=DT$12),$U$12*$F20,IF(AND($Q20<>0,$Q20<=DT$12),$Q$12*$F20,IF(AND($M20<>0,$M20<=DT$12),$M$12*$F20,IF(AND($J20<>0,$J20<=DT$12),$J$12*$F20,0))))) -> 0 | ... EG20: =IF(AND($Y20<>0,$Y20<=EG$12),$Y$12*$F20,IF(AND($U20<>0,$U20<=EG$12),$U$12*$F20,IF(AND($Q20<>0,$Q20<=EG$12),$Q$12*$F20,IF(AND($M20<>0,$M20<=EG$12),$M$12*$F20,IF(AND($J20<>0,$J20<=EG$12),$J$12*$F20,0))))) -> 0
A21: 3 | C21: Desain UI/UX | F21: =SUBTOTAL(9,F22:F24) -> 0.1733 | AZ21: 0.1733 | BD21: 3 | BE21: =SUBTOTAL(9,BE22:BE24) -> 0.1733 | BF21: =SUBTOTAL(9,BF22:BF24) -> 0.1733 | BG21: =SUBTOTAL(9,BG22:BG24) -> 0.168925 | BH21: =SUBTOTAL(9,BH22:BH24) -> 0.1733 | BI21: =SUBTOTAL(9,BI22:BI24) -> 0 | BJ21: =SUBTOTAL(9,BJ22:BJ24) -> 0 | BM21: =SUBTOTAL(9,BM22:BM24) -> 0 | BN21: =SUBTOTAL(9,BN22:BN24) -> 0.010825 | BO21: =SUBTOTAL(9,BO22:BO24) -> 0.02165 | BP21: =SUBTOTAL(9,BP22:BP24) -> 0.032475 | BQ21: =SUBTOTAL(9,BQ22:BQ24) -> 0.048925 | BR21: =SUBTOTAL(9,BR22:BR24) -> 0.071425 | BS21: =SUBTOTAL(9,BS22:BS24) -> 0.09955 | BT21: =SUBTOTAL(9,BT22:BT24) -> 0.127675 | ... CH21: =SUBTOTAL(9,CH22:CH24) -> 0.1733 | CL21: =SUBTOTAL(9,CL22:CL24) -> 0 | CM21: =SUBTOTAL(9,CM22:CM24) -> 0 | CN21: =SUBTOTAL(9,CN22:CN24) -> 0 | CO21: =SUBTOTAL(9,CO22:CO24) -> 0 | CP21: =SUBTOTAL(9,CP22:CP24) -> 0 | CQ21: =SUBTOTAL(9,CQ22:CQ24) -> 0 | CR21: =SUBTOTAL(9,CR22:CR24) -> 0 | CS21: =SUBTOTAL(9,CS22:CS24) -> 0 | ... DG21: =SUBTOTAL(9,DG22:DG24) -> 0 | DL21: =SUBTOTAL(9,DL22:DL24) -> 0 | DM21: =SUBTOTAL(9,DM22:DM24) -> 0.10185 | DN21: =SUBTOTAL(9,DN22:DN24) -> 0.1733 | DO21: =SUBTOTAL(9,DO22:DO24) -> 0.1733 | DP21: =SUBTOTAL(9,DP22:DP24) -> 0.1733 | DQ21: =SUBTOTAL(9,DQ22:DQ24) -> 0.1733 | DR21: =SUBTOTAL(9,DR22:DR24) -> 0.1733 | DS21: =SUBTOTAL(9,DS22:DS24) -> 0.1733 | ... EG21: =SUBTOTAL(9,EG22:EG24) -> 0.1733
A22: 3.a | B22: W2026I-DNGF-EM-100-PRD-SPC-0003 | C22: User Flow & Wireframe (Low-Fidelity) | F22: 0.0433 | H22: 46113 | J22: 46113 | K22: =H22+((O22-H22)*0.5) -> 46120.25 | M22: 46117 | O22: =H22+((W22-H22)*0.5) -> 46127.5 | Q22: 46119 | S22: =O22+((W22-O22)*0.5) -> 46134.75 | U22: 46122 | W22: 46142 | Y22: 46126 | AE22: =AN22 -> 0.0433 | AG22: =IF(AND($Y22<>0,$Y22<=$BL$6),$Y$12,IF(AND($U22<>0,$U22<=$BL$6),$U$12,IF(AND($Q22<>0,$Q22<=$BL$6),$Q$12,IF(AND($M22<>0,$M22<=$BL$6),$M$12,IF(AND($J22<>0,$J22<=$BL$6),$J$12,0))))) -> 1 | AH22: =AI22-AG22 -> 0 | AI22: =IF(AND($Y22<>0,$Y22<=$BL$5),$Y$12,IF(AND($U22<>0,$U22<=$BL$5),$U$12,IF(AND($Q22<>0,$Q22<=$BL$5),$Q$12,IF(AND($M22<>0,$M22<=$BL$5),$M$12,IF(AND($J22<>0,$J22<=$BL$5),$J$12,0))))) -> 1 | AJ22: =IF(AND($W22<>0,$W22<=$BL$5),$W$12,IF(AND($S22<>0,$S22<=$BL$5),$S$12,IF(AND($O22<>0,$O22<=$BL$5),$O$12,IF(AND($K22<>0,$K22<=$BL$5),$K$12,IF(AND($H22<>0,$H22<=$BL$5),$H$12,0))))) -> 1 | AK22: =IF(AND($X22<>0,$X22<=$BL$5),$X$12,IF(AND($T22<>0,$T22<=$BL$5),$T$12,IF(AND($P22<>0,$P22<=$BL$5),$P$12,IF(AND($L22<>0,$L22<=$BL$5),$L$12,IF(AND($I22<>0,$I22<=$BL$5),$I$12,0))))) -> 0 | AL22: =AI22-AJ22 -> 0 | AM22: =AI22-AK22 -> 1 | AN22: =AI22*F22 -> 0.0433 | AO22: =AJ22*F22 -> 0.0433 | AP22: =AK22*F22 -> 0 | AQ22: =AN22-AO22 -> 0 | AZ22: 0.0433 | BD22: 3.a | BE22: =AG22*F22 -> 0.0433 | BF22: =AI22*F22 -> 0.0433 | BG22: =IF(AND($W22<>0,$W22<=$BL$6),$W$12,IF(AND($S22<>0,$S22<=$BL$6),$S$12,IF(AND($O22<>0,$O22<=$BL$6),$O$12,IF(AND($K22<>0,$K22<=$BL$6),$K$12,IF(AND($H22<>0,$H22<=$BL$6),$H$12,0)))))*$F22 -> 0.0433 | BH22: =IF(AND($W22<>0,$W22<=$BL$5),$W$12,IF(AND($S22<>0,$S22<=$BL$5),$S$12,IF(AND($O22<>0,$O22<=$BL$5),$O$12,IF(AND($K22<>0,$K22<=$BL$5),$K$12,IF(AND($H22<>0,$H22<=$BL$5),$H$12,0)))))*$F22 -> 0.0433 | BI22: =IF(AND($X22<>0,$X22<=$BL$6),$X$12,IF(AND($T22<>0,$T22<=$BL$6),$T$12,IF(AND($P22<>0,$P22<=$BL$6),$P$12,IF(AND($L22<>0,$L22<=$BL$6),$L$12,IF(AND($I22<>0,$I22<=$BL$6),$I$12,0)))))*$F22 -> 0 | BJ22: =IF(AND($X22<>0,$X22<=$BL$5),$X$12,IF(AND($T22<>0,$T22<=$BL$5),$T$12,IF(AND($P22<>0,$P22<=$BL$5),$P$12,IF(AND($L22<>0,$L22<=$BL$5),$L$12,IF(AND($I22<>0,$I22<=$BL$5),$I$12,0)))))*$F22 -> 0 | BM22: 0 | BN22: =IF(AND($W22<>0,$W22<=BN$12),$W$12*$F22,IF(AND($S22<>0,$S22<=BN$12),$S$12*$F22,IF(AND($O22<>0,$O22<=BN$12),$O$12*$F22,IF(AND($K22<>0,$K22<=BN$12),$K$12*$F22,IF(AND($H22<>0,$H22<=BN$12),$H$12*$F22,0))))) -> 0.010825 | BO22: =IF(AND($W22<>0,$W22<=BO$12),$W$12*$F22,IF(AND($S22<>0,$S22<=BO$12),$S$12*$F22,IF(AND($O22<>0,$O22<=BO$12),$O$12*$F22,IF(AND($K22<>0,$K22<=BO$12),$K$12*$F22,IF(AND($H22<>0,$H22<=BO$12),$H$12*$F22,0))))) -> 0.02165 | BP22: =IF(AND($W22<>0,$W22<=BP$12),$W$12*$F22,IF(AND($S22<>0,$S22<=BP$12),$S$12*$F22,IF(AND($O22<>0,$O22<=BP$12),$O$12*$F22,IF(AND($K22<>0,$K22<=BP$12),$K$12*$F22,IF(AND($H22<>0,$H22<=BP$12),$H$12*$F22,0))))) -> 0.032475 | BQ22: =IF(AND($W22<>0,$W22<=BQ$12),$W$12*$F22,IF(AND($S22<>0,$S22<=BQ$12),$S$12*$F22,IF(AND($O22<>0,$O22<=BQ$12),$O$12*$F22,IF(AND($K22<>0,$K22<=BQ$12),$K$12*$F22,IF(AND($H22<>0,$H22<=BQ$12),$H$12*$F22,0))))) -> 0.0433 | BR22: =IF(AND($W22<>0,$W22<=BR$12),$W$12*$F22,IF(AND($S22<>0,$S22<=BR$12),$S$12*$F22,IF(AND($O22<>0,$O22<=BR$12),$O$12*$F22,IF(AND($K22<>0,$K22<=BR$12),$K$12*$F22,IF(AND($H22<>0,$H22<=BR$12),$H$12*$F22,0))))) -> 0.0433 | BS22: =IF(AND($W22<>0,$W22<=BS$12),$W$12*$F22,IF(AND($S22<>0,$S22<=BS$12),$S$12*$F22,IF(AND($O22<>0,$O22<=BS$12),$O$12*$F22,IF(AND($K22<>0,$K22<=BS$12),$K$12*$F22,IF(AND($H22<>0,$H22<=BS$12),$H$12*$F22,0))))) -> 0.0433 | BT22: =IF(AND($W22<>0,$W22<=BT$12),$W$12*$F22,IF(AND($S22<>0,$S22<=BT$12),$S$12*$F22,IF(AND($O22<>0,$O22<=BT$12),$O$12*$F22,IF(AND($K22<>0,$K22<=BT$12),$K$12*$F22,IF(AND($H22<>0,$H22<=BT$12),$H$12*$F22,0))))) -> 0.0433 | BU22: =IF(AND($W22<>0,$W22<=BU$12),$W$12*$F22,IF(AND($S22<>0,$S22<=BU$12),$S$12*$F22,IF(AND($O22<>0,$O22<=BU$12),$O$12*$F22,IF(AND($K22<>0,$K22<=BU$12),$K$12*$F22,IF(AND($H22<>0,$H22<=BU$12),$H$12*$F22,0))))) -> 0.0433 | ... CH22: =IF(AND($W22<>0,$W22<=CH$12),$W$12*$F22,IF(AND($S22<>0,$S22<=CH$12),$S$12*$F22,IF(AND($O22<>0,$O22<=CH$12),$O$12*$F22,IF(AND($K22<>0,$K22<=CH$12),$K$12*$F22,IF(AND($H22<>0,$H22<=CH$12),$H$12*$F22,0))))) -> 0.0433 | CL22: 0 | CM22: =IF(AND($X22<>0,$X22<=CM$12),$X$12*$F22,IF(AND($T22<>0,$T22<=CM$12),$T$12*$F22,IF(AND($P22<>0,$P22<=CM$12),$P$12*$F22,IF(AND($L22<>0,$L22<=CM$12),$L$12*$F22,IF(AND($I22<>0,$I22<=CM$12),$I$12*$F22,0))))) -> 0 | CN22: =IF(AND($X22<>0,$X22<=CN$12),$X$12*$F22,IF(AND($T22<>0,$T22<=CN$12),$T$12*$F22,IF(AND($P22<>0,$P22<=CN$12),$P$12*$F22,IF(AND($L22<>0,$L22<=CN$12),$L$12*$F22,IF(AND($I22<>0,$I22<=CN$12),$I$12*$F22,0))))) -> 0 | CO22: =IF(AND($X22<>0,$X22<=CO$12),$X$12*$F22,IF(AND($T22<>0,$T22<=CO$12),$T$12*$F22,IF(AND($P22<>0,$P22<=CO$12),$P$12*$F22,IF(AND($L22<>0,$L22<=CO$12),$L$12*$F22,IF(AND($I22<>0,$I22<=CO$12),$I$12*$F22,0))))) -> 0 | CP22: =IF(AND($X22<>0,$X22<=CP$12),$X$12*$F22,IF(AND($T22<>0,$T22<=CP$12),$T$12*$F22,IF(AND($P22<>0,$P22<=CP$12),$P$12*$F22,IF(AND($L22<>0,$L22<=CP$12),$L$12*$F22,IF(AND($I22<>0,$I22<=CP$12),$I$12*$F22,0))))) -> 0 | CQ22: =IF(AND($X22<>0,$X22<=CQ$12),$X$12*$F22,IF(AND($T22<>0,$T22<=CQ$12),$T$12*$F22,IF(AND($P22<>0,$P22<=CQ$12),$P$12*$F22,IF(AND($L22<>0,$L22<=CQ$12),$L$12*$F22,IF(AND($I22<>0,$I22<=CQ$12),$I$12*$F22,0))))) -> 0 | CR22: =IF(AND($X22<>0,$X22<=CR$12),$X$12*$F22,IF(AND($T22<>0,$T22<=CR$12),$T$12*$F22,IF(AND($P22<>0,$P22<=CR$12),$P$12*$F22,IF(AND($L22<>0,$L22<=CR$12),$L$12*$F22,IF(AND($I22<>0,$I22<=CR$12),$I$12*$F22,0))))) -> 0 | CS22: =IF(AND($X22<>0,$X22<=CS$12),$X$12*$F22,IF(AND($T22<>0,$T22<=CS$12),$T$12*$F22,IF(AND($P22<>0,$P22<=CS$12),$P$12*$F22,IF(AND($L22<>0,$L22<=CS$12),$L$12*$F22,IF(AND($I22<>0,$I22<=CS$12),$I$12*$F22,0))))) -> 0 | CT22: =IF(AND($X22<>0,$X22<=CT$12),$X$12*$F22,IF(AND($T22<>0,$T22<=CT$12),$T$12*$F22,IF(AND($P22<>0,$P22<=CT$12),$P$12*$F22,IF(AND($L22<>0,$L22<=CT$12),$L$12*$F22,IF(AND($I22<>0,$I22<=CT$12),$I$12*$F22,0))))) -> 0 | ... DG22: =IF(AND($X22<>0,$X22<=DG$12),$X$12*$F22,IF(AND($T22<>0,$T22<=DG$12),$T$12*$F22,IF(AND($P22<>0,$P22<=DG$12),$P$12*$F22,IF(AND($L22<>0,$L22<=DG$12),$L$12*$F22,IF(AND($I22<>0,$I22<=DG$12),$I$12*$F22,0))))) -> 0 | DL22: 0 | DM22: =IF(AND($Y22<>0,$Y22<=DM$12),$Y$12*$F22,IF(AND($U22<>0,$U22<=DM$12),$U$12*$F22,IF(AND($Q22<>0,$Q22<=DM$12),$Q$12*$F22,IF(AND($M22<>0,$M22<=DM$12),$M$12*$F22,IF(AND($J22<>0,$J22<=DM$12),$J$12*$F22,0))))) -> 0.032475 | DN22: =IF(AND($Y22<>0,$Y22<=DN$12),$Y$12*$F22,IF(AND($U22<>0,$U22<=DN$12),$U$12*$F22,IF(AND($Q22<>0,$Q22<=DN$12),$Q$12*$F22,IF(AND($M22<>0,$M22<=DN$12),$M$12*$F22,IF(AND($J22<>0,$J22<=DN$12),$J$12*$F22,0))))) -> 0.0433 | DO22: =IF(AND($Y22<>0,$Y22<=DO$12),$Y$12*$F22,IF(AND($U22<>0,$U22<=DO$12),$U$12*$F22,IF(AND($Q22<>0,$Q22<=DO$12),$Q$12*$F22,IF(AND($M22<>0,$M22<=DO$12),$M$12*$F22,IF(AND($J22<>0,$J22<=DO$12),$J$12*$F22,0))))) -> 0.0433 | DP22: =IF(AND($Y22<>0,$Y22<=DP$12),$Y$12*$F22,IF(AND($U22<>0,$U22<=DP$12),$U$12*$F22,IF(AND($Q22<>0,$Q22<=DP$12),$Q$12*$F22,IF(AND($M22<>0,$M22<=DP$12),$M$12*$F22,IF(AND($J22<>0,$J22<=DP$12),$J$12*$F22,0))))) -> 0.0433 | DQ22: =IF(AND($Y22<>0,$Y22<=DQ$12),$Y$12*$F22,IF(AND($U22<>0,$U22<=DQ$12),$U$12*$F22,IF(AND($Q22<>0,$Q22<=DQ$12),$Q$12*$F22,IF(AND($M22<>0,$M22<=DQ$12),$M$12*$F22,IF(AND($J22<>0,$J22<=DQ$12),$J$12*$F22,0))))) -> 0.0433 | DR22: =IF(AND($Y22<>0,$Y22<=DR$12),$Y$12*$F22,IF(AND($U22<>0,$U22<=DR$12),$U$12*$F22,IF(AND($Q22<>0,$Q22<=DR$12),$Q$12*$F22,IF(AND($M22<>0,$M22<=DR$12),$M$12*$F22,IF(AND($J22<>0,$J22<=DR$12),$J$12*$F22,0))))) -> 0.0433 | DS22: =IF(AND($Y22<>0,$Y22<=DS$12),$Y$12*$F22,IF(AND($U22<>0,$U22<=DS$12),$U$12*$F22,IF(AND($Q22<>0,$Q22<=DS$12),$Q$12*$F22,IF(AND($M22<>0,$M22<=DS$12),$M$12*$F22,IF(AND($J22<>0,$J22<=DS$12),$J$12*$F22,0))))) -> 0.0433 | DT22: =IF(AND($Y22<>0,$Y22<=DT$12),$Y$12*$F22,IF(AND($U22<>0,$U22<=DT$12),$U$12*$F22,IF(AND($Q22<>0,$Q22<=DT$12),$Q$12*$F22,IF(AND($M22<>0,$M22<=DT$12),$M$12*$F22,IF(AND($J22<>0,$J22<=DT$12),$J$12*$F22,0))))) -> 0.0433 | ... EG22: =IF(AND($Y22<>0,$Y22<=EG$12),$Y$12*$F22,IF(AND($U22<>0,$U22<=EG$12),$U$12*$F22,IF(AND($Q22<>0,$Q22<=EG$12),$Q$12*$F22,IF(AND($M22<>0,$M22<=EG$12),$M$12*$F22,IF(AND($J22<>0,$J22<=EG$12),$J$12*$F22,0))))) -> 0.0433
A23: 3.b | B23: W2026I-DNGF-EM-100-PRD-SPC-0004 | C23: Design System & High-Fidelity Mockup | F23: 0.1125 | H23: 46143 | J23: 46113 | K23: =H23+((O23-H23)*0.5) -> 46150.5 | M23: 46117 | O23: =H23+((W23-H23)*0.5) -> 46158 | Q23: 46119 | S23: =O23+((W23-O23)*0.5) -> 46165.5 | U23: 46131 | W23: 46173 | Y23: 46126 | AE23: =AN23 -> 0.1125 | AG23: =IF(AND($Y23<>0,$Y23<=$BL$6),$Y$12,IF(AND($U23<>0,$U23<=$BL$6),$U$12,IF(AND($Q23<>0,$Q23<=$BL$6),$Q$12,IF(AND($M23<>0,$M23<=$BL$6),$M$12,IF(AND($J23<>0,$J23<=$BL$6),$J$12,0))))) -> 1 | AH23: =AI23-AG23 -> 0 | AI23: =IF(AND($Y23<>0,$Y23<=$BL$5),$Y$12,IF(AND($U23<>0,$U23<=$BL$5),$U$12,IF(AND($Q23<>0,$Q23<=$BL$5),$Q$12,IF(AND($M23<>0,$M23<=$BL$5),$M$12,IF(AND($J23<>0,$J23<=$BL$5),$J$12,0))))) -> 1 | AJ23: =IF(AND($W23<>0,$W23<=$BL$5),$W$12,IF(AND($S23<>0,$S23<=$BL$5),$S$12,IF(AND($O23<>0,$O23<=$BL$5),$O$12,IF(AND($K23<>0,$K23<=$BL$5),$K$12,IF(AND($H23<>0,$H23<=$BL$5),$H$12,0))))) -> 1 | AK23: =IF(AND($X23<>0,$X23<=$BL$5),$X$12,IF(AND($T23<>0,$T23<=$BL$5),$T$12,IF(AND($P23<>0,$P23<=$BL$5),$P$12,IF(AND($L23<>0,$L23<=$BL$5),$L$12,IF(AND($I23<>0,$I23<=$BL$5),$I$12,0))))) -> 0 | AL23: =AI23-AJ23 -> 0 | AM23: =AI23-AK23 -> 1 | AN23: =AI23*F23 -> 0.1125 | AO23: =AJ23*F23 -> 0.1125 | AP23: =AK23*F23 -> 0 | AQ23: =AN23-AO23 -> 0 | AZ23: 0.1125 | BD23: 3.b | BE23: =AG23*F23 -> 0.1125 | BF23: =AI23*F23 -> 0.1125 | BG23: =IF(AND($W23<>0,$W23<=$BL$6),$W$12,IF(AND($S23<>0,$S23<=$BL$6),$S$12,IF(AND($O23<>0,$O23<=$BL$6),$O$12,IF(AND($K23<>0,$K23<=$BL$6),$K$12,IF(AND($H23<>0,$H23<=$BL$6),$H$12,0)))))*$F23 -> 0.1125 | BH23: =IF(AND($W23<>0,$W23<=$BL$5),$W$12,IF(AND($S23<>0,$S23<=$BL$5),$S$12,IF(AND($O23<>0,$O23<=$BL$5),$O$12,IF(AND($K23<>0,$K23<=$BL$5),$K$12,IF(AND($H23<>0,$H23<=$BL$5),$H$12,0)))))*$F23 -> 0.1125 | BI23: =IF(AND($X23<>0,$X23<=$BL$6),$X$12,IF(AND($T23<>0,$T23<=$BL$6),$T$12,IF(AND($P23<>0,$P23<=$BL$6),$P$12,IF(AND($L23<>0,$L23<=$BL$6),$L$12,IF(AND($I23<>0,$I23<=$BL$6),$I$12,0)))))*$F23 -> 0 | BJ23: =IF(AND($X23<>0,$X23<=$BL$5),$X$12,IF(AND($T23<>0,$T23<=$BL$5),$T$12,IF(AND($P23<>0,$P23<=$BL$5),$P$12,IF(AND($L23<>0,$L23<=$BL$5),$L$12,IF(AND($I23<>0,$I23<=$BL$5),$I$12,0)))))*$F23 -> 0 | BM23: 0 | BN23: =IF(AND($W23<>0,$W23<=BN$12),$W$12*$F23,IF(AND($S23<>0,$S23<=BN$12),$S$12*$F23,IF(AND($O23<>0,$O23<=BN$12),$O$12*$F23,IF(AND($K23<>0,$K23<=BN$12),$K$12*$F23,IF(AND($H23<>0,$H23<=BN$12),$H$12*$F23,0))))) -> 0 | BO23: =IF(AND($W23<>0,$W23<=BO$12),$W$12*$F23,IF(AND($S23<>0,$S23<=BO$12),$S$12*$F23,IF(AND($O23<>0,$O23<=BO$12),$O$12*$F23,IF(AND($K23<>0,$K23<=BO$12),$K$12*$F23,IF(AND($H23<>0,$H23<=BO$12),$H$12*$F23,0))))) -> 0 | BP23: =IF(AND($W23<>0,$W23<=BP$12),$W$12*$F23,IF(AND($S23<>0,$S23<=BP$12),$S$12*$F23,IF(AND($O23<>0,$O23<=BP$12),$O$12*$F23,IF(AND($K23<>0,$K23<=BP$12),$K$12*$F23,IF(AND($H23<>0,$H23<=BP$12),$H$12*$F23,0))))) -> 0 | BQ23: =IF(AND($W23<>0,$W23<=BQ$12),$W$12*$F23,IF(AND($S23<>0,$S23<=BQ$12),$S$12*$F23,IF(AND($O23<>0,$O23<=BQ$12),$O$12*$F23,IF(AND($K23<>0,$K23<=BQ$12),$K$12*$F23,IF(AND($H23<>0,$H23<=BQ$12),$H$12*$F23,0))))) -> 0.005625 | BR23: =IF(AND($W23<>0,$W23<=BR$12),$W$12*$F23,IF(AND($S23<>0,$S23<=BR$12),$S$12*$F23,IF(AND($O23<>0,$O23<=BR$12),$O$12*$F23,IF(AND($K23<>0,$K23<=BR$12),$K$12*$F23,IF(AND($H23<>0,$H23<=BR$12),$H$12*$F23,0))))) -> 0.028125 | BS23: =IF(AND($W23<>0,$W23<=BS$12),$W$12*$F23,IF(AND($S23<>0,$S23<=BS$12),$S$12*$F23,IF(AND($O23<>0,$O23<=BS$12),$O$12*$F23,IF(AND($K23<>0,$K23<=BS$12),$K$12*$F23,IF(AND($H23<>0,$H23<=BS$12),$H$12*$F23,0))))) -> 0.05625 | BT23: =IF(AND($W23<>0,$W23<=BT$12),$W$12*$F23,IF(AND($S23<>0,$S23<=BT$12),$S$12*$F23,IF(AND($O23<>0,$O23<=BT$12),$O$12*$F23,IF(AND($K23<>0,$K23<=BT$12),$K$12*$F23,IF(AND($H23<>0,$H23<=BT$12),$H$12*$F23,0))))) -> 0.084375 | BU23: =IF(AND($W23<>0,$W23<=BU$12),$W$12*$F23,IF(AND($S23<>0,$S23<=BU$12),$S$12*$F23,IF(AND($O23<>0,$O23<=BU$12),$O$12*$F23,IF(AND($K23<>0,$K23<=BU$12),$K$12*$F23,IF(AND($H23<>0,$H23<=BU$12),$H$12*$F23,0))))) -> 0.1125 | ... CH23: =IF(AND($W23<>0,$W23<=CH$12),$W$12*$F23,IF(AND($S23<>0,$S23<=CH$12),$S$12*$F23,IF(AND($O23<>0,$O23<=CH$12),$O$12*$F23,IF(AND($K23<>0,$K23<=CH$12),$K$12*$F23,IF(AND($H23<>0,$H23<=CH$12),$H$12*$F23,0))))) -> 0.1125 | CL23: 0 | CM23: =IF(AND($X23<>0,$X23<=CM$12),$X$12*$F23,IF(AND($T23<>0,$T23<=CM$12),$T$12*$F23,IF(AND($P23<>0,$P23<=CM$12),$P$12*$F23,IF(AND($L23<>0,$L23<=CM$12),$L$12*$F23,IF(AND($I23<>0,$I23<=CM$12),$I$12*$F23,0))))) -> 0 | CN23: =IF(AND($X23<>0,$X23<=CN$12),$X$12*$F23,IF(AND($T23<>0,$T23<=CN$12),$T$12*$F23,IF(AND($P23<>0,$P23<=CN$12),$P$12*$F23,IF(AND($L23<>0,$L23<=CN$12),$L$12*$F23,IF(AND($I23<>0,$I23<=CN$12),$I$12*$F23,0))))) -> 0 | CO23: =IF(AND($X23<>0,$X23<=CO$12),$X$12*$F23,IF(AND($T23<>0,$T23<=CO$12),$T$12*$F23,IF(AND($P23<>0,$P23<=CO$12),$P$12*$F23,IF(AND($L23<>0,$L23<=CO$12),$L$12*$F23,IF(AND($I23<>0,$I23<=CO$12),$I$12*$F23,0))))) -> 0 | CP23: =IF(AND($X23<>0,$X23<=CP$12),$X$12*$F23,IF(AND($T23<>0,$T23<=CP$12),$T$12*$F23,IF(AND($P23<>0,$P23<=CP$12),$P$12*$F23,IF(AND($L23<>0,$L23<=CP$12),$L$12*$F23,IF(AND($I23<>0,$I23<=CP$12),$I$12*$F23,0))))) -> 0 | CQ23: =IF(AND($X23<>0,$X23<=CQ$12),$X$12*$F23,IF(AND($T23<>0,$T23<=CQ$12),$T$12*$F23,IF(AND($P23<>0,$P23<=CQ$12),$P$12*$F23,IF(AND($L23<>0,$L23<=CQ$12),$L$12*$F23,IF(AND($I23<>0,$I23<=CQ$12),$I$12*$F23,0))))) -> 0 | CR23: =IF(AND($X23<>0,$X23<=CR$12),$X$12*$F23,IF(AND($T23<>0,$T23<=CR$12),$T$12*$F23,IF(AND($P23<>0,$P23<=CR$12),$P$12*$F23,IF(AND($L23<>0,$L23<=CR$12),$L$12*$F23,IF(AND($I23<>0,$I23<=CR$12),$I$12*$F23,0))))) -> 0 | CS23: =IF(AND($X23<>0,$X23<=CS$12),$X$12*$F23,IF(AND($T23<>0,$T23<=CS$12),$T$12*$F23,IF(AND($P23<>0,$P23<=CS$12),$P$12*$F23,IF(AND($L23<>0,$L23<=CS$12),$L$12*$F23,IF(AND($I23<>0,$I23<=CS$12),$I$12*$F23,0))))) -> 0 | CT23: =IF(AND($X23<>0,$X23<=CT$12),$X$12*$F23,IF(AND($T23<>0,$T23<=CT$12),$T$12*$F23,IF(AND($P23<>0,$P23<=CT$12),$P$12*$F23,IF(AND($L23<>0,$L23<=CT$12),$L$12*$F23,IF(AND($I23<>0,$I23<=CT$12),$I$12*$F23,0))))) -> 0 | ... DG23: =IF(AND($X23<>0,$X23<=DG$12),$X$12*$F23,IF(AND($T23<>0,$T23<=DG$12),$T$12*$F23,IF(AND($P23<>0,$P23<=DG$12),$P$12*$F23,IF(AND($L23<>0,$L23<=DG$12),$L$12*$F23,IF(AND($I23<>0,$I23<=DG$12),$I$12*$F23,0))))) -> 0 | DL23: 0 | DM23: =IF(AND($Y23<>0,$Y23<=DM$12),$Y$12*$F23,IF(AND($U23<>0,$U23<=DM$12),$U$12*$F23,IF(AND($Q23<>0,$Q23<=DM$12),$Q$12*$F23,IF(AND($M23<>0,$M23<=DM$12),$M$12*$F23,IF(AND($J23<>0,$J23<=DM$12),$J$12*$F23,0))))) -> 0.05625 | DN23: =IF(AND($Y23<>0,$Y23<=DN$12),$Y$12*$F23,IF(AND($U23<>0,$U23<=DN$12),$U$12*$F23,IF(AND($Q23<>0,$Q23<=DN$12),$Q$12*$F23,IF(AND($M23<>0,$M23<=DN$12),$M$12*$F23,IF(AND($J23<>0,$J23<=DN$12),$J$12*$F23,0))))) -> 0.1125 | DO23: =IF(AND($Y23<>0,$Y23<=DO$12),$Y$12*$F23,IF(AND($U23<>0,$U23<=DO$12),$U$12*$F23,IF(AND($Q23<>0,$Q23<=DO$12),$Q$12*$F23,IF(AND($M23<>0,$M23<=DO$12),$M$12*$F23,IF(AND($J23<>0,$J23<=DO$12),$J$12*$F23,0))))) -> 0.1125 | DP23: =IF(AND($Y23<>0,$Y23<=DP$12),$Y$12*$F23,IF(AND($U23<>0,$U23<=DP$12),$U$12*$F23,IF(AND($Q23<>0,$Q23<=DP$12),$Q$12*$F23,IF(AND($M23<>0,$M23<=DP$12),$M$12*$F23,IF(AND($J23<>0,$J23<=DP$12),$J$12*$F23,0))))) -> 0.1125 | DQ23: =IF(AND($Y23<>0,$Y23<=DQ$12),$Y$12*$F23,IF(AND($U23<>0,$U23<=DQ$12),$U$12*$F23,IF(AND($Q23<>0,$Q23<=DQ$12),$Q$12*$F23,IF(AND($M23<>0,$M23<=DQ$12),$M$12*$F23,IF(AND($J23<>0,$J23<=DQ$12),$J$12*$F23,0))))) -> 0.1125 | DR23: =IF(AND($Y23<>0,$Y23<=DR$12),$Y$12*$F23,IF(AND($U23<>0,$U23<=DR$12),$U$12*$F23,IF(AND($Q23<>0,$Q23<=DR$12),$Q$12*$F23,IF(AND($M23<>0,$M23<=DR$12),$M$12*$F23,IF(AND($J23<>0,$J23<=DR$12),$J$12*$F23,0))))) -> 0.1125 | DS23: =IF(AND($Y23<>0,$Y23<=DS$12),$Y$12*$F23,IF(AND($U23<>0,$U23<=DS$12),$U$12*$F23,IF(AND($Q23<>0,$Q23<=DS$12),$Q$12*$F23,IF(AND($M23<>0,$M23<=DS$12),$M$12*$F23,IF(AND($J23<>0,$J23<=DS$12),$J$12*$F23,0))))) -> 0.1125 | DT23: =IF(AND($Y23<>0,$Y23<=DT$12),$Y$12*$F23,IF(AND($U23<>0,$U23<=DT$12),$U$12*$F23,IF(AND($Q23<>0,$Q23<=DT$12),$Q$12*$F23,IF(AND($M23<>0,$M23<=DT$12),$M$12*$F23,IF(AND($J23<>0,$J23<=DT$12),$J$12*$F23,0))))) -> 0.1125 | ... EG23: =IF(AND($Y23<>0,$Y23<=EG$12),$Y$12*$F23,IF(AND($U23<>0,$U23<=EG$12),$U$12*$F23,IF(AND($Q23<>0,$Q23<=EG$12),$Q$12*$F23,IF(AND($M23<>0,$M23<=EG$12),$M$12*$F23,IF(AND($J23<>0,$J23<=EG$12),$J$12*$F23,0))))) -> 0.1125
A24: 3.c | B24: W2026I-DNGF-EM-100-PRD-SPC-0005 | C24: Interactive Prototype & User Testing | F24: 0.0175 | H24: 46174 | J24: 46113 | K24: =H24+((O24-H24)*0.5) -> 46181.25 | M24: 46117 | O24: =H24+((W24-H24)*0.5) -> 46188.5 | Q24: 46119 | S24: =O24+((W24-O24)*0.5) -> 46195.75 | U24: 46122 | W24: 46203 | Y24: 46126 | AE24: =AN24 -> 0.0175 | AG24: =IF(AND($Y24<>0,$Y24<=$BL$6),$Y$12,IF(AND($U24<>0,$U24<=$BL$6),$U$12,IF(AND($Q24<>0,$Q24<=$BL$6),$Q$12,IF(AND($M24<>0,$M24<=$BL$6),$M$12,IF(AND($J24<>0,$J24<=$BL$6),$J$12,0))))) -> 1 | AH24: =AI24-AG24 -> 0 | AI24: =IF(AND($Y24<>0,$Y24<=$BL$5),$Y$12,IF(AND($U24<>0,$U24<=$BL$5),$U$12,IF(AND($Q24<>0,$Q24<=$BL$5),$Q$12,IF(AND($M24<>0,$M24<=$BL$5),$M$12,IF(AND($J24<>0,$J24<=$BL$5),$J$12,0))))) -> 1 | AJ24: =IF(AND($W24<>0,$W24<=$BL$5),$W$12,IF(AND($S24<>0,$S24<=$BL$5),$S$12,IF(AND($O24<>0,$O24<=$BL$5),$O$12,IF(AND($K24<>0,$K24<=$BL$5),$K$12,IF(AND($H24<>0,$H24<=$BL$5),$H$12,0))))) -> 1 | AK24: =IF(AND($X24<>0,$X24<=$BL$5),$X$12,IF(AND($T24<>0,$T24<=$BL$5),$T$12,IF(AND($P24<>0,$P24<=$BL$5),$P$12,IF(AND($L24<>0,$L24<=$BL$5),$L$12,IF(AND($I24<>0,$I24<=$BL$5),$I$12,0))))) -> 0 | AL24: =AI24-AJ24 -> 0 | AM24: =AI24-AK24 -> 1 | AN24: =AI24*F24 -> 0.0175 | AO24: =AJ24*F24 -> 0.0175 | AP24: =AK24*F24 -> 0 | AQ24: =AN24-AO24 -> 0 | AZ24: 0.0175 | BD24: 3.c | BE24: =AG24*F24 -> 0.0175 | BF24: =AI24*F24 -> 0.0175 | BG24: =IF(AND($W24<>0,$W24<=$BL$6),$W$12,IF(AND($S24<>0,$S24<=$BL$6),$S$12,IF(AND($O24<>0,$O24<=$BL$6),$O$12,IF(AND($K24<>0,$K24<=$BL$6),$K$12,IF(AND($H24<>0,$H24<=$BL$6),$H$12,0)))))*$F24 -> 0.013125 | BH24: =IF(AND($W24<>0,$W24<=$BL$5),$W$12,IF(AND($S24<>0,$S24<=$BL$5),$S$12,IF(AND($O24<>0,$O24<=$BL$5),$O$12,IF(AND($K24<>0,$K24<=$BL$5),$K$12,IF(AND($H24<>0,$H24<=$BL$5),$H$12,0)))))*$F24 -> 0.0175 | BI24: =IF(AND($X24<>0,$X24<=$BL$6),$X$12,IF(AND($T24<>0,$T24<=$BL$6),$T$12,IF(AND($P24<>0,$P24<=$BL$6),$P$12,IF(AND($L24<>0,$L24<=$BL$6),$L$12,IF(AND($I24<>0,$I24<=$BL$6),$I$12,0)))))*$F24 -> 0 | BJ24: =IF(AND($X24<>0,$X24<=$BL$5),$X$12,IF(AND($T24<>0,$T24<=$BL$5),$T$12,IF(AND($P24<>0,$P24<=$BL$5),$P$12,IF(AND($L24<>0,$L24<=$BL$5),$L$12,IF(AND($I24<>0,$I24<=$BL$5),$I$12,0)))))*$F24 -> 0 | BM24: 0 | BN24: =IF(AND($W24<>0,$W24<=BN$12),$W$12*$F24,IF(AND($S24<>0,$S24<=BN$12),$S$12*$F24,IF(AND($O24<>0,$O24<=BN$12),$O$12*$F24,IF(AND($K24<>0,$K24<=BN$12),$K$12*$F24,IF(AND($H24<>0,$H24<=BN$12),$H$12*$F24,0))))) -> 0 | BO24: =IF(AND($W24<>0,$W24<=BO$12),$W$12*$F24,IF(AND($S24<>0,$S24<=BO$12),$S$12*$F24,IF(AND($O24<>0,$O24<=BO$12),$O$12*$F24,IF(AND($K24<>0,$K24<=BO$12),$K$12*$F24,IF(AND($H24<>0,$H24<=BO$12),$H$12*$F24,0))))) -> 0 | BP24: =IF(AND($W24<>0,$W24<=BP$12),$W$12*$F24,IF(AND($S24<>0,$S24<=BP$12),$S$12*$F24,IF(AND($O24<>0,$O24<=BP$12),$O$12*$F24,IF(AND($K24<>0,$K24<=BP$12),$K$12*$F24,IF(AND($H24<>0,$H24<=BP$12),$H$12*$F24,0))))) -> 0 | BQ24: =IF(AND($W24<>0,$W24<=BQ$12),$W$12*$F24,IF(AND($S24<>0,$S24<=BQ$12),$S$12*$F24,IF(AND($O24<>0,$O24<=BQ$12),$O$12*$F24,IF(AND($K24<>0,$K24<=BQ$12),$K$12*$F24,IF(AND($H24<>0,$H24<=BQ$12),$H$12*$F24,0))))) -> 0 | BR24: =IF(AND($W24<>0,$W24<=BR$12),$W$12*$F24,IF(AND($S24<>0,$S24<=BR$12),$S$12*$F24,IF(AND($O24<>0,$O24<=BR$12),$O$12*$F24,IF(AND($K24<>0,$K24<=BR$12),$K$12*$F24,IF(AND($H24<>0,$H24<=BR$12),$H$12*$F24,0))))) -> 0 | BS24: =IF(AND($W24<>0,$W24<=BS$12),$W$12*$F24,IF(AND($S24<>0,$S24<=BS$12),$S$12*$F24,IF(AND($O24<>0,$O24<=BS$12),$O$12*$F24,IF(AND($K24<>0,$K24<=BS$12),$K$12*$F24,IF(AND($H24<>0,$H24<=BS$12),$H$12*$F24,0))))) -> 0 | BT24: =IF(AND($W24<>0,$W24<=BT$12),$W$12*$F24,IF(AND($S24<>0,$S24<=BT$12),$S$12*$F24,IF(AND($O24<>0,$O24<=BT$12),$O$12*$F24,IF(AND($K24<>0,$K24<=BT$12),$K$12*$F24,IF(AND($H24<>0,$H24<=BT$12),$H$12*$F24,0))))) -> 0 | BU24: =IF(AND($W24<>0,$W24<=BU$12),$W$12*$F24,IF(AND($S24<>0,$S24<=BU$12),$S$12*$F24,IF(AND($O24<>0,$O24<=BU$12),$O$12*$F24,IF(AND($K24<>0,$K24<=BU$12),$K$12*$F24,IF(AND($H24<>0,$H24<=BU$12),$H$12*$F24,0))))) -> 0 | ... CH24: =IF(AND($W24<>0,$W24<=CH$12),$W$12*$F24,IF(AND($S24<>0,$S24<=CH$12),$S$12*$F24,IF(AND($O24<>0,$O24<=CH$12),$O$12*$F24,IF(AND($K24<>0,$K24<=CH$12),$K$12*$F24,IF(AND($H24<>0,$H24<=CH$12),$H$12*$F24,0))))) -> 0.0175 | CL24: 0 | CM24: =IF(AND($X24<>0,$X24<=CM$12),$X$12*$F24,IF(AND($T24<>0,$T24<=CM$12),$T$12*$F24,IF(AND($P24<>0,$P24<=CM$12),$P$12*$F24,IF(AND($L24<>0,$L24<=CM$12),$L$12*$F24,IF(AND($I24<>0,$I24<=CM$12),$I$12*$F24,0))))) -> 0 | CN24: =IF(AND($X24<>0,$X24<=CN$12),$X$12*$F24,IF(AND($T24<>0,$T24<=CN$12),$T$12*$F24,IF(AND($P24<>0,$P24<=CN$12),$P$12*$F24,IF(AND($L24<>0,$L24<=CN$12),$L$12*$F24,IF(AND($I24<>0,$I24<=CN$12),$I$12*$F24,0))))) -> 0 | CO24: =IF(AND($X24<>0,$X24<=CO$12),$X$12*$F24,IF(AND($T24<>0,$T24<=CO$12),$T$12*$F24,IF(AND($P24<>0,$P24<=CO$12),$P$12*$F24,IF(AND($L24<>0,$L24<=CO$12),$L$12*$F24,IF(AND($I24<>0,$I24<=CO$12),$I$12*$F24,0))))) -> 0 | CP24: =IF(AND($X24<>0,$X24<=CP$12),$X$12*$F24,IF(AND($T24<>0,$T24<=CP$12),$T$12*$F24,IF(AND($P24<>0,$P24<=CP$12),$P$12*$F24,IF(AND($L24<>0,$L24<=CP$12),$L$12*$F24,IF(AND($I24<>0,$I24<=CP$12),$I$12*$F24,0))))) -> 0 | CQ24: =IF(AND($X24<>0,$X24<=CQ$12),$X$12*$F24,IF(AND($T24<>0,$T24<=CQ$12),$T$12*$F24,IF(AND($P24<>0,$P24<=CQ$12),$P$12*$F24,IF(AND($L24<>0,$L24<=CQ$12),$L$12*$F24,IF(AND($I24<>0,$I24<=CQ$12),$I$12*$F24,0))))) -> 0 | CR24: =IF(AND($X24<>0,$X24<=CR$12),$X$12*$F24,IF(AND($T24<>0,$T24<=CR$12),$T$12*$F24,IF(AND($P24<>0,$P24<=CR$12),$P$12*$F24,IF(AND($L24<>0,$L24<=CR$12),$L$12*$F24,IF(AND($I24<>0,$I24<=CR$12),$I$12*$F24,0))))) -> 0 | CS24: =IF(AND($X24<>0,$X24<=CS$12),$X$12*$F24,IF(AND($T24<>0,$T24<=CS$12),$T$12*$F24,IF(AND($P24<>0,$P24<=CS$12),$P$12*$F24,IF(AND($L24<>0,$L24<=CS$12),$L$12*$F24,IF(AND($I24<>0,$I24<=CS$12),$I$12*$F24,0))))) -> 0 | CT24: =IF(AND($X24<>0,$X24<=CT$12),$X$12*$F24,IF(AND($T24<>0,$T24<=CT$12),$T$12*$F24,IF(AND($P24<>0,$P24<=CT$12),$P$12*$F24,IF(AND($L24<>0,$L24<=CT$12),$L$12*$F24,IF(AND($I24<>0,$I24<=CT$12),$I$12*$F24,0))))) -> 0 | ... DG24: =IF(AND($X24<>0,$X24<=DG$12),$X$12*$F24,IF(AND($T24<>0,$T24<=DG$12),$T$12*$F24,IF(AND($P24<>0,$P24<=DG$12),$P$12*$F24,IF(AND($L24<>0,$L24<=DG$12),$L$12*$F24,IF(AND($I24<>0,$I24<=DG$12),$I$12*$F24,0))))) -> 0 | DL24: 0 | DM24: =IF(AND($Y24<>0,$Y24<=DM$12),$Y$12*$F24,IF(AND($U24<>0,$U24<=DM$12),$U$12*$F24,IF(AND($Q24<>0,$Q24<=DM$12),$Q$12*$F24,IF(AND($M24<>0,$M24<=DM$12),$M$12*$F24,IF(AND($J24<>0,$J24<=DM$12),$J$12*$F24,0))))) -> 0.013125 | DN24: =IF(AND($Y24<>0,$Y24<=DN$12),$Y$12*$F24,IF(AND($U24<>0,$U24<=DN$12),$U$12*$F24,IF(AND($Q24<>0,$Q24<=DN$12),$Q$12*$F24,IF(AND($M24<>0,$M24<=DN$12),$M$12*$F24,IF(AND($J24<>0,$J24<=DN$12),$J$12*$F24,0))))) -> 0.0175 | DO24: =IF(AND($Y24<>0,$Y24<=DO$12),$Y$12*$F24,IF(AND($U24<>0,$U24<=DO$12),$U$12*$F24,IF(AND($Q24<>0,$Q24<=DO$12),$Q$12*$F24,IF(AND($M24<>0,$M24<=DO$12),$M$12*$F24,IF(AND($J24<>0,$J24<=DO$12),$J$12*$F24,0))))) -> 0.0175 | DP24: =IF(AND($Y24<>0,$Y24<=DP$12),$Y$12*$F24,IF(AND($U24<>0,$U24<=DP$12),$U$12*$F24,IF(AND($Q24<>0,$Q24<=DP$12),$Q$12*$F24,IF(AND($M24<>0,$M24<=DP$12),$M$12*$F24,IF(AND($J24<>0,$J24<=DP$12),$J$12*$F24,0))))) -> 0.0175 | DQ24: =IF(AND($Y24<>0,$Y24<=DQ$12),$Y$12*$F24,IF(AND($U24<>0,$U24<=DQ$12),$U$12*$F24,IF(AND($Q24<>0,$Q24<=DQ$12),$Q$12*$F24,IF(AND($M24<>0,$M24<=DQ$12),$M$12*$F24,IF(AND($J24<>0,$J24<=DQ$12),$J$12*$F24,0))))) -> 0.0175 | DR24: =IF(AND($Y24<>0,$Y24<=DR$12),$Y$12*$F24,IF(AND($U24<>0,$U24<=DR$12),$U$12*$F24,IF(AND($Q24<>0,$Q24<=DR$12),$Q$12*$F24,IF(AND($M24<>0,$M24<=DR$12),$M$12*$F24,IF(AND($J24<>0,$J24<=DR$12),$J$12*$F24,0))))) -> 0.0175 | DS24: =IF(AND($Y24<>0,$Y24<=DS$12),$Y$12*$F24,IF(AND($U24<>0,$U24<=DS$12),$U$12*$F24,IF(AND($Q24<>0,$Q24<=DS$12),$Q$12*$F24,IF(AND($M24<>0,$M24<=DS$12),$M$12*$F24,IF(AND($J24<>0,$J24<=DS$12),$J$12*$F24,0))))) -> 0.0175 | DT24: =IF(AND($Y24<>0,$Y24<=DT$12),$Y$12*$F24,IF(AND($U24<>0,$U24<=DT$12),$U$12*$F24,IF(AND($Q24<>0,$Q24<=DT$12),$Q$12*$F24,IF(AND($M24<>0,$M24<=DT$12),$M$12*$F24,IF(AND($J24<>0,$J24<=DT$12),$J$12*$F24,0))))) -> 0.0175 | ... EG24: =IF(AND($Y24<>0,$Y24<=EG$12),$Y$12*$F24,IF(AND($U24<>0,$U24<=EG$12),$U$12*$F24,IF(AND($Q24<>0,$Q24<=EG$12),$Q$12*$F24,IF(AND($M24<>0,$M24<=EG$12),$M$12*$F24,IF(AND($J24<>0,$J24<=EG$12),$J$12*$F24,0))))) -> 0.0175
A25: 4 | C25: Integrasi Sumber Data; Konfigurasi database dengan sumber data; Data Connection Schema & Production Data Mapping | F25: =SUBTOTAL(9,F26:F28) -> 0.1854 | AZ25: 0.1854 | BD25: 4 | BE25: =SUBTOTAL(9,BE26:BE28) -> 0.1854 | BF25: =SUBTOTAL(9,BF26:BF28) -> 0.1854 | BG25: =SUBTOTAL(9,BG26:BG28) -> 0.1854 | BH25: =SUBTOTAL(9,BH26:BH28) -> 0.1854 | BI25: =SUBTOTAL(9,BI26:BI28) -> 0 | BJ25: =SUBTOTAL(9,BJ26:BJ28) -> 0 | BM25: =SUBTOTAL(9,BM26:BM28) -> 0 | BN25: =SUBTOTAL(9,BN26:BN28) -> 0 | BO25: =SUBTOTAL(9,BO26:BO28) -> 0 | BP25: =SUBTOTAL(9,BP26:BP28) -> 0 | BQ25: =SUBTOTAL(9,BQ26:BQ28) -> 0.007385 | BR25: =SUBTOTAL(9,BR26:BR28) -> 0.018385 | BS25: =SUBTOTAL(9,BS26:BS28) -> 0.050675 | BT25: =SUBTOTAL(9,BT26:BT28) -> 0.0876 | ... CH25: =SUBTOTAL(9,CH26:CH28) -> 0.1854 | CL25: =SUBTOTAL(9,CL26:CL28) -> 0 | CM25: =SUBTOTAL(9,CM26:CM28) -> 0 | CN25: =SUBTOTAL(9,CN26:CN28) -> 0 | CO25: =SUBTOTAL(9,CO26:CO28) -> 0 | CP25: =SUBTOTAL(9,CP26:CP28) -> 0 | CQ25: =SUBTOTAL(9,CQ26:CQ28) -> 0 | CR25: =SUBTOTAL(9,CR26:CR28) -> 0 | CS25: =SUBTOTAL(9,CS26:CS28) -> 0 | ... DG25: =SUBTOTAL(9,DG26:DG28) -> 0 | DL25: =SUBTOTAL(9,DL26:DL28) -> 0 | DM25: =SUBTOTAL(9,DM26:DM28) -> 0.04635 | DN25: =SUBTOTAL(9,DN26:DN28) -> 0.0927 | DO25: =SUBTOTAL(9,DO26:DO28) -> 0.10645 | DP25: =SUBTOTAL(9,DP26:DP28) -> 0.10645 | DQ25: =SUBTOTAL(9,DQ26:DQ28) -> 0.10645 | DR25: =SUBTOTAL(9,DR26:DR28) -> 0.10645 | DS25: =SUBTOTAL(9,DS26:DS28) -> 0.115875 | ... EG25: =SUBTOTAL(9,EG26:EG28) -> 0.1854
A26: 4.a | B26: W2026I-DNGF-EM-100-PRD-SPC-0006 | C26: Integrasi Sumber Data | F26: =F27+F28 -> 0.0927 | H26: 46143 | J26: 46117 | K26: =H26+((O26-H26)*0.5) -> 46154 | M26: 46124 | O26: =H26+((W26-H26)*0.5) -> 46165 | Q26: 46127 | S26: =O26+((W26-O26)*0.5) -> 46176 | U26: 46174 | W26: 46187 | Y26: 46184 | AE26: =AN26 -> 0.0927 | AG26: =IF(AND($Y26<>0,$Y26<=$BL$6),$Y$12,IF(AND($U26<>0,$U26<=$BL$6),$U$12,IF(AND($Q26<>0,$Q26<=$BL$6),$Q$12,IF(AND($M26<>0,$M26<=$BL$6),$M$12,IF(AND($J26<>0,$J26<=$BL$6),$J$12,0))))) -> 1 | AH26: =AI26-AG26 -> 0 | AI26: =IF(AND($Y26<>0,$Y26<=$BL$5),$Y$12,IF(AND($U26<>0,$U26<=$BL$5),$U$12,IF(AND($Q26<>0,$Q26<=$BL$5),$Q$12,IF(AND($M26<>0,$M26<=$BL$5),$M$12,IF(AND($J26<>0,$J26<=$BL$5),$J$12,0))))) -> 1 | AJ26: =IF(AND($W26<>0,$W26<=$BL$5),$W$12,IF(AND($S26<>0,$S26<=$BL$5),$S$12,IF(AND($O26<>0,$O26<=$BL$5),$O$12,IF(AND($K26<>0,$K26<=$BL$5),$K$12,IF(AND($H26<>0,$H26<=$BL$5),$H$12,0))))) -> 1 | AK26: =IF(AND($X26<>0,$X26<=$BL$5),$X$12,IF(AND($T26<>0,$T26<=$BL$5),$T$12,IF(AND($P26<>0,$P26<=$BL$5),$P$12,IF(AND($L26<>0,$L26<=$BL$5),$L$12,IF(AND($I26<>0,$I26<=$BL$5),$I$12,0))))) -> 0 | AL26: =AI26-AJ26 -> 0 | AM26: =AI26-AK26 -> 1 | AN26: =AI26*F26 -> 0.0927 | AO26: =AJ26*F26 -> 0.0927 | AP26: =AK26*F26 -> 0 | AQ26: =AN26-AO26 -> 0 | AZ26: 0.0927 | BD26: 4.a | BE26: =AG26*F26 -> 0.0927 | BF26: =AI26*F26 -> 0.0927 | BG26: =IF(AND($W26<>0,$W26<=$BL$6),$W$12,IF(AND($S26<>0,$S26<=$BL$6),$S$12,IF(AND($O26<>0,$O26<=$BL$6),$O$12,IF(AND($K26<>0,$K26<=$BL$6),$K$12,IF(AND($H26<>0,$H26<=$BL$6),$H$12,0)))))*$F26 -> 0.0927 | BH26: =IF(AND($W26<>0,$W26<=$BL$5),$W$12,IF(AND($S26<>0,$S26<=$BL$5),$S$12,IF(AND($O26<>0,$O26<=$BL$5),$O$12,IF(AND($K26<>0,$K26<=$BL$5),$K$12,IF(AND($H26<>0,$H26<=$BL$5),$H$12,0)))))*$F26 -> 0.0927 | BI26: =IF(AND($X26<>0,$X26<=$BL$6),$X$12,IF(AND($T26<>0,$T26<=$BL$6),$T$12,IF(AND($P26<>0,$P26<=$BL$6),$P$12,IF(AND($L26<>0,$L26<=$BL$6),$L$12,IF(AND($I26<>0,$I26<=$BL$6),$I$12,0)))))*$F26 -> 0 | BJ26: =IF(AND($X26<>0,$X26<=$BL$5),$X$12,IF(AND($T26<>0,$T26<=$BL$5),$T$12,IF(AND($P26<>0,$P26<=$BL$5),$P$12,IF(AND($L26<>0,$L26<=$BL$5),$L$12,IF(AND($I26<>0,$I26<=$BL$5),$I$12,0)))))*$F26 -> 0 | BM26: 0 | BN26: =IF(AND($W26<>0,$W26<=BN$12),$W$12*$F26,IF(AND($S26<>0,$S26<=BN$12),$S$12*$F26,IF(AND($O26<>0,$O26<=BN$12),$O$12*$F26,IF(AND($K26<>0,$K26<=BN$12),$K$12*$F26,IF(AND($H26<>0,$H26<=BN$12),$H$12*$F26,0))))) -> 0 | BO26: =IF(AND($W26<>0,$W26<=BO$12),$W$12*$F26,IF(AND($S26<>0,$S26<=BO$12),$S$12*$F26,IF(AND($O26<>0,$O26<=BO$12),$O$12*$F26,IF(AND($K26<>0,$K26<=BO$12),$K$12*$F26,IF(AND($H26<>0,$H26<=BO$12),$H$12*$F26,0))))) -> 0 | BP26: =IF(AND($W26<>0,$W26<=BP$12),$W$12*$F26,IF(AND($S26<>0,$S26<=BP$12),$S$12*$F26,IF(AND($O26<>0,$O26<=BP$12),$O$12*$F26,IF(AND($K26<>0,$K26<=BP$12),$K$12*$F26,IF(AND($H26<>0,$H26<=BP$12),$H$12*$F26,0))))) -> 0 | BQ26: =IF(AND($W26<>0,$W26<=BQ$12),$W$12*$F26,IF(AND($S26<>0,$S26<=BQ$12),$S$12*$F26,IF(AND($O26<>0,$O26<=BQ$12),$O$12*$F26,IF(AND($K26<>0,$K26<=BQ$12),$K$12*$F26,IF(AND($H26<>0,$H26<=BQ$12),$H$12*$F26,0))))) -> 0.004635 | BR26: =IF(AND($W26<>0,$W26<=BR$12),$W$12*$F26,IF(AND($S26<>0,$S26<=BR$12),$S$12*$F26,IF(AND($O26<>0,$O26<=BR$12),$O$12*$F26,IF(AND($K26<>0,$K26<=BR$12),$K$12*$F26,IF(AND($H26<>0,$H26<=BR$12),$H$12*$F26,0))))) -> 0.004635 | BS26: =IF(AND($W26<>0,$W26<=BS$12),$W$12*$F26,IF(AND($S26<>0,$S26<=BS$12),$S$12*$F26,IF(AND($O26<>0,$O26<=BS$12),$O$12*$F26,IF(AND($K26<>0,$K26<=BS$12),$K$12*$F26,IF(AND($H26<>0,$H26<=BS$12),$H$12*$F26,0))))) -> 0.023175 | BT26: =IF(AND($W26<>0,$W26<=BT$12),$W$12*$F26,IF(AND($S26<>0,$S26<=BT$12),$S$12*$F26,IF(AND($O26<>0,$O26<=BT$12),$O$12*$F26,IF(AND($K26<>0,$K26<=BT$12),$K$12*$F26,IF(AND($H26<>0,$H26<=BT$12),$H$12*$F26,0))))) -> 0.04635 | BU26: =IF(AND($W26<>0,$W26<=BU$12),$W$12*$F26,IF(AND($S26<>0,$S26<=BU$12),$S$12*$F26,IF(AND($O26<>0,$O26<=BU$12),$O$12*$F26,IF(AND($K26<>0,$K26<=BU$12),$K$12*$F26,IF(AND($H26<>0,$H26<=BU$12),$H$12*$F26,0))))) -> 0.04635 | ... CH26: =IF(AND($W26<>0,$W26<=CH$12),$W$12*$F26,IF(AND($S26<>0,$S26<=CH$12),$S$12*$F26,IF(AND($O26<>0,$O26<=CH$12),$O$12*$F26,IF(AND($K26<>0,$K26<=CH$12),$K$12*$F26,IF(AND($H26<>0,$H26<=CH$12),$H$12*$F26,0))))) -> 0.0927 | CL26: 0 | CM26: =IF(AND($X26<>0,$X26<=CM$12),$X$12*$F26,IF(AND($T26<>0,$T26<=CM$12),$T$12*$F26,IF(AND($P26<>0,$P26<=CM$12),$P$12*$F26,IF(AND($L26<>0,$L26<=CM$12),$L$12*$F26,IF(AND($I26<>0,$I26<=CM$12),$I$12*$F26,0))))) -> 0 | CN26: =IF(AND($X26<>0,$X26<=CN$12),$X$12*$F26,IF(AND($T26<>0,$T26<=CN$12),$T$12*$F26,IF(AND($P26<>0,$P26<=CN$12),$P$12*$F26,IF(AND($L26<>0,$L26<=CN$12),$L$12*$F26,IF(AND($I26<>0,$I26<=CN$12),$I$12*$F26,0))))) -> 0 | CO26: =IF(AND($X26<>0,$X26<=CO$12),$X$12*$F26,IF(AND($T26<>0,$T26<=CO$12),$T$12*$F26,IF(AND($P26<>0,$P26<=CO$12),$P$12*$F26,IF(AND($L26<>0,$L26<=CO$12),$L$12*$F26,IF(AND($I26<>0,$I26<=CO$12),$I$12*$F26,0))))) -> 0 | CP26: =IF(AND($X26<>0,$X26<=CP$12),$X$12*$F26,IF(AND($T26<>0,$T26<=CP$12),$T$12*$F26,IF(AND($P26<>0,$P26<=CP$12),$P$12*$F26,IF(AND($L26<>0,$L26<=CP$12),$L$12*$F26,IF(AND($I26<>0,$I26<=CP$12),$I$12*$F26,0))))) -> 0 | CQ26: =IF(AND($X26<>0,$X26<=CQ$12),$X$12*$F26,IF(AND($T26<>0,$T26<=CQ$12),$T$12*$F26,IF(AND($P26<>0,$P26<=CQ$12),$P$12*$F26,IF(AND($L26<>0,$L26<=CQ$12),$L$12*$F26,IF(AND($I26<>0,$I26<=CQ$12),$I$12*$F26,0))))) -> 0 | CR26: =IF(AND($X26<>0,$X26<=CR$12),$X$12*$F26,IF(AND($T26<>0,$T26<=CR$12),$T$12*$F26,IF(AND($P26<>0,$P26<=CR$12),$P$12*$F26,IF(AND($L26<>0,$L26<=CR$12),$L$12*$F26,IF(AND($I26<>0,$I26<=CR$12),$I$12*$F26,0))))) -> 0 | CS26: =IF(AND($X26<>0,$X26<=CS$12),$X$12*$F26,IF(AND($T26<>0,$T26<=CS$12),$T$12*$F26,IF(AND($P26<>0,$P26<=CS$12),$P$12*$F26,IF(AND($L26<>0,$L26<=CS$12),$L$12*$F26,IF(AND($I26<>0,$I26<=CS$12),$I$12*$F26,0))))) -> 0 | CT26: =IF(AND($X26<>0,$X26<=CT$12),$X$12*$F26,IF(AND($T26<>0,$T26<=CT$12),$T$12*$F26,IF(AND($P26<>0,$P26<=CT$12),$P$12*$F26,IF(AND($L26<>0,$L26<=CT$12),$L$12*$F26,IF(AND($I26<>0,$I26<=CT$12),$I$12*$F26,0))))) -> 0 | ... DG26: =IF(AND($X26<>0,$X26<=DG$12),$X$12*$F26,IF(AND($T26<>0,$T26<=DG$12),$T$12*$F26,IF(AND($P26<>0,$P26<=DG$12),$P$12*$F26,IF(AND($L26<>0,$L26<=DG$12),$L$12*$F26,IF(AND($I26<>0,$I26<=DG$12),$I$12*$F26,0))))) -> 0 | DL26: 0 | DM26: =IF(AND($Y26<>0,$Y26<=DM$12),$Y$12*$F26,IF(AND($U26<>0,$U26<=DM$12),$U$12*$F26,IF(AND($Q26<>0,$Q26<=DM$12),$Q$12*$F26,IF(AND($M26<>0,$M26<=DM$12),$M$12*$F26,IF(AND($J26<>0,$J26<=DM$12),$J$12*$F26,0))))) -> 0.023175 | DN26: =IF(AND($Y26<>0,$Y26<=DN$12),$Y$12*$F26,IF(AND($U26<>0,$U26<=DN$12),$U$12*$F26,IF(AND($Q26<>0,$Q26<=DN$12),$Q$12*$F26,IF(AND($M26<>0,$M26<=DN$12),$M$12*$F26,IF(AND($J26<>0,$J26<=DN$12),$J$12*$F26,0))))) -> 0.04635 | DO26: =IF(AND($Y26<>0,$Y26<=DO$12),$Y$12*$F26,IF(AND($U26<>0,$U26<=DO$12),$U$12*$F26,IF(AND($Q26<>0,$Q26<=DO$12),$Q$12*$F26,IF(AND($M26<>0,$M26<=DO$12),$M$12*$F26,IF(AND($J26<>0,$J26<=DO$12),$J$12*$F26,0))))) -> 0.04635 | DP26: =IF(AND($Y26<>0,$Y26<=DP$12),$Y$12*$F26,IF(AND($U26<>0,$U26<=DP$12),$U$12*$F26,IF(AND($Q26<>0,$Q26<=DP$12),$Q$12*$F26,IF(AND($M26<>0,$M26<=DP$12),$M$12*$F26,IF(AND($J26<>0,$J26<=DP$12),$J$12*$F26,0))))) -> 0.04635 | DQ26: =IF(AND($Y26<>0,$Y26<=DQ$12),$Y$12*$F26,IF(AND($U26<>0,$U26<=DQ$12),$U$12*$F26,IF(AND($Q26<>0,$Q26<=DQ$12),$Q$12*$F26,IF(AND($M26<>0,$M26<=DQ$12),$M$12*$F26,IF(AND($J26<>0,$J26<=DQ$12),$J$12*$F26,0))))) -> 0.04635 | DR26: =IF(AND($Y26<>0,$Y26<=DR$12),$Y$12*$F26,IF(AND($U26<>0,$U26<=DR$12),$U$12*$F26,IF(AND($Q26<>0,$Q26<=DR$12),$Q$12*$F26,IF(AND($M26<>0,$M26<=DR$12),$M$12*$F26,IF(AND($J26<>0,$J26<=DR$12),$J$12*$F26,0))))) -> 0.04635 | DS26: =IF(AND($Y26<>0,$Y26<=DS$12),$Y$12*$F26,IF(AND($U26<>0,$U26<=DS$12),$U$12*$F26,IF(AND($Q26<>0,$Q26<=DS$12),$Q$12*$F26,IF(AND($M26<>0,$M26<=DS$12),$M$12*$F26,IF(AND($J26<>0,$J26<=DS$12),$J$12*$F26,0))))) -> 0.04635 | DT26: =IF(AND($Y26<>0,$Y26<=DT$12),$Y$12*$F26,IF(AND($U26<>0,$U26<=DT$12),$U$12*$F26,IF(AND($Q26<>0,$Q26<=DT$12),$Q$12*$F26,IF(AND($M26<>0,$M26<=DT$12),$M$12*$F26,IF(AND($J26<>0,$J26<=DT$12),$J$12*$F26,0))))) -> 0.04635 | ... EG26: =IF(AND($Y26<>0,$Y26<=EG$12),$Y$12*$F26,IF(AND($U26<>0,$U26<=EG$12),$U$12*$F26,IF(AND($Q26<>0,$Q26<=EG$12),$Q$12*$F26,IF(AND($M26<>0,$M26<=EG$12),$M$12*$F26,IF(AND($J26<>0,$J26<=EG$12),$J$12*$F26,0))))) -> 0.0927
A27: 4.b | B27: W2026I-DNGF-EM-100-PRD-SPC-0007 | C27: Konfigurasi database dengan sumber data | F27: 0.055 | H27: 46143 | J27: 46117 | K27: =H27+((O27-H27)*0.5) -> 46150.5 | M27: 46124 | O27: =H27+((W27-H27)*0.5) -> 46158 | Q27: 46127 | S27: =O27+((W27-O27)*0.5) -> 46165.5 | U27: 46135 | W27: 46173 | Y27: 46173 | AE27: =AN27 -> 0.055 | AG27: =IF(AND($Y27<>0,$Y27<=$BL$6),$Y$12,IF(AND($U27<>0,$U27<=$BL$6),$U$12,IF(AND($Q27<>0,$Q27<=$BL$6),$Q$12,IF(AND($M27<>0,$M27<=$BL$6),$M$12,IF(AND($J27<>0,$J27<=$BL$6),$J$12,0))))) -> 1 | AH27: =AI27-AG27 -> 0 | AI27: =IF(AND($Y27<>0,$Y27<=$BL$5),$Y$12,IF(AND($U27<>0,$U27<=$BL$5),$U$12,IF(AND($Q27<>0,$Q27<=$BL$5),$Q$12,IF(AND($M27<>0,$M27<=$BL$5),$M$12,IF(AND($J27<>0,$J27<=$BL$5),$J$12,0))))) -> 1 | AJ27: =IF(AND($W27<>0,$W27<=$BL$5),$W$12,IF(AND($S27<>0,$S27<=$BL$5),$S$12,IF(AND($O27<>0,$O27<=$BL$5),$O$12,IF(AND($K27<>0,$K27<=$BL$5),$K$12,IF(AND($H27<>0,$H27<=$BL$5),$H$12,0))))) -> 1 | AK27: =IF(AND($X27<>0,$X27<=$BL$5),$X$12,IF(AND($T27<>0,$T27<=$BL$5),$T$12,IF(AND($P27<>0,$P27<=$BL$5),$P$12,IF(AND($L27<>0,$L27<=$BL$5),$L$12,IF(AND($I27<>0,$I27<=$BL$5),$I$12,0))))) -> 0 | AL27: =AI27-AJ27 -> 0 | AM27: =AI27-AK27 -> 1 | AN27: =AI27*F27 -> 0.055 | AO27: =AJ27*F27 -> 0.055 | AP27: =AK27*F27 -> 0 | AQ27: =AN27-AO27 -> 0 | AZ27: 0.055 | BD27: 4.b | BE27: =AG27*F27 -> 0.055 | BF27: =AI27*F27 -> 0.055 | BG27: =IF(AND($W27<>0,$W27<=$BL$6),$W$12,IF(AND($S27<>0,$S27<=$BL$6),$S$12,IF(AND($O27<>0,$O27<=$BL$6),$O$12,IF(AND($K27<>0,$K27<=$BL$6),$K$12,IF(AND($H27<>0,$H27<=$BL$6),$H$12,0)))))*$F27 -> 0.055 | BH27: =IF(AND($W27<>0,$W27<=$BL$5),$W$12,IF(AND($S27<>0,$S27<=$BL$5),$S$12,IF(AND($O27<>0,$O27<=$BL$5),$O$12,IF(AND($K27<>0,$K27<=$BL$5),$K$12,IF(AND($H27<>0,$H27<=$BL$5),$H$12,0)))))*$F27 -> 0.055 | BI27: =IF(AND($X27<>0,$X27<=$BL$6),$X$12,IF(AND($T27<>0,$T27<=$BL$6),$T$12,IF(AND($P27<>0,$P27<=$BL$6),$P$12,IF(AND($L27<>0,$L27<=$BL$6),$L$12,IF(AND($I27<>0,$I27<=$BL$6),$I$12,0)))))*$F27 -> 0 | BJ27: =IF(AND($X27<>0,$X27<=$BL$5),$X$12,IF(AND($T27<>0,$T27<=$BL$5),$T$12,IF(AND($P27<>0,$P27<=$BL$5),$P$12,IF(AND($L27<>0,$L27<=$BL$5),$L$12,IF(AND($I27<>0,$I27<=$BL$5),$I$12,0)))))*$F27 -> 0 | BM27: 0 | BN27: =IF(AND($W27<>0,$W27<=BN$12),$W$12*$F27,IF(AND($S27<>0,$S27<=BN$12),$S$12*$F27,IF(AND($O27<>0,$O27<=BN$12),$O$12*$F27,IF(AND($K27<>0,$K27<=BN$12),$K$12*$F27,IF(AND($H27<>0,$H27<=BN$12),$H$12*$F27,0))))) -> 0 | BO27: =IF(AND($W27<>0,$W27<=BO$12),$W$12*$F27,IF(AND($S27<>0,$S27<=BO$12),$S$12*$F27,IF(AND($O27<>0,$O27<=BO$12),$O$12*$F27,IF(AND($K27<>0,$K27<=BO$12),$K$12*$F27,IF(AND($H27<>0,$H27<=BO$12),$H$12*$F27,0))))) -> 0 | BP27: =IF(AND($W27<>0,$W27<=BP$12),$W$12*$F27,IF(AND($S27<>0,$S27<=BP$12),$S$12*$F27,IF(AND($O27<>0,$O27<=BP$12),$O$12*$F27,IF(AND($K27<>0,$K27<=BP$12),$K$12*$F27,IF(AND($H27<>0,$H27<=BP$12),$H$12*$F27,0))))) -> 0 | BQ27: =IF(AND($W27<>0,$W27<=BQ$12),$W$12*$F27,IF(AND($S27<>0,$S27<=BQ$12),$S$12*$F27,IF(AND($O27<>0,$O27<=BQ$12),$O$12*$F27,IF(AND($K27<>0,$K27<=BQ$12),$K$12*$F27,IF(AND($H27<>0,$H27<=BQ$12),$H$12*$F27,0))))) -> 0.00275 | BR27: =IF(AND($W27<>0,$W27<=BR$12),$W$12*$F27,IF(AND($S27<>0,$S27<=BR$12),$S$12*$F27,IF(AND($O27<>0,$O27<=BR$12),$O$12*$F27,IF(AND($K27<>0,$K27<=BR$12),$K$12*$F27,IF(AND($H27<>0,$H27<=BR$12),$H$12*$F27,0))))) -> 0.01375 | BS27: =IF(AND($W27<>0,$W27<=BS$12),$W$12*$F27,IF(AND($S27<>0,$S27<=BS$12),$S$12*$F27,IF(AND($O27<>0,$O27<=BS$12),$O$12*$F27,IF(AND($K27<>0,$K27<=BS$12),$K$12*$F27,IF(AND($H27<>0,$H27<=BS$12),$H$12*$F27,0))))) -> 0.0275 | BT27: =IF(AND($W27<>0,$W27<=BT$12),$W$12*$F27,IF(AND($S27<>0,$S27<=BT$12),$S$12*$F27,IF(AND($O27<>0,$O27<=BT$12),$O$12*$F27,IF(AND($K27<>0,$K27<=BT$12),$K$12*$F27,IF(AND($H27<>0,$H27<=BT$12),$H$12*$F27,0))))) -> 0.04125 | BU27: =IF(AND($W27<>0,$W27<=BU$12),$W$12*$F27,IF(AND($S27<>0,$S27<=BU$12),$S$12*$F27,IF(AND($O27<>0,$O27<=BU$12),$O$12*$F27,IF(AND($K27<>0,$K27<=BU$12),$K$12*$F27,IF(AND($H27<>0,$H27<=BU$12),$H$12*$F27,0))))) -> 0.055 | ... CH27: =IF(AND($W27<>0,$W27<=CH$12),$W$12*$F27,IF(AND($S27<>0,$S27<=CH$12),$S$12*$F27,IF(AND($O27<>0,$O27<=CH$12),$O$12*$F27,IF(AND($K27<>0,$K27<=CH$12),$K$12*$F27,IF(AND($H27<>0,$H27<=CH$12),$H$12*$F27,0))))) -> 0.055 | CL27: 0 | CM27: =IF(AND($X27<>0,$X27<=CM$12),$X$12*$F27,IF(AND($T27<>0,$T27<=CM$12),$T$12*$F27,IF(AND($P27<>0,$P27<=CM$12),$P$12*$F27,IF(AND($L27<>0,$L27<=CM$12),$L$12*$F27,IF(AND($I27<>0,$I27<=CM$12),$I$12*$F27,0))))) -> 0 | CN27: =IF(AND($X27<>0,$X27<=CN$12),$X$12*$F27,IF(AND($T27<>0,$T27<=CN$12),$T$12*$F27,IF(AND($P27<>0,$P27<=CN$12),$P$12*$F27,IF(AND($L27<>0,$L27<=CN$12),$L$12*$F27,IF(AND($I27<>0,$I27<=CN$12),$I$12*$F27,0))))) -> 0 | CO27: =IF(AND($X27<>0,$X27<=CO$12),$X$12*$F27,IF(AND($T27<>0,$T27<=CO$12),$T$12*$F27,IF(AND($P27<>0,$P27<=CO$12),$P$12*$F27,IF(AND($L27<>0,$L27<=CO$12),$L$12*$F27,IF(AND($I27<>0,$I27<=CO$12),$I$12*$F27,0))))) -> 0 | CP27: =IF(AND($X27<>0,$X27<=CP$12),$X$12*$F27,IF(AND($T27<>0,$T27<=CP$12),$T$12*$F27,IF(AND($P27<>0,$P27<=CP$12),$P$12*$F27,IF(AND($L27<>0,$L27<=CP$12),$L$12*$F27,IF(AND($I27<>0,$I27<=CP$12),$I$12*$F27,0))))) -> 0 | CQ27: =IF(AND($X27<>0,$X27<=CQ$12),$X$12*$F27,IF(AND($T27<>0,$T27<=CQ$12),$T$12*$F27,IF(AND($P27<>0,$P27<=CQ$12),$P$12*$F27,IF(AND($L27<>0,$L27<=CQ$12),$L$12*$F27,IF(AND($I27<>0,$I27<=CQ$12),$I$12*$F27,0))))) -> 0 | CR27: =IF(AND($X27<>0,$X27<=CR$12),$X$12*$F27,IF(AND($T27<>0,$T27<=CR$12),$T$12*$F27,IF(AND($P27<>0,$P27<=CR$12),$P$12*$F27,IF(AND($L27<>0,$L27<=CR$12),$L$12*$F27,IF(AND($I27<>0,$I27<=CR$12),$I$12*$F27,0))))) -> 0 | CS27: =IF(AND($X27<>0,$X27<=CS$12),$X$12*$F27,IF(AND($T27<>0,$T27<=CS$12),$T$12*$F27,IF(AND($P27<>0,$P27<=CS$12),$P$12*$F27,IF(AND($L27<>0,$L27<=CS$12),$L$12*$F27,IF(AND($I27<>0,$I27<=CS$12),$I$12*$F27,0))))) -> 0 | CT27: =IF(AND($X27<>0,$X27<=CT$12),$X$12*$F27,IF(AND($T27<>0,$T27<=CT$12),$T$12*$F27,IF(AND($P27<>0,$P27<=CT$12),$P$12*$F27,IF(AND($L27<>0,$L27<=CT$12),$L$12*$F27,IF(AND($I27<>0,$I27<=CT$12),$I$12*$F27,0))))) -> 0 | ... DG27: =IF(AND($X27<>0,$X27<=DG$12),$X$12*$F27,IF(AND($T27<>0,$T27<=DG$12),$T$12*$F27,IF(AND($P27<>0,$P27<=DG$12),$P$12*$F27,IF(AND($L27<>0,$L27<=DG$12),$L$12*$F27,IF(AND($I27<>0,$I27<=DG$12),$I$12*$F27,0))))) -> 0 | DL27: 0 | DM27: =IF(AND($Y27<>0,$Y27<=DM$12),$Y$12*$F27,IF(AND($U27<>0,$U27<=DM$12),$U$12*$F27,IF(AND($Q27<>0,$Q27<=DM$12),$Q$12*$F27,IF(AND($M27<>0,$M27<=DM$12),$M$12*$F27,IF(AND($J27<>0,$J27<=DM$12),$J$12*$F27,0))))) -> 0.01375 | DN27: =IF(AND($Y27<>0,$Y27<=DN$12),$Y$12*$F27,IF(AND($U27<>0,$U27<=DN$12),$U$12*$F27,IF(AND($Q27<>0,$Q27<=DN$12),$Q$12*$F27,IF(AND($M27<>0,$M27<=DN$12),$M$12*$F27,IF(AND($J27<>0,$J27<=DN$12),$J$12*$F27,0))))) -> 0.0275 | DO27: =IF(AND($Y27<>0,$Y27<=DO$12),$Y$12*$F27,IF(AND($U27<>0,$U27<=DO$12),$U$12*$F27,IF(AND($Q27<>0,$Q27<=DO$12),$Q$12*$F27,IF(AND($M27<>0,$M27<=DO$12),$M$12*$F27,IF(AND($J27<>0,$J27<=DO$12),$J$12*$F27,0))))) -> 0.04125 | DP27: =IF(AND($Y27<>0,$Y27<=DP$12),$Y$12*$F27,IF(AND($U27<>0,$U27<=DP$12),$U$12*$F27,IF(AND($Q27<>0,$Q27<=DP$12),$Q$12*$F27,IF(AND($M27<>0,$M27<=DP$12),$M$12*$F27,IF(AND($J27<>0,$J27<=DP$12),$J$12*$F27,0))))) -> 0.04125 | DQ27: =IF(AND($Y27<>0,$Y27<=DQ$12),$Y$12*$F27,IF(AND($U27<>0,$U27<=DQ$12),$U$12*$F27,IF(AND($Q27<>0,$Q27<=DQ$12),$Q$12*$F27,IF(AND($M27<>0,$M27<=DQ$12),$M$12*$F27,IF(AND($J27<>0,$J27<=DQ$12),$J$12*$F27,0))))) -> 0.04125 | DR27: =IF(AND($Y27<>0,$Y27<=DR$12),$Y$12*$F27,IF(AND($U27<>0,$U27<=DR$12),$U$12*$F27,IF(AND($Q27<>0,$Q27<=DR$12),$Q$12*$F27,IF(AND($M27<>0,$M27<=DR$12),$M$12*$F27,IF(AND($J27<>0,$J27<=DR$12),$J$12*$F27,0))))) -> 0.04125 | DS27: =IF(AND($Y27<>0,$Y27<=DS$12),$Y$12*$F27,IF(AND($U27<>0,$U27<=DS$12),$U$12*$F27,IF(AND($Q27<>0,$Q27<=DS$12),$Q$12*$F27,IF(AND($M27<>0,$M27<=DS$12),$M$12*$F27,IF(AND($J27<>0,$J27<=DS$12),$J$12*$F27,0))))) -> 0.04125 | DT27: =IF(AND($Y27<>0,$Y27<=DT$12),$Y$12*$F27,IF(AND($U27<>0,$U27<=DT$12),$U$12*$F27,IF(AND($Q27<>0,$Q27<=DT$12),$Q$12*$F27,IF(AND($M27<>0,$M27<=DT$12),$M$12*$F27,IF(AND($J27<>0,$J27<=DT$12),$J$12*$F27,0))))) -> 0.055 | ... EG27: =IF(AND($Y27<>0,$Y27<=EG$12),$Y$12*$F27,IF(AND($U27<>0,$U27<=EG$12),$U$12*$F27,IF(AND($Q27<>0,$Q27<=EG$12),$Q$12*$F27,IF(AND($M27<>0,$M27<=EG$12),$M$12*$F27,IF(AND($J27<>0,$J27<=EG$12),$J$12*$F27,0))))) -> 0.055
A28: 4.c | B28: W2026I-DNGF-EM-100-PRD-SPC-0008 | C28: Data Connection Schema & Production Data Mapping | F28: 0.0377 | H28: 46174 | J28: 46117 | K28: =H28+((O28-H28)*0.5) -> 46177.25 | M28: 46124 | O28: =H28+((W28-H28)*0.5) -> 46180.5 | Q28: 46127 | S28: =O28+((W28-O28)*0.5) -> 46183.75 | U28: 46161 | W28: 46187 | Y28: 46184 | AE28: =AN28 -> 0.0377 | AG28: =IF(AND($Y28<>0,$Y28<=$BL$6),$Y$12,IF(AND($U28<>0,$U28<=$BL$6),$U$12,IF(AND($Q28<>0,$Q28<=$BL$6),$Q$12,IF(AND($M28<>0,$M28<=$BL$6),$M$12,IF(AND($J28<>0,$J28<=$BL$6),$J$12,0))))) -> 1 | AH28: =AI28-AG28 -> 0 | AI28: =IF(AND($Y28<>0,$Y28<=$BL$5),$Y$12,IF(AND($U28<>0,$U28<=$BL$5),$U$12,IF(AND($Q28<>0,$Q28<=$BL$5),$Q$12,IF(AND($M28<>0,$M28<=$BL$5),$M$12,IF(AND($J28<>0,$J28<=$BL$5),$J$12,0))))) -> 1 | AJ28: =IF(AND($W28<>0,$W28<=$BL$5),$W$12,IF(AND($S28<>0,$S28<=$BL$5),$S$12,IF(AND($O28<>0,$O28<=$BL$5),$O$12,IF(AND($K28<>0,$K28<=$BL$5),$K$12,IF(AND($H28<>0,$H28<=$BL$5),$H$12,0))))) -> 1 | AK28: =IF(AND($X28<>0,$X28<=$BL$5),$X$12,IF(AND($T28<>0,$T28<=$BL$5),$T$12,IF(AND($P28<>0,$P28<=$BL$5),$P$12,IF(AND($L28<>0,$L28<=$BL$5),$L$12,IF(AND($I28<>0,$I28<=$BL$5),$I$12,0))))) -> 0 | AL28: =AI28-AJ28 -> 0 | AM28: =AI28-AK28 -> 1 | AN28: =AI28*F28 -> 0.0377 | AO28: =AJ28*F28 -> 0.0377 | AP28: =AK28*F28 -> 0 | AQ28: =AN28-AO28 -> 0 | AZ28: 0.0377 | BD28: 4.c | BE28: =AG28*F28 -> 0.0377 | BF28: =AI28*F28 -> 0.0377 | BG28: =IF(AND($W28<>0,$W28<=$BL$6),$W$12,IF(AND($S28<>0,$S28<=$BL$6),$S$12,IF(AND($O28<>0,$O28<=$BL$6),$O$12,IF(AND($K28<>0,$K28<=$BL$6),$K$12,IF(AND($H28<>0,$H28<=$BL$6),$H$12,0)))))*$F28 -> 0.0377 | BH28: =IF(AND($W28<>0,$W28<=$BL$5),$W$12,IF(AND($S28<>0,$S28<=$BL$5),$S$12,IF(AND($O28<>0,$O28<=$BL$5),$O$12,IF(AND($K28<>0,$K28<=$BL$5),$K$12,IF(AND($H28<>0,$H28<=$BL$5),$H$12,0)))))*$F28 -> 0.0377 | BI28: =IF(AND($X28<>0,$X28<=$BL$6),$X$12,IF(AND($T28<>0,$T28<=$BL$6),$T$12,IF(AND($P28<>0,$P28<=$BL$6),$P$12,IF(AND($L28<>0,$L28<=$BL$6),$L$12,IF(AND($I28<>0,$I28<=$BL$6),$I$12,0)))))*$F28 -> 0 | BJ28: =IF(AND($X28<>0,$X28<=$BL$5),$X$12,IF(AND($T28<>0,$T28<=$BL$5),$T$12,IF(AND($P28<>0,$P28<=$BL$5),$P$12,IF(AND($L28<>0,$L28<=$BL$5),$L$12,IF(AND($I28<>0,$I28<=$BL$5),$I$12,0)))))*$F28 -> 0 | BM28: 0 | BN28: =IF(AND($W28<>0,$W28<=BN$12),$W$12*$F28,IF(AND($S28<>0,$S28<=BN$12),$S$12*$F28,IF(AND($O28<>0,$O28<=BN$12),$O$12*$F28,IF(AND($K28<>0,$K28<=BN$12),$K$12*$F28,IF(AND($H28<>0,$H28<=BN$12),$H$12*$F28,0))))) -> 0 | BO28: =IF(AND($W28<>0,$W28<=BO$12),$W$12*$F28,IF(AND($S28<>0,$S28<=BO$12),$S$12*$F28,IF(AND($O28<>0,$O28<=BO$12),$O$12*$F28,IF(AND($K28<>0,$K28<=BO$12),$K$12*$F28,IF(AND($H28<>0,$H28<=BO$12),$H$12*$F28,0))))) -> 0 | BP28: =IF(AND($W28<>0,$W28<=BP$12),$W$12*$F28,IF(AND($S28<>0,$S28<=BP$12),$S$12*$F28,IF(AND($O28<>0,$O28<=BP$12),$O$12*$F28,IF(AND($K28<>0,$K28<=BP$12),$K$12*$F28,IF(AND($H28<>0,$H28<=BP$12),$H$12*$F28,0))))) -> 0 | BQ28: =IF(AND($W28<>0,$W28<=BQ$12),$W$12*$F28,IF(AND($S28<>0,$S28<=BQ$12),$S$12*$F28,IF(AND($O28<>0,$O28<=BQ$12),$O$12*$F28,IF(AND($K28<>0,$K28<=BQ$12),$K$12*$F28,IF(AND($H28<>0,$H28<=BQ$12),$H$12*$F28,0))))) -> 0 | BR28: =IF(AND($W28<>0,$W28<=BR$12),$W$12*$F28,IF(AND($S28<>0,$S28<=BR$12),$S$12*$F28,IF(AND($O28<>0,$O28<=BR$12),$O$12*$F28,IF(AND($K28<>0,$K28<=BR$12),$K$12*$F28,IF(AND($H28<>0,$H28<=BR$12),$H$12*$F28,0))))) -> 0 | BS28: =IF(AND($W28<>0,$W28<=BS$12),$W$12*$F28,IF(AND($S28<>0,$S28<=BS$12),$S$12*$F28,IF(AND($O28<>0,$O28<=BS$12),$O$12*$F28,IF(AND($K28<>0,$K28<=BS$12),$K$12*$F28,IF(AND($H28<>0,$H28<=BS$12),$H$12*$F28,0))))) -> 0 | BT28: =IF(AND($W28<>0,$W28<=BT$12),$W$12*$F28,IF(AND($S28<>0,$S28<=BT$12),$S$12*$F28,IF(AND($O28<>0,$O28<=BT$12),$O$12*$F28,IF(AND($K28<>0,$K28<=BT$12),$K$12*$F28,IF(AND($H28<>0,$H28<=BT$12),$H$12*$F28,0))))) -> 0 | BU28: =IF(AND($W28<>0,$W28<=BU$12),$W$12*$F28,IF(AND($S28<>0,$S28<=BU$12),$S$12*$F28,IF(AND($O28<>0,$O28<=BU$12),$O$12*$F28,IF(AND($K28<>0,$K28<=BU$12),$K$12*$F28,IF(AND($H28<>0,$H28<=BU$12),$H$12*$F28,0))))) -> 0 | ... CH28: =IF(AND($W28<>0,$W28<=CH$12),$W$12*$F28,IF(AND($S28<>0,$S28<=CH$12),$S$12*$F28,IF(AND($O28<>0,$O28<=CH$12),$O$12*$F28,IF(AND($K28<>0,$K28<=CH$12),$K$12*$F28,IF(AND($H28<>0,$H28<=CH$12),$H$12*$F28,0))))) -> 0.0377 | CL28: 0 | CM28: =IF(AND($X28<>0,$X28<=CM$12),$X$12*$F28,IF(AND($T28<>0,$T28<=CM$12),$T$12*$F28,IF(AND($P28<>0,$P28<=CM$12),$P$12*$F28,IF(AND($L28<>0,$L28<=CM$12),$L$12*$F28,IF(AND($I28<>0,$I28<=CM$12),$I$12*$F28,0))))) -> 0 | CN28: =IF(AND($X28<>0,$X28<=CN$12),$X$12*$F28,IF(AND($T28<>0,$T28<=CN$12),$T$12*$F28,IF(AND($P28<>0,$P28<=CN$12),$P$12*$F28,IF(AND($L28<>0,$L28<=CN$12),$L$12*$F28,IF(AND($I28<>0,$I28<=CN$12),$I$12*$F28,0))))) -> 0 | CO28: =IF(AND($X28<>0,$X28<=CO$12),$X$12*$F28,IF(AND($T28<>0,$T28<=CO$12),$T$12*$F28,IF(AND($P28<>0,$P28<=CO$12),$P$12*$F28,IF(AND($L28<>0,$L28<=CO$12),$L$12*$F28,IF(AND($I28<>0,$I28<=CO$12),$I$12*$F28,0))))) -> 0 | CP28: =IF(AND($X28<>0,$X28<=CP$12),$X$12*$F28,IF(AND($T28<>0,$T28<=CP$12),$T$12*$F28,IF(AND($P28<>0,$P28<=CP$12),$P$12*$F28,IF(AND($L28<>0,$L28<=CP$12),$L$12*$F28,IF(AND($I28<>0,$I28<=CP$12),$I$12*$F28,0))))) -> 0 | CQ28: =IF(AND($X28<>0,$X28<=CQ$12),$X$12*$F28,IF(AND($T28<>0,$T28<=CQ$12),$T$12*$F28,IF(AND($P28<>0,$P28<=CQ$12),$P$12*$F28,IF(AND($L28<>0,$L28<=CQ$12),$L$12*$F28,IF(AND($I28<>0,$I28<=CQ$12),$I$12*$F28,0))))) -> 0 | CR28: =IF(AND($X28<>0,$X28<=CR$12),$X$12*$F28,IF(AND($T28<>0,$T28<=CR$12),$T$12*$F28,IF(AND($P28<>0,$P28<=CR$12),$P$12*$F28,IF(AND($L28<>0,$L28<=CR$12),$L$12*$F28,IF(AND($I28<>0,$I28<=CR$12),$I$12*$F28,0))))) -> 0 | CS28: =IF(AND($X28<>0,$X28<=CS$12),$X$12*$F28,IF(AND($T28<>0,$T28<=CS$12),$T$12*$F28,IF(AND($P28<>0,$P28<=CS$12),$P$12*$F28,IF(AND($L28<>0,$L28<=CS$12),$L$12*$F28,IF(AND($I28<>0,$I28<=CS$12),$I$12*$F28,0))))) -> 0 | CT28: =IF(AND($X28<>0,$X28<=CT$12),$X$12*$F28,IF(AND($T28<>0,$T28<=CT$12),$T$12*$F28,IF(AND($P28<>0,$P28<=CT$12),$P$12*$F28,IF(AND($L28<>0,$L28<=CT$12),$L$12*$F28,IF(AND($I28<>0,$I28<=CT$12),$I$12*$F28,0))))) -> 0 | ... DG28: =IF(AND($X28<>0,$X28<=DG$12),$X$12*$F28,IF(AND($T28<>0,$T28<=DG$12),$T$12*$F28,IF(AND($P28<>0,$P28<=DG$12),$P$12*$F28,IF(AND($L28<>0,$L28<=DG$12),$L$12*$F28,IF(AND($I28<>0,$I28<=DG$12),$I$12*$F28,0))))) -> 0 | DL28: 0 | DM28: =IF(AND($Y28<>0,$Y28<=DM$12),$Y$12*$F28,IF(AND($U28<>0,$U28<=DM$12),$U$12*$F28,IF(AND($Q28<>0,$Q28<=DM$12),$Q$12*$F28,IF(AND($M28<>0,$M28<=DM$12),$M$12*$F28,IF(AND($J28<>0,$J28<=DM$12),$J$12*$F28,0))))) -> 0.009425 | DN28: =IF(AND($Y28<>0,$Y28<=DN$12),$Y$12*$F28,IF(AND($U28<>0,$U28<=DN$12),$U$12*$F28,IF(AND($Q28<>0,$Q28<=DN$12),$Q$12*$F28,IF(AND($M28<>0,$M28<=DN$12),$M$12*$F28,IF(AND($J28<>0,$J28<=DN$12),$J$12*$F28,0))))) -> 0.01885 | DO28: =IF(AND($Y28<>0,$Y28<=DO$12),$Y$12*$F28,IF(AND($U28<>0,$U28<=DO$12),$U$12*$F28,IF(AND($Q28<>0,$Q28<=DO$12),$Q$12*$F28,IF(AND($M28<>0,$M28<=DO$12),$M$12*$F28,IF(AND($J28<>0,$J28<=DO$12),$J$12*$F28,0))))) -> 0.01885 | DP28: =IF(AND($Y28<>0,$Y28<=DP$12),$Y$12*$F28,IF(AND($U28<>0,$U28<=DP$12),$U$12*$F28,IF(AND($Q28<>0,$Q28<=DP$12),$Q$12*$F28,IF(AND($M28<>0,$M28<=DP$12),$M$12*$F28,IF(AND($J28<>0,$J28<=DP$12),$J$12*$F28,0))))) -> 0.01885 | DQ28: =IF(AND($Y28<>0,$Y28<=DQ$12),$Y$12*$F28,IF(AND($U28<>0,$U28<=DQ$12),$U$12*$F28,IF(AND($Q28<>0,$Q28<=DQ$12),$Q$12*$F28,IF(AND($M28<>0,$M28<=DQ$12),$M$12*$F28,IF(AND($J28<>0,$J28<=DQ$12),$J$12*$F28,0))))) -> 0.01885 | DR28: =IF(AND($Y28<>0,$Y28<=DR$12),$Y$12*$F28,IF(AND($U28<>0,$U28<=DR$12),$U$12*$F28,IF(AND($Q28<>0,$Q28<=DR$12),$Q$12*$F28,IF(AND($M28<>0,$M28<=DR$12),$M$12*$F28,IF(AND($J28<>0,$J28<=DR$12),$J$12*$F28,0))))) -> 0.01885 | DS28: =IF(AND($Y28<>0,$Y28<=DS$12),$Y$12*$F28,IF(AND($U28<>0,$U28<=DS$12),$U$12*$F28,IF(AND($Q28<>0,$Q28<=DS$12),$Q$12*$F28,IF(AND($M28<>0,$M28<=DS$12),$M$12*$F28,IF(AND($J28<>0,$J28<=DS$12),$J$12*$F28,0))))) -> 0.028275 | DT28: =IF(AND($Y28<>0,$Y28<=DT$12),$Y$12*$F28,IF(AND($U28<>0,$U28<=DT$12),$U$12*$F28,IF(AND($Q28<>0,$Q28<=DT$12),$Q$12*$F28,IF(AND($M28<>0,$M28<=DT$12),$M$12*$F28,IF(AND($J28<>0,$J28<=DT$12),$J$12*$F28,0))))) -> 0.028275 | ... EG28: =IF(AND($Y28<>0,$Y28<=EG$12),$Y$12*$F28,IF(AND($U28<>0,$U28<=EG$12),$U$12*$F28,IF(AND($Q28<>0,$Q28<=EG$12),$Q$12*$F28,IF(AND($M28<>0,$M28<=EG$12),$M$12*$F28,IF(AND($J28<>0,$J28<=EG$12),$J$12*$F28,0))))) -> 0.0377
A29: 5 | C29: Persiapan Data (ETL) | F29: =SUBTOTAL(9,F30:F31) -> 0.1854 | AZ29: 0.1545 | BD29: 5 | BE29: =SUBTOTAL(9,BE30:BE31) -> 0.1854 | BF29: =SUBTOTAL(9,BF30:BF31) -> 0.1854 | BG29: =SUBTOTAL(9,BG30:BG31) -> 0.1545 | BH29: =SUBTOTAL(9,BH30:BH31) -> 0.1854 | BI29: =SUBTOTAL(9,BI30:BI31) -> 0.0309 | BJ29: =SUBTOTAL(9,BJ30:BJ31) -> 0.0309 | BM29: =SUBTOTAL(9,BM30:BM31) -> 0 | BN29: =SUBTOTAL(9,BN30:BN31) -> 0.00618 | BO29: =SUBTOTAL(9,BO30:BO31) -> 0.00927 | BP29: =SUBTOTAL(9,BP30:BP31) -> 0.04635 | BQ29: =SUBTOTAL(9,BQ30:BQ31) -> 0.0618 | BR29: =SUBTOTAL(9,BR30:BR31) -> 0.07725 | BS29: =SUBTOTAL(9,BS30:BS31) -> 0.1236 | BT29: =SUBTOTAL(9,BT30:BT31) -> 0.1236 | ... CH29: =SUBTOTAL(9,CH30:CH31) -> 0.1854 | CL29: =SUBTOTAL(9,CL30:CL31) -> 0 | CM29: =SUBTOTAL(9,CM30:CM31) -> 0 | CN29: =SUBTOTAL(9,CN30:CN31) -> 0 | CO29: =SUBTOTAL(9,CO30:CO31) -> 0.0309 | CP29: =SUBTOTAL(9,CP30:CP31) -> 0.0309 | CQ29: =SUBTOTAL(9,CQ30:CQ31) -> 0.0309 | CR29: =SUBTOTAL(9,CR30:CR31) -> 0.0309 | CS29: =SUBTOTAL(9,CS30:CS31) -> 0.0309 | ... DG29: =SUBTOTAL(9,DG30:DG31) -> 0.0309 | DL29: =SUBTOTAL(9,DL30:DL31) -> 0 | DM29: =SUBTOTAL(9,DM30:DM31) -> 0 | DN29: =SUBTOTAL(9,DN30:DN31) -> 0.00309 | DO29: =SUBTOTAL(9,DO30:DO31) -> 0.04635 | DP29: =SUBTOTAL(9,DP30:DP31) -> 0.0618 | DQ29: =SUBTOTAL(9,DQ30:DQ31) -> 0.07725 | DR29: =SUBTOTAL(9,DR30:DR31) -> 0.1236 | DS29: =SUBTOTAL(9,DS30:DS31) -> 0.1236 | ... EG29: =SUBTOTAL(9,EG30:EG31) -> 0.1854
A30: 5.a | B30: W2026I-DNGF-EM-100-PRD-SPC-0009 | C30: Data Mapping | F30: 0.0618 | H30: 46127 | J30: 46126 | K30: =H30+((O30-H30)*0.5) -> 46134.25 | M30: 46133 | O30: =H30+((W30-H30)*0.5) -> 46141.5 | Q30: 46140 | S30: =O30+((W30-O30)*0.5) -> 46148.75 | U30: 46148 | W30: 46156 | Y30: 46156 | AE30: =AN30 -> 0.0618 | AG30: =IF(AND($Y30<>0,$Y30<=$BL$6),$Y$12,IF(AND($U30<>0,$U30<=$BL$6),$U$12,IF(AND($Q30<>0,$Q30<=$BL$6),$Q$12,IF(AND($M30<>0,$M30<=$BL$6),$M$12,IF(AND($J30<>0,$J30<=$BL$6),$J$12,0))))) -> 1 | AH30: =AI30-AG30 -> 0 | AI30: =IF(AND($Y30<>0,$Y30<=$BL$5),$Y$12,IF(AND($U30<>0,$U30<=$BL$5),$U$12,IF(AND($Q30<>0,$Q30<=$BL$5),$Q$12,IF(AND($M30<>0,$M30<=$BL$5),$M$12,IF(AND($J30<>0,$J30<=$BL$5),$J$12,0))))) -> 1 | AJ30: =IF(AND($W30<>0,$W30<=$BL$5),$W$12,IF(AND($S30<>0,$S30<=$BL$5),$S$12,IF(AND($O30<>0,$O30<=$BL$5),$O$12,IF(AND($K30<>0,$K30<=$BL$5),$K$12,IF(AND($H30<>0,$H30<=$BL$5),$H$12,0))))) -> 1 | AK30: =IF(AND($X30<>0,$X30<=$BL$5),$X$12,IF(AND($T30<>0,$T30<=$BL$5),$T$12,IF(AND($P30<>0,$P30<=$BL$5),$P$12,IF(AND($L30<>0,$L30<=$BL$5),$L$12,IF(AND($I30<>0,$I30<=$BL$5),$I$12,0))))) -> 0 | AL30: =AI30-AJ30 -> 0 | AM30: =AI30-AK30 -> 1 | AN30: =AI30*F30 -> 0.0618 | AO30: =AJ30*F30 -> 0.0618 | AP30: =AK30*F30 -> 0 | AQ30: =AN30-AO30 -> 0 | AZ30: 0.0618 | BD30: 5.a | BE30: =AG30*F30 -> 0.0618 | BF30: =AI30*F30 -> 0.0618 | BG30: =IF(AND($W30<>0,$W30<=$BL$6),$W$12,IF(AND($S30<>0,$S30<=$BL$6),$S$12,IF(AND($O30<>0,$O30<=$BL$6),$O$12,IF(AND($K30<>0,$K30<=$BL$6),$K$12,IF(AND($H30<>0,$H30<=$BL$6),$H$12,0)))))*$F30 -> 0.0618 | BH30: =IF(AND($W30<>0,$W30<=$BL$5),$W$12,IF(AND($S30<>0,$S30<=$BL$5),$S$12,IF(AND($O30<>0,$O30<=$BL$5),$O$12,IF(AND($K30<>0,$K30<=$BL$5),$K$12,IF(AND($H30<>0,$H30<=$BL$5),$H$12,0)))))*$F30 -> 0.0618 | BI30: =IF(AND($X30<>0,$X30<=$BL$6),$X$12,IF(AND($T30<>0,$T30<=$BL$6),$T$12,IF(AND($P30<>0,$P30<=$BL$6),$P$12,IF(AND($L30<>0,$L30<=$BL$6),$L$12,IF(AND($I30<>0,$I30<=$BL$6),$I$12,0)))))*$F30 -> 0 | BJ30: =IF(AND($X30<>0,$X30<=$BL$5),$X$12,IF(AND($T30<>0,$T30<=$BL$5),$T$12,IF(AND($P30<>0,$P30<=$BL$5),$P$12,IF(AND($L30<>0,$L30<=$BL$5),$L$12,IF(AND($I30<>0,$I30<=$BL$5),$I$12,0)))))*$F30 -> 0 | BM30: 0 | BN30: =IF(AND($W30<>0,$W30<=BN$12),$W$12*$F30,IF(AND($S30<>0,$S30<=BN$12),$S$12*$F30,IF(AND($O30<>0,$O30<=BN$12),$O$12*$F30,IF(AND($K30<>0,$K30<=BN$12),$K$12*$F30,IF(AND($H30<>0,$H30<=BN$12),$H$12*$F30,0))))) -> 0 | BO30: =IF(AND($W30<>0,$W30<=BO$12),$W$12*$F30,IF(AND($S30<>0,$S30<=BO$12),$S$12*$F30,IF(AND($O30<>0,$O30<=BO$12),$O$12*$F30,IF(AND($K30<>0,$K30<=BO$12),$K$12*$F30,IF(AND($H30<>0,$H30<=BO$12),$H$12*$F30,0))))) -> 0.00309 | BP30: =IF(AND($W30<>0,$W30<=BP$12),$W$12*$F30,IF(AND($S30<>0,$S30<=BP$12),$S$12*$F30,IF(AND($O30<>0,$O30<=BP$12),$O$12*$F30,IF(AND($K30<>0,$K30<=BP$12),$K$12*$F30,IF(AND($H30<>0,$H30<=BP$12),$H$12*$F30,0))))) -> 0.01545 | BQ30: =IF(AND($W30<>0,$W30<=BQ$12),$W$12*$F30,IF(AND($S30<>0,$S30<=BQ$12),$S$12*$F30,IF(AND($O30<>0,$O30<=BQ$12),$O$12*$F30,IF(AND($K30<>0,$K30<=BQ$12),$K$12*$F30,IF(AND($H30<>0,$H30<=BQ$12),$H$12*$F30,0))))) -> 0.0309 | BR30: =IF(AND($W30<>0,$W30<=BR$12),$W$12*$F30,IF(AND($S30<>0,$S30<=BR$12),$S$12*$F30,IF(AND($O30<>0,$O30<=BR$12),$O$12*$F30,IF(AND($K30<>0,$K30<=BR$12),$K$12*$F30,IF(AND($H30<>0,$H30<=BR$12),$H$12*$F30,0))))) -> 0.04635 | BS30: =IF(AND($W30<>0,$W30<=BS$12),$W$12*$F30,IF(AND($S30<>0,$S30<=BS$12),$S$12*$F30,IF(AND($O30<>0,$O30<=BS$12),$O$12*$F30,IF(AND($K30<>0,$K30<=BS$12),$K$12*$F30,IF(AND($H30<>0,$H30<=BS$12),$H$12*$F30,0))))) -> 0.0618 | BT30: =IF(AND($W30<>0,$W30<=BT$12),$W$12*$F30,IF(AND($S30<>0,$S30<=BT$12),$S$12*$F30,IF(AND($O30<>0,$O30<=BT$12),$O$12*$F30,IF(AND($K30<>0,$K30<=BT$12),$K$12*$F30,IF(AND($H30<>0,$H30<=BT$12),$H$12*$F30,0))))) -> 0.0618 | BU30: =IF(AND($W30<>0,$W30<=BU$12),$W$12*$F30,IF(AND($S30<>0,$S30<=BU$12),$S$12*$F30,IF(AND($O30<>0,$O30<=BU$12),$O$12*$F30,IF(AND($K30<>0,$K30<=BU$12),$K$12*$F30,IF(AND($H30<>0,$H30<=BU$12),$H$12*$F30,0))))) -> 0.0618 | ... CH30: =IF(AND($W30<>0,$W30<=CH$12),$W$12*$F30,IF(AND($S30<>0,$S30<=CH$12),$S$12*$F30,IF(AND($O30<>0,$O30<=CH$12),$O$12*$F30,IF(AND($K30<>0,$K30<=CH$12),$K$12*$F30,IF(AND($H30<>0,$H30<=CH$12),$H$12*$F30,0))))) -> 0.0618 | CL30: 0 | CM30: =IF(AND($X30<>0,$X30<=CM$12),$X$12*$F30,IF(AND($T30<>0,$T30<=CM$12),$T$12*$F30,IF(AND($P30<>0,$P30<=CM$12),$P$12*$F30,IF(AND($L30<>0,$L30<=CM$12),$L$12*$F30,IF(AND($I30<>0,$I30<=CM$12),$I$12*$F30,0))))) -> 0 | CN30: =IF(AND($X30<>0,$X30<=CN$12),$X$12*$F30,IF(AND($T30<>0,$T30<=CN$12),$T$12*$F30,IF(AND($P30<>0,$P30<=CN$12),$P$12*$F30,IF(AND($L30<>0,$L30<=CN$12),$L$12*$F30,IF(AND($I30<>0,$I30<=CN$12),$I$12*$F30,0))))) -> 0 | CO30: =IF(AND($X30<>0,$X30<=CO$12),$X$12*$F30,IF(AND($T30<>0,$T30<=CO$12),$T$12*$F30,IF(AND($P30<>0,$P30<=CO$12),$P$12*$F30,IF(AND($L30<>0,$L30<=CO$12),$L$12*$F30,IF(AND($I30<>0,$I30<=CO$12),$I$12*$F30,0))))) -> 0 | CP30: =IF(AND($X30<>0,$X30<=CP$12),$X$12*$F30,IF(AND($T30<>0,$T30<=CP$12),$T$12*$F30,IF(AND($P30<>0,$P30<=CP$12),$P$12*$F30,IF(AND($L30<>0,$L30<=CP$12),$L$12*$F30,IF(AND($I30<>0,$I30<=CP$12),$I$12*$F30,0))))) -> 0 | CQ30: =IF(AND($X30<>0,$X30<=CQ$12),$X$12*$F30,IF(AND($T30<>0,$T30<=CQ$12),$T$12*$F30,IF(AND($P30<>0,$P30<=CQ$12),$P$12*$F30,IF(AND($L30<>0,$L30<=CQ$12),$L$12*$F30,IF(AND($I30<>0,$I30<=CQ$12),$I$12*$F30,0))))) -> 0 | CR30: =IF(AND($X30<>0,$X30<=CR$12),$X$12*$F30,IF(AND($T30<>0,$T30<=CR$12),$T$12*$F30,IF(AND($P30<>0,$P30<=CR$12),$P$12*$F30,IF(AND($L30<>0,$L30<=CR$12),$L$12*$F30,IF(AND($I30<>0,$I30<=CR$12),$I$12*$F30,0))))) -> 0 | CS30: =IF(AND($X30<>0,$X30<=CS$12),$X$12*$F30,IF(AND($T30<>0,$T30<=CS$12),$T$12*$F30,IF(AND($P30<>0,$P30<=CS$12),$P$12*$F30,IF(AND($L30<>0,$L30<=CS$12),$L$12*$F30,IF(AND($I30<>0,$I30<=CS$12),$I$12*$F30,0))))) -> 0 | CT30: =IF(AND($X30<>0,$X30<=CT$12),$X$12*$F30,IF(AND($T30<>0,$T30<=CT$12),$T$12*$F30,IF(AND($P30<>0,$P30<=CT$12),$P$12*$F30,IF(AND($L30<>0,$L30<=CT$12),$L$12*$F30,IF(AND($I30<>0,$I30<=CT$12),$I$12*$F30,0))))) -> 0 | ... DG30: =IF(AND($X30<>0,$X30<=DG$12),$X$12*$F30,IF(AND($T30<>0,$T30<=DG$12),$T$12*$F30,IF(AND($P30<>0,$P30<=DG$12),$P$12*$F30,IF(AND($L30<>0,$L30<=DG$12),$L$12*$F30,IF(AND($I30<>0,$I30<=DG$12),$I$12*$F30,0))))) -> 0 | DL30: 0 | DM30: =IF(AND($Y30<>0,$Y30<=DM$12),$Y$12*$F30,IF(AND($U30<>0,$U30<=DM$12),$U$12*$F30,IF(AND($Q30<>0,$Q30<=DM$12),$Q$12*$F30,IF(AND($M30<>0,$M30<=DM$12),$M$12*$F30,IF(AND($J30<>0,$J30<=DM$12),$J$12*$F30,0))))) -> 0 | DN30: =IF(AND($Y30<>0,$Y30<=DN$12),$Y$12*$F30,IF(AND($U30<>0,$U30<=DN$12),$U$12*$F30,IF(AND($Q30<>0,$Q30<=DN$12),$Q$12*$F30,IF(AND($M30<>0,$M30<=DN$12),$M$12*$F30,IF(AND($J30<>0,$J30<=DN$12),$J$12*$F30,0))))) -> 0.00309 | DO30: =IF(AND($Y30<>0,$Y30<=DO$12),$Y$12*$F30,IF(AND($U30<>0,$U30<=DO$12),$U$12*$F30,IF(AND($Q30<>0,$Q30<=DO$12),$Q$12*$F30,IF(AND($M30<>0,$M30<=DO$12),$M$12*$F30,IF(AND($J30<>0,$J30<=DO$12),$J$12*$F30,0))))) -> 0.01545 | DP30: =IF(AND($Y30<>0,$Y30<=DP$12),$Y$12*$F30,IF(AND($U30<>0,$U30<=DP$12),$U$12*$F30,IF(AND($Q30<>0,$Q30<=DP$12),$Q$12*$F30,IF(AND($M30<>0,$M30<=DP$12),$M$12*$F30,IF(AND($J30<>0,$J30<=DP$12),$J$12*$F30,0))))) -> 0.0309 | DQ30: =IF(AND($Y30<>0,$Y30<=DQ$12),$Y$12*$F30,IF(AND($U30<>0,$U30<=DQ$12),$U$12*$F30,IF(AND($Q30<>0,$Q30<=DQ$12),$Q$12*$F30,IF(AND($M30<>0,$M30<=DQ$12),$M$12*$F30,IF(AND($J30<>0,$J30<=DQ$12),$J$12*$F30,0))))) -> 0.04635 | DR30: =IF(AND($Y30<>0,$Y30<=DR$12),$Y$12*$F30,IF(AND($U30<>0,$U30<=DR$12),$U$12*$F30,IF(AND($Q30<>0,$Q30<=DR$12),$Q$12*$F30,IF(AND($M30<>0,$M30<=DR$12),$M$12*$F30,IF(AND($J30<>0,$J30<=DR$12),$J$12*$F30,0))))) -> 0.0618 | DS30: =IF(AND($Y30<>0,$Y30<=DS$12),$Y$12*$F30,IF(AND($U30<>0,$U30<=DS$12),$U$12*$F30,IF(AND($Q30<>0,$Q30<=DS$12),$Q$12*$F30,IF(AND($M30<>0,$M30<=DS$12),$M$12*$F30,IF(AND($J30<>0,$J30<=DS$12),$J$12*$F30,0))))) -> 0.0618 | DT30: =IF(AND($Y30<>0,$Y30<=DT$12),$Y$12*$F30,IF(AND($U30<>0,$U30<=DT$12),$U$12*$F30,IF(AND($Q30<>0,$Q30<=DT$12),$Q$12*$F30,IF(AND($M30<>0,$M30<=DT$12),$M$12*$F30,IF(AND($J30<>0,$J30<=DT$12),$J$12*$F30,0))))) -> 0.0618 | ... EG30: =IF(AND($Y30<>0,$Y30<=EG$12),$Y$12*$F30,IF(AND($U30<>0,$U30<=EG$12),$U$12*$F30,IF(AND($Q30<>0,$Q30<=EG$12),$Q$12*$F30,IF(AND($M30<>0,$M30<=EG$12),$M$12*$F30,IF(AND($J30<>0,$J30<=EG$12),$J$12*$F30,0))))) -> 0.0618
A31: 5.b | B31: W2026I-DNGF-EM-100-PRD-SPC-0010 | C31: Database yang sudah bersih, terstruktur, dan siap digunakan untuk visualisasi | F31: 0.1236 | H31: 46113 | I31: 46132 | J31: 46132 | K31: =H31+((O31-H31)*0.5) -> 46135.5 | L31: 46137 | M31: 46137 | O31: =H31+((W31-H31)*0.5) -> 46158 | Q31: 46155 | S31: =O31+((W31-O31)*0.5) -> 46180.5 | U31: 46178 | W31: 46203 | Y31: 46198 | AE31: =AN31 -> 0.1236 | AG31: =IF(AND($Y31<>0,$Y31<=$BL$6),$Y$12,IF(AND($U31<>0,$U31<=$BL$6),$U$12,IF(AND($Q31<>0,$Q31<=$BL$6),$Q$12,IF(AND($M31<>0,$M31<=$BL$6),$M$12,IF(AND($J31<>0,$J31<=$BL$6),$J$12,0))))) -> 1 | AH31: =AI31-AG31 -> 0 | AI31: =IF(AND($Y31<>0,$Y31<=$BL$5),$Y$12,IF(AND($U31<>0,$U31<=$BL$5),$U$12,IF(AND($Q31<>0,$Q31<=$BL$5),$Q$12,IF(AND($M31<>0,$M31<=$BL$5),$M$12,IF(AND($J31<>0,$J31<=$BL$5),$J$12,0))))) -> 1 | AJ31: =IF(AND($W31<>0,$W31<=$BL$5),$W$12,IF(AND($S31<>0,$S31<=$BL$5),$S$12,IF(AND($O31<>0,$O31<=$BL$5),$O$12,IF(AND($K31<>0,$K31<=$BL$5),$K$12,IF(AND($H31<>0,$H31<=$BL$5),$H$12,0))))) -> 1 | AK31: =IF(AND($X31<>0,$X31<=$BL$5),$X$12,IF(AND($T31<>0,$T31<=$BL$5),$T$12,IF(AND($P31<>0,$P31<=$BL$5),$P$12,IF(AND($L31<>0,$L31<=$BL$5),$L$12,IF(AND($I31<>0,$I31<=$BL$5),$I$12,0))))) -> 0.25 | AL31: =AI31-AJ31 -> 0 | AM31: =AI31-AK31 -> 0.75 | AN31: =AI31*F31 -> 0.1236 | AO31: =AJ31*F31 -> 0.1236 | AP31: =AK31*F31 -> 0.0309 | AQ31: =AN31-AO31 -> 0 | AZ31: 0.0927 | BD31: 5.b | BE31: =AG31*F31 -> 0.1236 | BF31: =AI31*F31 -> 0.1236 | BG31: =IF(AND($W31<>0,$W31<=$BL$6),$W$12,IF(AND($S31<>0,$S31<=$BL$6),$S$12,IF(AND($O31<>0,$O31<=$BL$6),$O$12,IF(AND($K31<>0,$K31<=$BL$6),$K$12,IF(AND($H31<>0,$H31<=$BL$6),$H$12,0)))))*$F31 -> 0.0927 | BH31: =IF(AND($W31<>0,$W31<=$BL$5),$W$12,IF(AND($S31<>0,$S31<=$BL$5),$S$12,IF(AND($O31<>0,$O31<=$BL$5),$O$12,IF(AND($K31<>0,$K31<=$BL$5),$K$12,IF(AND($H31<>0,$H31<=$BL$5),$H$12,0)))))*$F31 -> 0.1236 | BI31: =IF(AND($X31<>0,$X31<=$BL$6),$X$12,IF(AND($T31<>0,$T31<=$BL$6),$T$12,IF(AND($P31<>0,$P31<=$BL$6),$P$12,IF(AND($L31<>0,$L31<=$BL$6),$L$12,IF(AND($I31<>0,$I31<=$BL$6),$I$12,0)))))*$F31 -> 0.0309 | BJ31: =IF(AND($X31<>0,$X31<=$BL$5),$X$12,IF(AND($T31<>0,$T31<=$BL$5),$T$12,IF(AND($P31<>0,$P31<=$BL$5),$P$12,IF(AND($L31<>0,$L31<=$BL$5),$L$12,IF(AND($I31<>0,$I31<=$BL$5),$I$12,0)))))*$F31 -> 0.0309 | BM31: 0 | BN31: =IF(AND($W31<>0,$W31<=BN$12),$W$12*$F31,IF(AND($S31<>0,$S31<=BN$12),$S$12*$F31,IF(AND($O31<>0,$O31<=BN$12),$O$12*$F31,IF(AND($K31<>0,$K31<=BN$12),$K$12*$F31,IF(AND($H31<>0,$H31<=BN$12),$H$12*$F31,0))))) -> 0.00618 | BO31: =IF(AND($W31<>0,$W31<=BO$12),$W$12*$F31,IF(AND($S31<>0,$S31<=BO$12),$S$12*$F31,IF(AND($O31<>0,$O31<=BO$12),$O$12*$F31,IF(AND($K31<>0,$K31<=BO$12),$K$12*$F31,IF(AND($H31<>0,$H31<=BO$12),$H$12*$F31,0))))) -> 0.00618 | BP31: =IF(AND($W31<>0,$W31<=BP$12),$W$12*$F31,IF(AND($S31<>0,$S31<=BP$12),$S$12*$F31,IF(AND($O31<>0,$O31<=BP$12),$O$12*$F31,IF(AND($K31<>0,$K31<=BP$12),$K$12*$F31,IF(AND($H31<>0,$H31<=BP$12),$H$12*$F31,0))))) -> 0.0309 | BQ31: =IF(AND($W31<>0,$W31<=BQ$12),$W$12*$F31,IF(AND($S31<>0,$S31<=BQ$12),$S$12*$F31,IF(AND($O31<>0,$O31<=BQ$12),$O$12*$F31,IF(AND($K31<>0,$K31<=BQ$12),$K$12*$F31,IF(AND($H31<>0,$H31<=BQ$12),$H$12*$F31,0))))) -> 0.0309 | BR31: =IF(AND($W31<>0,$W31<=BR$12),$W$12*$F31,IF(AND($S31<>0,$S31<=BR$12),$S$12*$F31,IF(AND($O31<>0,$O31<=BR$12),$O$12*$F31,IF(AND($K31<>0,$K31<=BR$12),$K$12*$F31,IF(AND($H31<>0,$H31<=BR$12),$H$12*$F31,0))))) -> 0.0309 | BS31: =IF(AND($W31<>0,$W31<=BS$12),$W$12*$F31,IF(AND($S31<>0,$S31<=BS$12),$S$12*$F31,IF(AND($O31<>0,$O31<=BS$12),$O$12*$F31,IF(AND($K31<>0,$K31<=BS$12),$K$12*$F31,IF(AND($H31<>0,$H31<=BS$12),$H$12*$F31,0))))) -> 0.0618 | BT31: =IF(AND($W31<>0,$W31<=BT$12),$W$12*$F31,IF(AND($S31<>0,$S31<=BT$12),$S$12*$F31,IF(AND($O31<>0,$O31<=BT$12),$O$12*$F31,IF(AND($K31<>0,$K31<=BT$12),$K$12*$F31,IF(AND($H31<>0,$H31<=BT$12),$H$12*$F31,0))))) -> 0.0618 | BU31: =IF(AND($W31<>0,$W31<=BU$12),$W$12*$F31,IF(AND($S31<>0,$S31<=BU$12),$S$12*$F31,IF(AND($O31<>0,$O31<=BU$12),$O$12*$F31,IF(AND($K31<>0,$K31<=BU$12),$K$12*$F31,IF(AND($H31<>0,$H31<=BU$12),$H$12*$F31,0))))) -> 0.0618 | ... CH31: =IF(AND($W31<>0,$W31<=CH$12),$W$12*$F31,IF(AND($S31<>0,$S31<=CH$12),$S$12*$F31,IF(AND($O31<>0,$O31<=CH$12),$O$12*$F31,IF(AND($K31<>0,$K31<=CH$12),$K$12*$F31,IF(AND($H31<>0,$H31<=CH$12),$H$12*$F31,0))))) -> 0.1236 | CL31: 0 | CM31: =IF(AND($X31<>0,$X31<=CM$12),$X$12*$F31,IF(AND($T31<>0,$T31<=CM$12),$T$12*$F31,IF(AND($P31<>0,$P31<=CM$12),$P$12*$F31,IF(AND($L31<>0,$L31<=CM$12),$L$12*$F31,IF(AND($I31<>0,$I31<=CM$12),$I$12*$F31,0))))) -> 0 | CN31: =IF(AND($X31<>0,$X31<=CN$12),$X$12*$F31,IF(AND($T31<>0,$T31<=CN$12),$T$12*$F31,IF(AND($P31<>0,$P31<=CN$12),$P$12*$F31,IF(AND($L31<>0,$L31<=CN$12),$L$12*$F31,IF(AND($I31<>0,$I31<=CN$12),$I$12*$F31,0))))) -> 0 | CO31: =IF(AND($X31<>0,$X31<=CO$12),$X$12*$F31,IF(AND($T31<>0,$T31<=CO$12),$T$12*$F31,IF(AND($P31<>0,$P31<=CO$12),$P$12*$F31,IF(AND($L31<>0,$L31<=CO$12),$L$12*$F31,IF(AND($I31<>0,$I31<=CO$12),$I$12*$F31,0))))) -> 0.0309 | CP31: =IF(AND($X31<>0,$X31<=CP$12),$X$12*$F31,IF(AND($T31<>0,$T31<=CP$12),$T$12*$F31,IF(AND($P31<>0,$P31<=CP$12),$P$12*$F31,IF(AND($L31<>0,$L31<=CP$12),$L$12*$F31,IF(AND($I31<>0,$I31<=CP$12),$I$12*$F31,0))))) -> 0.0309 | CQ31: =IF(AND($X31<>0,$X31<=CQ$12),$X$12*$F31,IF(AND($T31<>0,$T31<=CQ$12),$T$12*$F31,IF(AND($P31<>0,$P31<=CQ$12),$P$12*$F31,IF(AND($L31<>0,$L31<=CQ$12),$L$12*$F31,IF(AND($I31<>0,$I31<=CQ$12),$I$12*$F31,0))))) -> 0.0309 | CR31: =IF(AND($X31<>0,$X31<=CR$12),$X$12*$F31,IF(AND($T31<>0,$T31<=CR$12),$T$12*$F31,IF(AND($P31<>0,$P31<=CR$12),$P$12*$F31,IF(AND($L31<>0,$L31<=CR$12),$L$12*$F31,IF(AND($I31<>0,$I31<=CR$12),$I$12*$F31,0))))) -> 0.0309 | CS31: =IF(AND($X31<>0,$X31<=CS$12),$X$12*$F31,IF(AND($T31<>0,$T31<=CS$12),$T$12*$F31,IF(AND($P31<>0,$P31<=CS$12),$P$12*$F31,IF(AND($L31<>0,$L31<=CS$12),$L$12*$F31,IF(AND($I31<>0,$I31<=CS$12),$I$12*$F31,0))))) -> 0.0309 | CT31: =IF(AND($X31<>0,$X31<=CT$12),$X$12*$F31,IF(AND($T31<>0,$T31<=CT$12),$T$12*$F31,IF(AND($P31<>0,$P31<=CT$12),$P$12*$F31,IF(AND($L31<>0,$L31<=CT$12),$L$12*$F31,IF(AND($I31<>0,$I31<=CT$12),$I$12*$F31,0))))) -> 0.0309 | ... DG31: =IF(AND($X31<>0,$X31<=DG$12),$X$12*$F31,IF(AND($T31<>0,$T31<=DG$12),$T$12*$F31,IF(AND($P31<>0,$P31<=DG$12),$P$12*$F31,IF(AND($L31<>0,$L31<=DG$12),$L$12*$F31,IF(AND($I31<>0,$I31<=DG$12),$I$12*$F31,0))))) -> 0.0309 | DL31: 0 | DM31: =IF(AND($Y31<>0,$Y31<=DM$12),$Y$12*$F31,IF(AND($U31<>0,$U31<=DM$12),$U$12*$F31,IF(AND($Q31<>0,$Q31<=DM$12),$Q$12*$F31,IF(AND($M31<>0,$M31<=DM$12),$M$12*$F31,IF(AND($J31<>0,$J31<=DM$12),$J$12*$F31,0))))) -> 0 | DN31: =IF(AND($Y31<>0,$Y31<=DN$12),$Y$12*$F31,IF(AND($U31<>0,$U31<=DN$12),$U$12*$F31,IF(AND($Q31<>0,$Q31<=DN$12),$Q$12*$F31,IF(AND($M31<>0,$M31<=DN$12),$M$12*$F31,IF(AND($J31<>0,$J31<=DN$12),$J$12*$F31,0))))) -> 0 | DO31: =IF(AND($Y31<>0,$Y31<=DO$12),$Y$12*$F31,IF(AND($U31<>0,$U31<=DO$12),$U$12*$F31,IF(AND($Q31<>0,$Q31<=DO$12),$Q$12*$F31,IF(AND($M31<>0,$M31<=DO$12),$M$12*$F31,IF(AND($J31<>0,$J31<=DO$12),$J$12*$F31,0))))) -> 0.0309 | DP31: =IF(AND($Y31<>0,$Y31<=DP$12),$Y$12*$F31,IF(AND($U31<>0,$U31<=DP$12),$U$12*$F31,IF(AND($Q31<>0,$Q31<=DP$12),$Q$12*$F31,IF(AND($M31<>0,$M31<=DP$12),$M$12*$F31,IF(AND($J31<>0,$J31<=DP$12),$J$12*$F31,0))))) -> 0.0309 | DQ31: =IF(AND($Y31<>0,$Y31<=DQ$12),$Y$12*$F31,IF(AND($U31<>0,$U31<=DQ$12),$U$12*$F31,IF(AND($Q31<>0,$Q31<=DQ$12),$Q$12*$F31,IF(AND($M31<>0,$M31<=DQ$12),$M$12*$F31,IF(AND($J31<>0,$J31<=DQ$12),$J$12*$F31,0))))) -> 0.0309 | DR31: =IF(AND($Y31<>0,$Y31<=DR$12),$Y$12*$F31,IF(AND($U31<>0,$U31<=DR$12),$U$12*$F31,IF(AND($Q31<>0,$Q31<=DR$12),$Q$12*$F31,IF(AND($M31<>0,$M31<=DR$12),$M$12*$F31,IF(AND($J31<>0,$J31<=DR$12),$J$12*$F31,0))))) -> 0.0618 | DS31: =IF(AND($Y31<>0,$Y31<=DS$12),$Y$12*$F31,IF(AND($U31<>0,$U31<=DS$12),$U$12*$F31,IF(AND($Q31<>0,$Q31<=DS$12),$Q$12*$F31,IF(AND($M31<>0,$M31<=DS$12),$M$12*$F31,IF(AND($J31<>0,$J31<=DS$12),$J$12*$F31,0))))) -> 0.0618 | DT31: =IF(AND($Y31<>0,$Y31<=DT$12),$Y$12*$F31,IF(AND($U31<>0,$U31<=DT$12),$U$12*$F31,IF(AND($Q31<>0,$Q31<=DT$12),$Q$12*$F31,IF(AND($M31<>0,$M31<=DT$12),$M$12*$F31,IF(AND($J31<>0,$J31<=DT$12),$J$12*$F31,0))))) -> 0.0618 | ... EG31: =IF(AND($Y31<>0,$Y31<=EG$12),$Y$12*$F31,IF(AND($U31<>0,$U31<=EG$12),$U$12*$F31,IF(AND($Q31<>0,$Q31<=EG$12),$Q$12*$F31,IF(AND($M31<>0,$M31<=EG$12),$M$12*$F31,IF(AND($J31<>0,$J31<=EG$12),$J$12*$F31,0))))) -> 0.1236
A32: 6 | C32: Pengembangan Dashboard | F32: =SUBTOTAL(9,F33:F36) -> 0.3117 | AZ32: 0.17145 | BD32: 6 | BE32: =SUBTOTAL(9,BE33:BE36) -> 0.1948 | BF32: =SUBTOTAL(9,BF33:BF36) -> 0.2299 | BG32: =SUBTOTAL(9,BG33:BG36) -> 0.10112 | BH32: =SUBTOTAL(9,BH33:BH36) -> 0.17145 | BI32: =SUBTOTAL(9,BI33:BI36) -> 0 | BJ32: =SUBTOTAL(9,BJ33:BJ36) -> 0 | BM32: =SUBTOTAL(9,BM33:BM36) -> 0 | BN32: =SUBTOTAL(9,BN33:BN36) -> 0 | BO32: =SUBTOTAL(9,BO33:BO36) -> 0 | BP32: =SUBTOTAL(9,BP33:BP36) -> 0 | BQ32: =SUBTOTAL(9,BQ33:BQ36) -> 0.00331 | BR32: =SUBTOTAL(9,BR33:BR36) -> 0.00331 | BS32: =SUBTOTAL(9,BS33:BS36) -> 0.01655 | BT32: =SUBTOTAL(9,BT33:BT36) -> 0.01655 | ... CH32: =SUBTOTAL(9,CH33:CH36) -> 0.3117 | CL32: =SUBTOTAL(9,CL33:CL36) -> 0 | CM32: =SUBTOTAL(9,CM33:CM36) -> 0 | CN32: =SUBTOTAL(9,CN33:CN36) -> 0 | CO32: =SUBTOTAL(9,CO33:CO36) -> 0 | CP32: =SUBTOTAL(9,CP33:CP36) -> 0 | CQ32: =SUBTOTAL(9,CQ33:CQ36) -> 0 | CR32: =SUBTOTAL(9,CR33:CR36) -> 0 | CS32: =SUBTOTAL(9,CS33:CS36) -> 0 | ... DG32: =SUBTOTAL(9,DG33:DG36) -> 0 | DL32: =SUBTOTAL(9,DL33:DL36) -> 0 | DM32: =SUBTOTAL(9,DM33:DM36) -> 0 | DN32: =SUBTOTAL(9,DN33:DN36) -> 0 | DO32: =SUBTOTAL(9,DO33:DO36) -> 0 | DP32: =SUBTOTAL(9,DP33:DP36) -> 0.00331 | DQ32: =SUBTOTAL(9,DQ33:DQ36) -> 0.00331 | DR32: =SUBTOTAL(9,DR33:DR36) -> 0.01655 | DS32: =SUBTOTAL(9,DS33:DS36) -> 0.01655 | ... EG32: =SUBTOTAL(9,EG33:EG36) -> 0.2299
A33: 6.a | B33: W2026I-DNGF-EM-100-PRD-SPC-0011 | C33: Penyusunan sitemap dashboard, definisi hak akses menu (Role Based Access Control), dan struktur navigasi | F33: 0.0117 | H33: 46181 | J33: 46172 | K33: =H33+((O33-H33)*0.5) -> 46184.25 | M33: 46174 | O33: =H33+((W33-H33)*0.5) -> 46187.5 | Q33: 46174 | S33: =O33+((W33-O33)*0.5) -> 46190.75 | U33: 46179 | W33: 46194 | Y33: 46187 | AE33: =AN33 -> 0.0117 | AG33: =IF(AND($Y33<>0,$Y33<=$BL$6),$Y$12,IF(AND($U33<>0,$U33<=$BL$6),$U$12,IF(AND($Q33<>0,$Q33<=$BL$6),$Q$12,IF(AND($M33<>0,$M33<=$BL$6),$M$12,IF(AND($J33<>0,$J33<=$BL$6),$J$12,0))))) -> 1 | AH33: =AI33-AG33 -> 0 | AI33: =IF(AND($Y33<>0,$Y33<=$BL$5),$Y$12,IF(AND($U33<>0,$U33<=$BL$5),$U$12,IF(AND($Q33<>0,$Q33<=$BL$5),$Q$12,IF(AND($M33<>0,$M33<=$BL$5),$M$12,IF(AND($J33<>0,$J33<=$BL$5),$J$12,0))))) -> 1 | AJ33: =IF(AND($W33<>0,$W33<=$BL$5),$W$12,IF(AND($S33<>0,$S33<=$BL$5),$S$12,IF(AND($O33<>0,$O33<=$BL$5),$O$12,IF(AND($K33<>0,$K33<=$BL$5),$K$12,IF(AND($H33<>0,$H33<=$BL$5),$H$12,0))))) -> 1 | AK33: =IF(AND($X33<>0,$X33<=$BL$5),$X$12,IF(AND($T33<>0,$T33<=$BL$5),$T$12,IF(AND($P33<>0,$P33<=$BL$5),$P$12,IF(AND($L33<>0,$L33<=$BL$5),$L$12,IF(AND($I33<>0,$I33<=$BL$5),$I$12,0))))) -> 0 | AL33: =AI33-AJ33 -> 0 | AM33: =AI33-AK33 -> 1 | AN33: =AI33*F33 -> 0.0117 | AO33: =AJ33*F33 -> 0.0117 | AP33: =AK33*F33 -> 0 | AQ33: =AN33-AO33 -> 0 | AZ33: 0.0117 | BD33: 6.a | BE33: =AG33*F33 -> 0.0117 | BF33: =AI33*F33 -> 0.0117 | BG33: =IF(AND($W33<>0,$W33<=$BL$6),$W$12,IF(AND($S33<>0,$S33<=$BL$6),$S$12,IF(AND($O33<>0,$O33<=$BL$6),$O$12,IF(AND($K33<>0,$K33<=$BL$6),$K$12,IF(AND($H33<>0,$H33<=$BL$6),$H$12,0)))))*$F33 -> 0.0117 | BH33: =IF(AND($W33<>0,$W33<=$BL$5),$W$12,IF(AND($S33<>0,$S33<=$BL$5),$S$12,IF(AND($O33<>0,$O33<=$BL$5),$O$12,IF(AND($K33<>0,$K33<=$BL$5),$K$12,IF(AND($H33<>0,$H33<=$BL$5),$H$12,0)))))*$F33 -> 0.0117 | BI33: =IF(AND($X33<>0,$X33<=$BL$6),$X$12,IF(AND($T33<>0,$T33<=$BL$6),$T$12,IF(AND($P33<>0,$P33<=$BL$6),$P$12,IF(AND($L33<>0,$L33<=$BL$6),$L$12,IF(AND($I33<>0,$I33<=$BL$6),$I$12,0)))))*$F33 -> 0 | BJ33: =IF(AND($X33<>0,$X33<=$BL$5),$X$12,IF(AND($T33<>0,$T33<=$BL$5),$T$12,IF(AND($P33<>0,$P33<=$BL$5),$P$12,IF(AND($L33<>0,$L33<=$BL$5),$L$12,IF(AND($I33<>0,$I33<=$BL$5),$I$12,0)))))*$F33 -> 0 | BM33: 0 | BN33: =IF(AND($W33<>0,$W33<=BN$12),$W$12*$F33,IF(AND($S33<>0,$S33<=BN$12),$S$12*$F33,IF(AND($O33<>0,$O33<=BN$12),$O$12*$F33,IF(AND($K33<>0,$K33<=BN$12),$K$12*$F33,IF(AND($H33<>0,$H33<=BN$12),$H$12*$F33,0))))) -> 0 | BO33: =IF(AND($W33<>0,$W33<=BO$12),$W$12*$F33,IF(AND($S33<>0,$S33<=BO$12),$S$12*$F33,IF(AND($O33<>0,$O33<=BO$12),$O$12*$F33,IF(AND($K33<>0,$K33<=BO$12),$K$12*$F33,IF(AND($H33<>0,$H33<=BO$12),$H$12*$F33,0))))) -> 0 | BP33: =IF(AND($W33<>0,$W33<=BP$12),$W$12*$F33,IF(AND($S33<>0,$S33<=BP$12),$S$12*$F33,IF(AND($O33<>0,$O33<=BP$12),$O$12*$F33,IF(AND($K33<>0,$K33<=BP$12),$K$12*$F33,IF(AND($H33<>0,$H33<=BP$12),$H$12*$F33,0))))) -> 0 | BQ33: =IF(AND($W33<>0,$W33<=BQ$12),$W$12*$F33,IF(AND($S33<>0,$S33<=BQ$12),$S$12*$F33,IF(AND($O33<>0,$O33<=BQ$12),$O$12*$F33,IF(AND($K33<>0,$K33<=BQ$12),$K$12*$F33,IF(AND($H33<>0,$H33<=BQ$12),$H$12*$F33,0))))) -> 0 | BR33: =IF(AND($W33<>0,$W33<=BR$12),$W$12*$F33,IF(AND($S33<>0,$S33<=BR$12),$S$12*$F33,IF(AND($O33<>0,$O33<=BR$12),$O$12*$F33,IF(AND($K33<>0,$K33<=BR$12),$K$12*$F33,IF(AND($H33<>0,$H33<=BR$12),$H$12*$F33,0))))) -> 0 | BS33: =IF(AND($W33<>0,$W33<=BS$12),$W$12*$F33,IF(AND($S33<>0,$S33<=BS$12),$S$12*$F33,IF(AND($O33<>0,$O33<=BS$12),$O$12*$F33,IF(AND($K33<>0,$K33<=BS$12),$K$12*$F33,IF(AND($H33<>0,$H33<=BS$12),$H$12*$F33,0))))) -> 0 | BT33: =IF(AND($W33<>0,$W33<=BT$12),$W$12*$F33,IF(AND($S33<>0,$S33<=BT$12),$S$12*$F33,IF(AND($O33<>0,$O33<=BT$12),$O$12*$F33,IF(AND($K33<>0,$K33<=BT$12),$K$12*$F33,IF(AND($H33<>0,$H33<=BT$12),$H$12*$F33,0))))) -> 0 | BU33: =IF(AND($W33<>0,$W33<=BU$12),$W$12*$F33,IF(AND($S33<>0,$S33<=BU$12),$S$12*$F33,IF(AND($O33<>0,$O33<=BU$12),$O$12*$F33,IF(AND($K33<>0,$K33<=BU$12),$K$12*$F33,IF(AND($H33<>0,$H33<=BU$12),$H$12*$F33,0))))) -> 0 | ... CH33: =IF(AND($W33<>0,$W33<=CH$12),$W$12*$F33,IF(AND($S33<>0,$S33<=CH$12),$S$12*$F33,IF(AND($O33<>0,$O33<=CH$12),$O$12*$F33,IF(AND($K33<>0,$K33<=CH$12),$K$12*$F33,IF(AND($H33<>0,$H33<=CH$12),$H$12*$F33,0))))) -> 0.0117 | CL33: 0 | CM33: =IF(AND($X33<>0,$X33<=CM$12),$X$12*$F33,IF(AND($T33<>0,$T33<=CM$12),$T$12*$F33,IF(AND($P33<>0,$P33<=CM$12),$P$12*$F33,IF(AND($L33<>0,$L33<=CM$12),$L$12*$F33,IF(AND($I33<>0,$I33<=CM$12),$I$12*$F33,0))))) -> 0 | CN33: =IF(AND($X33<>0,$X33<=CN$12),$X$12*$F33,IF(AND($T33<>0,$T33<=CN$12),$T$12*$F33,IF(AND($P33<>0,$P33<=CN$12),$P$12*$F33,IF(AND($L33<>0,$L33<=CN$12),$L$12*$F33,IF(AND($I33<>0,$I33<=CN$12),$I$12*$F33,0))))) -> 0 | CO33: =IF(AND($X33<>0,$X33<=CO$12),$X$12*$F33,IF(AND($T33<>0,$T33<=CO$12),$T$12*$F33,IF(AND($P33<>0,$P33<=CO$12),$P$12*$F33,IF(AND($L33<>0,$L33<=CO$12),$L$12*$F33,IF(AND($I33<>0,$I33<=CO$12),$I$12*$F33,0))))) -> 0 | CP33: =IF(AND($X33<>0,$X33<=CP$12),$X$12*$F33,IF(AND($T33<>0,$T33<=CP$12),$T$12*$F33,IF(AND($P33<>0,$P33<=CP$12),$P$12*$F33,IF(AND($L33<>0,$L33<=CP$12),$L$12*$F33,IF(AND($I33<>0,$I33<=CP$12),$I$12*$F33,0))))) -> 0 | CQ33: =IF(AND($X33<>0,$X33<=CQ$12),$X$12*$F33,IF(AND($T33<>0,$T33<=CQ$12),$T$12*$F33,IF(AND($P33<>0,$P33<=CQ$12),$P$12*$F33,IF(AND($L33<>0,$L33<=CQ$12),$L$12*$F33,IF(AND($I33<>0,$I33<=CQ$12),$I$12*$F33,0))))) -> 0 | CR33: =IF(AND($X33<>0,$X33<=CR$12),$X$12*$F33,IF(AND($T33<>0,$T33<=CR$12),$T$12*$F33,IF(AND($P33<>0,$P33<=CR$12),$P$12*$F33,IF(AND($L33<>0,$L33<=CR$12),$L$12*$F33,IF(AND($I33<>0,$I33<=CR$12),$I$12*$F33,0))))) -> 0 | CS33: =IF(AND($X33<>0,$X33<=CS$12),$X$12*$F33,IF(AND($T33<>0,$T33<=CS$12),$T$12*$F33,IF(AND($P33<>0,$P33<=CS$12),$P$12*$F33,IF(AND($L33<>0,$L33<=CS$12),$L$12*$F33,IF(AND($I33<>0,$I33<=CS$12),$I$12*$F33,0))))) -> 0 | CT33: =IF(AND($X33<>0,$X33<=CT$12),$X$12*$F33,IF(AND($T33<>0,$T33<=CT$12),$T$12*$F33,IF(AND($P33<>0,$P33<=CT$12),$P$12*$F33,IF(AND($L33<>0,$L33<=CT$12),$L$12*$F33,IF(AND($I33<>0,$I33<=CT$12),$I$12*$F33,0))))) -> 0 | ... DG33: =IF(AND($X33<>0,$X33<=DG$12),$X$12*$F33,IF(AND($T33<>0,$T33<=DG$12),$T$12*$F33,IF(AND($P33<>0,$P33<=DG$12),$P$12*$F33,IF(AND($L33<>0,$L33<=DG$12),$L$12*$F33,IF(AND($I33<>0,$I33<=DG$12),$I$12*$F33,0))))) -> 0 | DL33: 0 | DM33: =IF(AND($Y33<>0,$Y33<=DM$12),$Y$12*$F33,IF(AND($U33<>0,$U33<=DM$12),$U$12*$F33,IF(AND($Q33<>0,$Q33<=DM$12),$Q$12*$F33,IF(AND($M33<>0,$M33<=DM$12),$M$12*$F33,IF(AND($J33<>0,$J33<=DM$12),$J$12*$F33,0))))) -> 0 | DN33: =IF(AND($Y33<>0,$Y33<=DN$12),$Y$12*$F33,IF(AND($U33<>0,$U33<=DN$12),$U$12*$F33,IF(AND($Q33<>0,$Q33<=DN$12),$Q$12*$F33,IF(AND($M33<>0,$M33<=DN$12),$M$12*$F33,IF(AND($J33<>0,$J33<=DN$12),$J$12*$F33,0))))) -> 0 | DO33: =IF(AND($Y33<>0,$Y33<=DO$12),$Y$12*$F33,IF(AND($U33<>0,$U33<=DO$12),$U$12*$F33,IF(AND($Q33<>0,$Q33<=DO$12),$Q$12*$F33,IF(AND($M33<>0,$M33<=DO$12),$M$12*$F33,IF(AND($J33<>0,$J33<=DO$12),$J$12*$F33,0))))) -> 0 | DP33: =IF(AND($Y33<>0,$Y33<=DP$12),$Y$12*$F33,IF(AND($U33<>0,$U33<=DP$12),$U$12*$F33,IF(AND($Q33<>0,$Q33<=DP$12),$Q$12*$F33,IF(AND($M33<>0,$M33<=DP$12),$M$12*$F33,IF(AND($J33<>0,$J33<=DP$12),$J$12*$F33,0))))) -> 0 | DQ33: =IF(AND($Y33<>0,$Y33<=DQ$12),$Y$12*$F33,IF(AND($U33<>0,$U33<=DQ$12),$U$12*$F33,IF(AND($Q33<>0,$Q33<=DQ$12),$Q$12*$F33,IF(AND($M33<>0,$M33<=DQ$12),$M$12*$F33,IF(AND($J33<>0,$J33<=DQ$12),$J$12*$F33,0))))) -> 0 | DR33: =IF(AND($Y33<>0,$Y33<=DR$12),$Y$12*$F33,IF(AND($U33<>0,$U33<=DR$12),$U$12*$F33,IF(AND($Q33<>0,$Q33<=DR$12),$Q$12*$F33,IF(AND($M33<>0,$M33<=DR$12),$M$12*$F33,IF(AND($J33<>0,$J33<=DR$12),$J$12*$F33,0))))) -> 0 | DS33: =IF(AND($Y33<>0,$Y33<=DS$12),$Y$12*$F33,IF(AND($U33<>0,$U33<=DS$12),$U$12*$F33,IF(AND($Q33<>0,$Q33<=DS$12),$Q$12*$F33,IF(AND($M33<>0,$M33<=DS$12),$M$12*$F33,IF(AND($J33<>0,$J33<=DS$12),$J$12*$F33,0))))) -> 0 | DT33: =IF(AND($Y33<>0,$Y33<=DT$12),$Y$12*$F33,IF(AND($U33<>0,$U33<=DT$12),$U$12*$F33,IF(AND($Q33<>0,$Q33<=DT$12),$Q$12*$F33,IF(AND($M33<>0,$M33<=DT$12),$M$12*$F33,IF(AND($J33<>0,$J33<=DT$12),$J$12*$F33,0))))) -> 0.000585 | ... EG33: =IF(AND($Y33<>0,$Y33<=EG$12),$Y$12*$F33,IF(AND($U33<>0,$U33<=EG$12),$U$12*$F33,IF(AND($Q33<>0,$Q33<=EG$12),$Q$12*$F33,IF(AND($M33<>0,$M33<=EG$12),$M$12*$F33,IF(AND($J33<>0,$J33<=EG$12),$J$12*$F33,0))))) -> 0.0117
A34: 6.b | B34: W2026I-DNGF-EM-100-PRD-SPC-0012 | C34: Pengembangan Home Page | F34: 0.0662 | H34: 46143 | J34: 46143 | K34: =H34+((O34-H34)*0.5) -> 46158 | M34: 46158 | O34: =H34+((W34-H34)*0.5) -> 46173 | Q34: 46172 | S34: =O34+((W34-O34)*0.5) -> 46188 | U34: 46182 | W34: 46203 | Y34: 46187 | AE34: =AN34 -> 0.0662 | AG34: =IF(AND($Y34<>0,$Y34<=$BL$6),$Y$12,IF(AND($U34<>0,$U34<=$BL$6),$U$12,IF(AND($Q34<>0,$Q34<=$BL$6),$Q$12,IF(AND($M34<>0,$M34<=$BL$6),$M$12,IF(AND($J34<>0,$J34<=$BL$6),$J$12,0))))) -> 1 | AH34: =AI34-AG34 -> 0 | AI34: =IF(AND($Y34<>0,$Y34<=$BL$5),$Y$12,IF(AND($U34<>0,$U34<=$BL$5),$U$12,IF(AND($Q34<>0,$Q34<=$BL$5),$Q$12,IF(AND($M34<>0,$M34<=$BL$5),$M$12,IF(AND($J34<>0,$J34<=$BL$5),$J$12,0))))) -> 1 | AJ34: =IF(AND($W34<>0,$W34<=$BL$5),$W$12,IF(AND($S34<>0,$S34<=$BL$5),$S$12,IF(AND($O34<>0,$O34<=$BL$5),$O$12,IF(AND($K34<>0,$K34<=$BL$5),$K$12,IF(AND($H34<>0,$H34<=$BL$5),$H$12,0))))) -> 1 | AK34: =IF(AND($X34<>0,$X34<=$BL$5),$X$12,IF(AND($T34<>0,$T34<=$BL$5),$T$12,IF(AND($P34<>0,$P34<=$BL$5),$P$12,IF(AND($L34<>0,$L34<=$BL$5),$L$12,IF(AND($I34<>0,$I34<=$BL$5),$I$12,0))))) -> 0 | AL34: =AI34-AJ34 -> 0 | AM34: =AI34-AK34 -> 1 | AN34: =AI34*F34 -> 0.0662 | AO34: =AJ34*F34 -> 0.0662 | AP34: =AK34*F34 -> 0 | AQ34: =AN34-AO34 -> 0 | AZ34: 0.0662 | BD34: 6.b | BE34: =AG34*F34 -> 0.0662 | BF34: =AI34*F34 -> 0.0662 | BG34: =IF(AND($W34<>0,$W34<=$BL$6),$W$12,IF(AND($S34<>0,$S34<=$BL$6),$S$12,IF(AND($O34<>0,$O34<=$BL$6),$O$12,IF(AND($K34<>0,$K34<=$BL$6),$K$12,IF(AND($H34<>0,$H34<=$BL$6),$H$12,0)))))*$F34 -> 0.04965 | BH34: =IF(AND($W34<>0,$W34<=$BL$5),$W$12,IF(AND($S34<>0,$S34<=$BL$5),$S$12,IF(AND($O34<>0,$O34<=$BL$5),$O$12,IF(AND($K34<>0,$K34<=$BL$5),$K$12,IF(AND($H34<>0,$H34<=$BL$5),$H$12,0)))))*$F34 -> 0.0662 | BI34: =IF(AND($X34<>0,$X34<=$BL$6),$X$12,IF(AND($T34<>0,$T34<=$BL$6),$T$12,IF(AND($P34<>0,$P34<=$BL$6),$P$12,IF(AND($L34<>0,$L34<=$BL$6),$L$12,IF(AND($I34<>0,$I34<=$BL$6),$I$12,0)))))*$F34 -> 0 | BJ34: =IF(AND($X34<>0,$X34<=$BL$5),$X$12,IF(AND($T34<>0,$T34<=$BL$5),$T$12,IF(AND($P34<>0,$P34<=$BL$5),$P$12,IF(AND($L34<>0,$L34<=$BL$5),$L$12,IF(AND($I34<>0,$I34<=$BL$5),$I$12,0)))))*$F34 -> 0 | BM34: 0 | BN34: =IF(AND($W34<>0,$W34<=BN$12),$W$12*$F34,IF(AND($S34<>0,$S34<=BN$12),$S$12*$F34,IF(AND($O34<>0,$O34<=BN$12),$O$12*$F34,IF(AND($K34<>0,$K34<=BN$12),$K$12*$F34,IF(AND($H34<>0,$H34<=BN$12),$H$12*$F34,0))))) -> 0 | BO34: =IF(AND($W34<>0,$W34<=BO$12),$W$12*$F34,IF(AND($S34<>0,$S34<=BO$12),$S$12*$F34,IF(AND($O34<>0,$O34<=BO$12),$O$12*$F34,IF(AND($K34<>0,$K34<=BO$12),$K$12*$F34,IF(AND($H34<>0,$H34<=BO$12),$H$12*$F34,0))))) -> 0 | BP34: =IF(AND($W34<>0,$W34<=BP$12),$W$12*$F34,IF(AND($S34<>0,$S34<=BP$12),$S$12*$F34,IF(AND($O34<>0,$O34<=BP$12),$O$12*$F34,IF(AND($K34<>0,$K34<=BP$12),$K$12*$F34,IF(AND($H34<>0,$H34<=BP$12),$H$12*$F34,0))))) -> 0 | BQ34: =IF(AND($W34<>0,$W34<=BQ$12),$W$12*$F34,IF(AND($S34<>0,$S34<=BQ$12),$S$12*$F34,IF(AND($O34<>0,$O34<=BQ$12),$O$12*$F34,IF(AND($K34<>0,$K34<=BQ$12),$K$12*$F34,IF(AND($H34<>0,$H34<=BQ$12),$H$12*$F34,0))))) -> 0.00331 | BR34: =IF(AND($W34<>0,$W34<=BR$12),$W$12*$F34,IF(AND($S34<>0,$S34<=BR$12),$S$12*$F34,IF(AND($O34<>0,$O34<=BR$12),$O$12*$F34,IF(AND($K34<>0,$K34<=BR$12),$K$12*$F34,IF(AND($H34<>0,$H34<=BR$12),$H$12*$F34,0))))) -> 0.00331 | BS34: =IF(AND($W34<>0,$W34<=BS$12),$W$12*$F34,IF(AND($S34<>0,$S34<=BS$12),$S$12*$F34,IF(AND($O34<>0,$O34<=BS$12),$O$12*$F34,IF(AND($K34<>0,$K34<=BS$12),$K$12*$F34,IF(AND($H34<>0,$H34<=BS$12),$H$12*$F34,0))))) -> 0.01655 | BT34: =IF(AND($W34<>0,$W34<=BT$12),$W$12*$F34,IF(AND($S34<>0,$S34<=BT$12),$S$12*$F34,IF(AND($O34<>0,$O34<=BT$12),$O$12*$F34,IF(AND($K34<>0,$K34<=BT$12),$K$12*$F34,IF(AND($H34<>0,$H34<=BT$12),$H$12*$F34,0))))) -> 0.01655 | BU34: =IF(AND($W34<>0,$W34<=BU$12),$W$12*$F34,IF(AND($S34<>0,$S34<=BU$12),$S$12*$F34,IF(AND($O34<>0,$O34<=BU$12),$O$12*$F34,IF(AND($K34<>0,$K34<=BU$12),$K$12*$F34,IF(AND($H34<>0,$H34<=BU$12),$H$12*$F34,0))))) -> 0.0331 | ... CH34: =IF(AND($W34<>0,$W34<=CH$12),$W$12*$F34,IF(AND($S34<>0,$S34<=CH$12),$S$12*$F34,IF(AND($O34<>0,$O34<=CH$12),$O$12*$F34,IF(AND($K34<>0,$K34<=CH$12),$K$12*$F34,IF(AND($H34<>0,$H34<=CH$12),$H$12*$F34,0))))) -> 0.0662 | CL34: 0 | CM34: =IF(AND($X34<>0,$X34<=CM$12),$X$12*$F34,IF(AND($T34<>0,$T34<=CM$12),$T$12*$F34,IF(AND($P34<>0,$P34<=CM$12),$P$12*$F34,IF(AND($L34<>0,$L34<=CM$12),$L$12*$F34,IF(AND($I34<>0,$I34<=CM$12),$I$12*$F34,0))))) -> 0 | CN34: =IF(AND($X34<>0,$X34<=CN$12),$X$12*$F34,IF(AND($T34<>0,$T34<=CN$12),$T$12*$F34,IF(AND($P34<>0,$P34<=CN$12),$P$12*$F34,IF(AND($L34<>0,$L34<=CN$12),$L$12*$F34,IF(AND($I34<>0,$I34<=CN$12),$I$12*$F34,0))))) -> 0 | CO34: =IF(AND($X34<>0,$X34<=CO$12),$X$12*$F34,IF(AND($T34<>0,$T34<=CO$12),$T$12*$F34,IF(AND($P34<>0,$P34<=CO$12),$P$12*$F34,IF(AND($L34<>0,$L34<=CO$12),$L$12*$F34,IF(AND($I34<>0,$I34<=CO$12),$I$12*$F34,0))))) -> 0 | CP34: =IF(AND($X34<>0,$X34<=CP$12),$X$12*$F34,IF(AND($T34<>0,$T34<=CP$12),$T$12*$F34,IF(AND($P34<>0,$P34<=CP$12),$P$12*$F34,IF(AND($L34<>0,$L34<=CP$12),$L$12*$F34,IF(AND($I34<>0,$I34<=CP$12),$I$12*$F34,0))))) -> 0 | CQ34: =IF(AND($X34<>0,$X34<=CQ$12),$X$12*$F34,IF(AND($T34<>0,$T34<=CQ$12),$T$12*$F34,IF(AND($P34<>0,$P34<=CQ$12),$P$12*$F34,IF(AND($L34<>0,$L34<=CQ$12),$L$12*$F34,IF(AND($I34<>0,$I34<=CQ$12),$I$12*$F34,0))))) -> 0 | CR34: =IF(AND($X34<>0,$X34<=CR$12),$X$12*$F34,IF(AND($T34<>0,$T34<=CR$12),$T$12*$F34,IF(AND($P34<>0,$P34<=CR$12),$P$12*$F34,IF(AND($L34<>0,$L34<=CR$12),$L$12*$F34,IF(AND($I34<>0,$I34<=CR$12),$I$12*$F34,0))))) -> 0 | CS34: =IF(AND($X34<>0,$X34<=CS$12),$X$12*$F34,IF(AND($T34<>0,$T34<=CS$12),$T$12*$F34,IF(AND($P34<>0,$P34<=CS$12),$P$12*$F34,IF(AND($L34<>0,$L34<=CS$12),$L$12*$F34,IF(AND($I34<>0,$I34<=CS$12),$I$12*$F34,0))))) -> 0 | CT34: =IF(AND($X34<>0,$X34<=CT$12),$X$12*$F34,IF(AND($T34<>0,$T34<=CT$12),$T$12*$F34,IF(AND($P34<>0,$P34<=CT$12),$P$12*$F34,IF(AND($L34<>0,$L34<=CT$12),$L$12*$F34,IF(AND($I34<>0,$I34<=CT$12),$I$12*$F34,0))))) -> 0 | ... DG34: =IF(AND($X34<>0,$X34<=DG$12),$X$12*$F34,IF(AND($T34<>0,$T34<=DG$12),$T$12*$F34,IF(AND($P34<>0,$P34<=DG$12),$P$12*$F34,IF(AND($L34<>0,$L34<=DG$12),$L$12*$F34,IF(AND($I34<>0,$I34<=DG$12),$I$12*$F34,0))))) -> 0 | DL34: 0 | DM34: =IF(AND($Y34<>0,$Y34<=DM$12),$Y$12*$F34,IF(AND($U34<>0,$U34<=DM$12),$U$12*$F34,IF(AND($Q34<>0,$Q34<=DM$12),$Q$12*$F34,IF(AND($M34<>0,$M34<=DM$12),$M$12*$F34,IF(AND($J34<>0,$J34<=DM$12),$J$12*$F34,0))))) -> 0 | DN34: =IF(AND($Y34<>0,$Y34<=DN$12),$Y$12*$F34,IF(AND($U34<>0,$U34<=DN$12),$U$12*$F34,IF(AND($Q34<>0,$Q34<=DN$12),$Q$12*$F34,IF(AND($M34<>0,$M34<=DN$12),$M$12*$F34,IF(AND($J34<>0,$J34<=DN$12),$J$12*$F34,0))))) -> 0 | DO34: =IF(AND($Y34<>0,$Y34<=DO$12),$Y$12*$F34,IF(AND($U34<>0,$U34<=DO$12),$U$12*$F34,IF(AND($Q34<>0,$Q34<=DO$12),$Q$12*$F34,IF(AND($M34<>0,$M34<=DO$12),$M$12*$F34,IF(AND($J34<>0,$J34<=DO$12),$J$12*$F34,0))))) -> 0 | DP34: =IF(AND($Y34<>0,$Y34<=DP$12),$Y$12*$F34,IF(AND($U34<>0,$U34<=DP$12),$U$12*$F34,IF(AND($Q34<>0,$Q34<=DP$12),$Q$12*$F34,IF(AND($M34<>0,$M34<=DP$12),$M$12*$F34,IF(AND($J34<>0,$J34<=DP$12),$J$12*$F34,0))))) -> 0.00331 | DQ34: =IF(AND($Y34<>0,$Y34<=DQ$12),$Y$12*$F34,IF(AND($U34<>0,$U34<=DQ$12),$U$12*$F34,IF(AND($Q34<>0,$Q34<=DQ$12),$Q$12*$F34,IF(AND($M34<>0,$M34<=DQ$12),$M$12*$F34,IF(AND($J34<>0,$J34<=DQ$12),$J$12*$F34,0))))) -> 0.00331 | DR34: =IF(AND($Y34<>0,$Y34<=DR$12),$Y$12*$F34,IF(AND($U34<>0,$U34<=DR$12),$U$12*$F34,IF(AND($Q34<>0,$Q34<=DR$12),$Q$12*$F34,IF(AND($M34<>0,$M34<=DR$12),$M$12*$F34,IF(AND($J34<>0,$J34<=DR$12),$J$12*$F34,0))))) -> 0.01655 | DS34: =IF(AND($Y34<>0,$Y34<=DS$12),$Y$12*$F34,IF(AND($U34<>0,$U34<=DS$12),$U$12*$F34,IF(AND($Q34<>0,$Q34<=DS$12),$Q$12*$F34,IF(AND($M34<>0,$M34<=DS$12),$M$12*$F34,IF(AND($J34<>0,$J34<=DS$12),$J$12*$F34,0))))) -> 0.01655 | DT34: =IF(AND($Y34<>0,$Y34<=DT$12),$Y$12*$F34,IF(AND($U34<>0,$U34<=DT$12),$U$12*$F34,IF(AND($Q34<>0,$Q34<=DT$12),$Q$12*$F34,IF(AND($M34<>0,$M34<=DT$12),$M$12*$F34,IF(AND($J34<>0,$J34<=DT$12),$J$12*$F34,0))))) -> 0.0331 | ... EG34: =IF(AND($Y34<>0,$Y34<=EG$12),$Y$12*$F34,IF(AND($U34<>0,$U34<=EG$12),$U$12*$F34,IF(AND($Q34<>0,$Q34<=EG$12),$Q$12*$F34,IF(AND($M34<>0,$M34<=EG$12),$M$12*$F34,IF(AND($J34<>0,$J34<=EG$12),$J$12*$F34,0))))) -> 0.0662
A35: 6.c | B35: W2026I-DNGF-EM-100-PRD-SPC-0013 | C35: Pengembangan Modul & Komponen Visual | F35: 0.1404 | H35: 46181 | J35: 46181 | K35: =H35+((O35-H35)*0.5) -> 46194 | M35: 46192 | O35: =H35+((W35-H35)*0.5) -> 46207 | Q35: 46192 | S35: =O35+((W35-O35)*0.5) -> 46220 | U35: 46204 | W35: 46233 | AE35: =AN35 -> 0.1053 | AG35: =IF(AND($Y35<>0,$Y35<=$BL$6),$Y$12,IF(AND($U35<>0,$U35<=$BL$6),$U$12,IF(AND($Q35<>0,$Q35<=$BL$6),$Q$12,IF(AND($M35<>0,$M35<=$BL$6),$M$12,IF(AND($J35<>0,$J35<=$BL$6),$J$12,0))))) -> 0.5 | AH35: =AI35-AG35 -> 0.25 | AI35: =IF(AND($Y35<>0,$Y35<=$BL$5),$Y$12,IF(AND($U35<>0,$U35<=$BL$5),$U$12,IF(AND($Q35<>0,$Q35<=$BL$5),$Q$12,IF(AND($M35<>0,$M35<=$BL$5),$M$12,IF(AND($J35<>0,$J35<=$BL$5),$J$12,0))))) -> 0.75 | AJ35: =IF(AND($W35<>0,$W35<=$BL$5),$W$12,IF(AND($S35<>0,$S35<=$BL$5),$S$12,IF(AND($O35<>0,$O35<=$BL$5),$O$12,IF(AND($K35<>0,$K35<=$BL$5),$K$12,IF(AND($H35<>0,$H35<=$BL$5),$H$12,0))))) -> 0.5 | AK35: =IF(AND($X35<>0,$X35<=$BL$5),$X$12,IF(AND($T35<>0,$T35<=$BL$5),$T$12,IF(AND($P35<>0,$P35<=$BL$5),$P$12,IF(AND($L35<>0,$L35<=$BL$5),$L$12,IF(AND($I35<>0,$I35<=$BL$5),$I$12,0))))) -> 0 | AL35: =AI35-AJ35 -> 0.25 | AM35: =AI35-AK35 -> 0.75 | AN35: =AI35*F35 -> 0.1053 | AO35: =AJ35*F35 -> 0.0702 | AP35: =AK35*F35 -> 0 | AQ35: =AN35-AO35 -> 0.0351 | AZ35: 0.0702 | BD35: 6.c | BE35: =AG35*F35 -> 0.0702 | BF35: =AI35*F35 -> 0.1053 | BG35: =IF(AND($W35<>0,$W35<=$BL$6),$W$12,IF(AND($S35<>0,$S35<=$BL$6),$S$12,IF(AND($O35<>0,$O35<=$BL$6),$O$12,IF(AND($K35<>0,$K35<=$BL$6),$K$12,IF(AND($H35<>0,$H35<=$BL$6),$H$12,0)))))*$F35 -> 0.0351 | BH35: =IF(AND($W35<>0,$W35<=$BL$5),$W$12,IF(AND($S35<>0,$S35<=$BL$5),$S$12,IF(AND($O35<>0,$O35<=$BL$5),$O$12,IF(AND($K35<>0,$K35<=$BL$5),$K$12,IF(AND($H35<>0,$H35<=$BL$5),$H$12,0)))))*$F35 -> 0.0702 | BI35: =IF(AND($X35<>0,$X35<=$BL$6),$X$12,IF(AND($T35<>0,$T35<=$BL$6),$T$12,IF(AND($P35<>0,$P35<=$BL$6),$P$12,IF(AND($L35<>0,$L35<=$BL$6),$L$12,IF(AND($I35<>0,$I35<=$BL$6),$I$12,0)))))*$F35 -> 0 | BJ35: =IF(AND($X35<>0,$X35<=$BL$5),$X$12,IF(AND($T35<>0,$T35<=$BL$5),$T$12,IF(AND($P35<>0,$P35<=$BL$5),$P$12,IF(AND($L35<>0,$L35<=$BL$5),$L$12,IF(AND($I35<>0,$I35<=$BL$5),$I$12,0)))))*$F35 -> 0 | BM35: 0 | BN35: =IF(AND($W35<>0,$W35<=BN$12),$W$12*$F35,IF(AND($S35<>0,$S35<=BN$12),$S$12*$F35,IF(AND($O35<>0,$O35<=BN$12),$O$12*$F35,IF(AND($K35<>0,$K35<=BN$12),$K$12*$F35,IF(AND($H35<>0,$H35<=BN$12),$H$12*$F35,0))))) -> 0 | BO35: =IF(AND($W35<>0,$W35<=BO$12),$W$12*$F35,IF(AND($S35<>0,$S35<=BO$12),$S$12*$F35,IF(AND($O35<>0,$O35<=BO$12),$O$12*$F35,IF(AND($K35<>0,$K35<=BO$12),$K$12*$F35,IF(AND($H35<>0,$H35<=BO$12),$H$12*$F35,0))))) -> 0 | BP35: =IF(AND($W35<>0,$W35<=BP$12),$W$12*$F35,IF(AND($S35<>0,$S35<=BP$12),$S$12*$F35,IF(AND($O35<>0,$O35<=BP$12),$O$12*$F35,IF(AND($K35<>0,$K35<=BP$12),$K$12*$F35,IF(AND($H35<>0,$H35<=BP$12),$H$12*$F35,0))))) -> 0 | BQ35: =IF(AND($W35<>0,$W35<=BQ$12),$W$12*$F35,IF(AND($S35<>0,$S35<=BQ$12),$S$12*$F35,IF(AND($O35<>0,$O35<=BQ$12),$O$12*$F35,IF(AND($K35<>0,$K35<=BQ$12),$K$12*$F35,IF(AND($H35<>0,$H35<=BQ$12),$H$12*$F35,0))))) -> 0 | BR35: =IF(AND($W35<>0,$W35<=BR$12),$W$12*$F35,IF(AND($S35<>0,$S35<=BR$12),$S$12*$F35,IF(AND($O35<>0,$O35<=BR$12),$O$12*$F35,IF(AND($K35<>0,$K35<=BR$12),$K$12*$F35,IF(AND($H35<>0,$H35<=BR$12),$H$12*$F35,0))))) -> 0 | BS35: =IF(AND($W35<>0,$W35<=BS$12),$W$12*$F35,IF(AND($S35<>0,$S35<=BS$12),$S$12*$F35,IF(AND($O35<>0,$O35<=BS$12),$O$12*$F35,IF(AND($K35<>0,$K35<=BS$12),$K$12*$F35,IF(AND($H35<>0,$H35<=BS$12),$H$12*$F35,0))))) -> 0 | BT35: =IF(AND($W35<>0,$W35<=BT$12),$W$12*$F35,IF(AND($S35<>0,$S35<=BT$12),$S$12*$F35,IF(AND($O35<>0,$O35<=BT$12),$O$12*$F35,IF(AND($K35<>0,$K35<=BT$12),$K$12*$F35,IF(AND($H35<>0,$H35<=BT$12),$H$12*$F35,0))))) -> 0 | BU35: =IF(AND($W35<>0,$W35<=BU$12),$W$12*$F35,IF(AND($S35<>0,$S35<=BU$12),$S$12*$F35,IF(AND($O35<>0,$O35<=BU$12),$O$12*$F35,IF(AND($K35<>0,$K35<=BU$12),$K$12*$F35,IF(AND($H35<>0,$H35<=BU$12),$H$12*$F35,0))))) -> 0 | ... CH35: =IF(AND($W35<>0,$W35<=CH$12),$W$12*$F35,IF(AND($S35<>0,$S35<=CH$12),$S$12*$F35,IF(AND($O35<>0,$O35<=CH$12),$O$12*$F35,IF(AND($K35<>0,$K35<=CH$12),$K$12*$F35,IF(AND($H35<>0,$H35<=CH$12),$H$12*$F35,0))))) -> 0.1404 | CL35: 0 | CM35: =IF(AND($X35<>0,$X35<=CM$12),$X$12*$F35,IF(AND($T35<>0,$T35<=CM$12),$T$12*$F35,IF(AND($P35<>0,$P35<=CM$12),$P$12*$F35,IF(AND($L35<>0,$L35<=CM$12),$L$12*$F35,IF(AND($I35<>0,$I35<=CM$12),$I$12*$F35,0))))) -> 0 | CN35: =IF(AND($X35<>0,$X35<=CN$12),$X$12*$F35,IF(AND($T35<>0,$T35<=CN$12),$T$12*$F35,IF(AND($P35<>0,$P35<=CN$12),$P$12*$F35,IF(AND($L35<>0,$L35<=CN$12),$L$12*$F35,IF(AND($I35<>0,$I35<=CN$12),$I$12*$F35,0))))) -> 0 | CO35: =IF(AND($X35<>0,$X35<=CO$12),$X$12*$F35,IF(AND($T35<>0,$T35<=CO$12),$T$12*$F35,IF(AND($P35<>0,$P35<=CO$12),$P$12*$F35,IF(AND($L35<>0,$L35<=CO$12),$L$12*$F35,IF(AND($I35<>0,$I35<=CO$12),$I$12*$F35,0))))) -> 0 | CP35: =IF(AND($X35<>0,$X35<=CP$12),$X$12*$F35,IF(AND($T35<>0,$T35<=CP$12),$T$12*$F35,IF(AND($P35<>0,$P35<=CP$12),$P$12*$F35,IF(AND($L35<>0,$L35<=CP$12),$L$12*$F35,IF(AND($I35<>0,$I35<=CP$12),$I$12*$F35,0))))) -> 0 | CQ35: =IF(AND($X35<>0,$X35<=CQ$12),$X$12*$F35,IF(AND($T35<>0,$T35<=CQ$12),$T$12*$F35,IF(AND($P35<>0,$P35<=CQ$12),$P$12*$F35,IF(AND($L35<>0,$L35<=CQ$12),$L$12*$F35,IF(AND($I35<>0,$I35<=CQ$12),$I$12*$F35,0))))) -> 0 | CR35: =IF(AND($X35<>0,$X35<=CR$12),$X$12*$F35,IF(AND($T35<>0,$T35<=CR$12),$T$12*$F35,IF(AND($P35<>0,$P35<=CR$12),$P$12*$F35,IF(AND($L35<>0,$L35<=CR$12),$L$12*$F35,IF(AND($I35<>0,$I35<=CR$12),$I$12*$F35,0))))) -> 0 | CS35: =IF(AND($X35<>0,$X35<=CS$12),$X$12*$F35,IF(AND($T35<>0,$T35<=CS$12),$T$12*$F35,IF(AND($P35<>0,$P35<=CS$12),$P$12*$F35,IF(AND($L35<>0,$L35<=CS$12),$L$12*$F35,IF(AND($I35<>0,$I35<=CS$12),$I$12*$F35,0))))) -> 0 | CT35: =IF(AND($X35<>0,$X35<=CT$12),$X$12*$F35,IF(AND($T35<>0,$T35<=CT$12),$T$12*$F35,IF(AND($P35<>0,$P35<=CT$12),$P$12*$F35,IF(AND($L35<>0,$L35<=CT$12),$L$12*$F35,IF(AND($I35<>0,$I35<=CT$12),$I$12*$F35,0))))) -> 0 | ... DG35: =IF(AND($X35<>0,$X35<=DG$12),$X$12*$F35,IF(AND($T35<>0,$T35<=DG$12),$T$12*$F35,IF(AND($P35<>0,$P35<=DG$12),$P$12*$F35,IF(AND($L35<>0,$L35<=DG$12),$L$12*$F35,IF(AND($I35<>0,$I35<=DG$12),$I$12*$F35,0))))) -> 0 | DL35: 0 | DM35: =IF(AND($Y35<>0,$Y35<=DM$12),$Y$12*$F35,IF(AND($U35<>0,$U35<=DM$12),$U$12*$F35,IF(AND($Q35<>0,$Q35<=DM$12),$Q$12*$F35,IF(AND($M35<>0,$M35<=DM$12),$M$12*$F35,IF(AND($J35<>0,$J35<=DM$12),$J$12*$F35,0))))) -> 0 | DN35: =IF(AND($Y35<>0,$Y35<=DN$12),$Y$12*$F35,IF(AND($U35<>0,$U35<=DN$12),$U$12*$F35,IF(AND($Q35<>0,$Q35<=DN$12),$Q$12*$F35,IF(AND($M35<>0,$M35<=DN$12),$M$12*$F35,IF(AND($J35<>0,$J35<=DN$12),$J$12*$F35,0))))) -> 0 | DO35: =IF(AND($Y35<>0,$Y35<=DO$12),$Y$12*$F35,IF(AND($U35<>0,$U35<=DO$12),$U$12*$F35,IF(AND($Q35<>0,$Q35<=DO$12),$Q$12*$F35,IF(AND($M35<>0,$M35<=DO$12),$M$12*$F35,IF(AND($J35<>0,$J35<=DO$12),$J$12*$F35,0))))) -> 0 | DP35: =IF(AND($Y35<>0,$Y35<=DP$12),$Y$12*$F35,IF(AND($U35<>0,$U35<=DP$12),$U$12*$F35,IF(AND($Q35<>0,$Q35<=DP$12),$Q$12*$F35,IF(AND($M35<>0,$M35<=DP$12),$M$12*$F35,IF(AND($J35<>0,$J35<=DP$12),$J$12*$F35,0))))) -> 0 | DQ35: =IF(AND($Y35<>0,$Y35<=DQ$12),$Y$12*$F35,IF(AND($U35<>0,$U35<=DQ$12),$U$12*$F35,IF(AND($Q35<>0,$Q35<=DQ$12),$Q$12*$F35,IF(AND($M35<>0,$M35<=DQ$12),$M$12*$F35,IF(AND($J35<>0,$J35<=DQ$12),$J$12*$F35,0))))) -> 0 | DR35: =IF(AND($Y35<>0,$Y35<=DR$12),$Y$12*$F35,IF(AND($U35<>0,$U35<=DR$12),$U$12*$F35,IF(AND($Q35<>0,$Q35<=DR$12),$Q$12*$F35,IF(AND($M35<>0,$M35<=DR$12),$M$12*$F35,IF(AND($J35<>0,$J35<=DR$12),$J$12*$F35,0))))) -> 0 | DS35: =IF(AND($Y35<>0,$Y35<=DS$12),$Y$12*$F35,IF(AND($U35<>0,$U35<=DS$12),$U$12*$F35,IF(AND($Q35<>0,$Q35<=DS$12),$Q$12*$F35,IF(AND($M35<>0,$M35<=DS$12),$M$12*$F35,IF(AND($J35<>0,$J35<=DS$12),$J$12*$F35,0))))) -> 0 | DT35: =IF(AND($Y35<>0,$Y35<=DT$12),$Y$12*$F35,IF(AND($U35<>0,$U35<=DT$12),$U$12*$F35,IF(AND($Q35<>0,$Q35<=DT$12),$Q$12*$F35,IF(AND($M35<>0,$M35<=DT$12),$M$12*$F35,IF(AND($J35<>0,$J35<=DT$12),$J$12*$F35,0))))) -> 0 | ... EG35: =IF(AND($Y35<>0,$Y35<=EG$12),$Y$12*$F35,IF(AND($U35<>0,$U35<=EG$12),$U$12*$F35,IF(AND($Q35<>0,$Q35<=EG$12),$Q$12*$F35,IF(AND($M35<>0,$M35<=EG$12),$M$12*$F35,IF(AND($J35<>0,$J35<=EG$12),$J$12*$F35,0))))) -> 0.1053
A36: 6.d | B36: W2026I-DNGF-EM-100-PRD-SPC-0014 | C36: Integrasi Data & Finalisasi Interaktivitas | F36: 0.0934 | H36: 46197 | J36: 46187 | K36: =H36+((O36-H36)*0.5) -> 46206.25 | M36: 46191 | O36: =H36+((W36-H36)*0.5) -> 46215.5 | Q36: 46202 | S36: =O36+((W36-O36)*0.5) -> 46224.75 | W36: 46234 | AE36: =AN36 -> 0.0467 | AG36: =IF(AND($Y36<>0,$Y36<=$BL$6),$Y$12,IF(AND($U36<>0,$U36<=$BL$6),$U$12,IF(AND($Q36<>0,$Q36<=$BL$6),$Q$12,IF(AND($M36<>0,$M36<=$BL$6),$M$12,IF(AND($J36<>0,$J36<=$BL$6),$J$12,0))))) -> 0.5 | AH36: =AI36-AG36 -> 0 | AI36: =IF(AND($Y36<>0,$Y36<=$BL$5),$Y$12,IF(AND($U36<>0,$U36<=$BL$5),$U$12,IF(AND($Q36<>0,$Q36<=$BL$5),$Q$12,IF(AND($M36<>0,$M36<=$BL$5),$M$12,IF(AND($J36<>0,$J36<=$BL$5),$J$12,0))))) -> 0.5 | AJ36: =IF(AND($W36<>0,$W36<=$BL$5),$W$12,IF(AND($S36<>0,$S36<=$BL$5),$S$12,IF(AND($O36<>0,$O36<=$BL$5),$O$12,IF(AND($K36<>0,$K36<=$BL$5),$K$12,IF(AND($H36<>0,$H36<=$BL$5),$H$12,0))))) -> 0.25 | AK36: =IF(AND($X36<>0,$X36<=$BL$5),$X$12,IF(AND($T36<>0,$T36<=$BL$5),$T$12,IF(AND($P36<>0,$P36<=$BL$5),$P$12,IF(AND($L36<>0,$L36<=$BL$5),$L$12,IF(AND($I36<>0,$I36<=$BL$5),$I$12,0))))) -> 0 | AL36: =AI36-AJ36 -> 0.25 | AM36: =AI36-AK36 -> 0.5 | AN36: =AI36*F36 -> 0.0467 | AO36: =AJ36*F36 -> 0.02335 | AP36: =AK36*F36 -> 0 | AQ36: =AN36-AO36 -> 0.02335 | AZ36: 0.02335 | BD36: 6.d | BE36: =AG36*F36 -> 0.0467 | BF36: =AI36*F36 -> 0.0467 | BG36: =IF(AND($W36<>0,$W36<=$BL$6),$W$12,IF(AND($S36<>0,$S36<=$BL$6),$S$12,IF(AND($O36<>0,$O36<=$BL$6),$O$12,IF(AND($K36<>0,$K36<=$BL$6),$K$12,IF(AND($H36<>0,$H36<=$BL$6),$H$12,0)))))*$F36 -> 0.00467 | BH36: =IF(AND($W36<>0,$W36<=$BL$5),$W$12,IF(AND($S36<>0,$S36<=$BL$5),$S$12,IF(AND($O36<>0,$O36<=$BL$5),$O$12,IF(AND($K36<>0,$K36<=$BL$5),$K$12,IF(AND($H36<>0,$H36<=$BL$5),$H$12,0)))))*$F36 -> 0.02335 | BI36: =IF(AND($X36<>0,$X36<=$BL$6),$X$12,IF(AND($T36<>0,$T36<=$BL$6),$T$12,IF(AND($P36<>0,$P36<=$BL$6),$P$12,IF(AND($L36<>0,$L36<=$BL$6),$L$12,IF(AND($I36<>0,$I36<=$BL$6),$I$12,0)))))*$F36 -> 0 | BJ36: =IF(AND($X36<>0,$X36<=$BL$5),$X$12,IF(AND($T36<>0,$T36<=$BL$5),$T$12,IF(AND($P36<>0,$P36<=$BL$5),$P$12,IF(AND($L36<>0,$L36<=$BL$5),$L$12,IF(AND($I36<>0,$I36<=$BL$5),$I$12,0)))))*$F36 -> 0 | BM36: 0 | BN36: =IF(AND($W36<>0,$W36<=BN$12),$W$12*$F36,IF(AND($S36<>0,$S36<=BN$12),$S$12*$F36,IF(AND($O36<>0,$O36<=BN$12),$O$12*$F36,IF(AND($K36<>0,$K36<=BN$12),$K$12*$F36,IF(AND($H36<>0,$H36<=BN$12),$H$12*$F36,0))))) -> 0 | BO36: =IF(AND($W36<>0,$W36<=BO$12),$W$12*$F36,IF(AND($S36<>0,$S36<=BO$12),$S$12*$F36,IF(AND($O36<>0,$O36<=BO$12),$O$12*$F36,IF(AND($K36<>0,$K36<=BO$12),$K$12*$F36,IF(AND($H36<>0,$H36<=BO$12),$H$12*$F36,0))))) -> 0 | BP36: =IF(AND($W36<>0,$W36<=BP$12),$W$12*$F36,IF(AND($S36<>0,$S36<=BP$12),$S$12*$F36,IF(AND($O36<>0,$O36<=BP$12),$O$12*$F36,IF(AND($K36<>0,$K36<=BP$12),$K$12*$F36,IF(AND($H36<>0,$H36<=BP$12),$H$12*$F36,0))))) -> 0 | BQ36: =IF(AND($W36<>0,$W36<=BQ$12),$W$12*$F36,IF(AND($S36<>0,$S36<=BQ$12),$S$12*$F36,IF(AND($O36<>0,$O36<=BQ$12),$O$12*$F36,IF(AND($K36<>0,$K36<=BQ$12),$K$12*$F36,IF(AND($H36<>0,$H36<=BQ$12),$H$12*$F36,0))))) -> 0 | BR36: =IF(AND($W36<>0,$W36<=BR$12),$W$12*$F36,IF(AND($S36<>0,$S36<=BR$12),$S$12*$F36,IF(AND($O36<>0,$O36<=BR$12),$O$12*$F36,IF(AND($K36<>0,$K36<=BR$12),$K$12*$F36,IF(AND($H36<>0,$H36<=BR$12),$H$12*$F36,0))))) -> 0 | BS36: =IF(AND($W36<>0,$W36<=BS$12),$W$12*$F36,IF(AND($S36<>0,$S36<=BS$12),$S$12*$F36,IF(AND($O36<>0,$O36<=BS$12),$O$12*$F36,IF(AND($K36<>0,$K36<=BS$12),$K$12*$F36,IF(AND($H36<>0,$H36<=BS$12),$H$12*$F36,0))))) -> 0 | BT36: =IF(AND($W36<>0,$W36<=BT$12),$W$12*$F36,IF(AND($S36<>0,$S36<=BT$12),$S$12*$F36,IF(AND($O36<>0,$O36<=BT$12),$O$12*$F36,IF(AND($K36<>0,$K36<=BT$12),$K$12*$F36,IF(AND($H36<>0,$H36<=BT$12),$H$12*$F36,0))))) -> 0 | BU36: =IF(AND($W36<>0,$W36<=BU$12),$W$12*$F36,IF(AND($S36<>0,$S36<=BU$12),$S$12*$F36,IF(AND($O36<>0,$O36<=BU$12),$O$12*$F36,IF(AND($K36<>0,$K36<=BU$12),$K$12*$F36,IF(AND($H36<>0,$H36<=BU$12),$H$12*$F36,0))))) -> 0 | ... CH36: =IF(AND($W36<>0,$W36<=CH$12),$W$12*$F36,IF(AND($S36<>0,$S36<=CH$12),$S$12*$F36,IF(AND($O36<>0,$O36<=CH$12),$O$12*$F36,IF(AND($K36<>0,$K36<=CH$12),$K$12*$F36,IF(AND($H36<>0,$H36<=CH$12),$H$12*$F36,0))))) -> 0.0934 | CL36: 0 | CM36: =IF(AND($X36<>0,$X36<=CM$12),$X$12*$F36,IF(AND($T36<>0,$T36<=CM$12),$T$12*$F36,IF(AND($P36<>0,$P36<=CM$12),$P$12*$F36,IF(AND($L36<>0,$L36<=CM$12),$L$12*$F36,IF(AND($I36<>0,$I36<=CM$12),$I$12*$F36,0))))) -> 0 | CN36: =IF(AND($X36<>0,$X36<=CN$12),$X$12*$F36,IF(AND($T36<>0,$T36<=CN$12),$T$12*$F36,IF(AND($P36<>0,$P36<=CN$12),$P$12*$F36,IF(AND($L36<>0,$L36<=CN$12),$L$12*$F36,IF(AND($I36<>0,$I36<=CN$12),$I$12*$F36,0))))) -> 0 | CO36: =IF(AND($X36<>0,$X36<=CO$12),$X$12*$F36,IF(AND($T36<>0,$T36<=CO$12),$T$12*$F36,IF(AND($P36<>0,$P36<=CO$12),$P$12*$F36,IF(AND($L36<>0,$L36<=CO$12),$L$12*$F36,IF(AND($I36<>0,$I36<=CO$12),$I$12*$F36,0))))) -> 0 | CP36: =IF(AND($X36<>0,$X36<=CP$12),$X$12*$F36,IF(AND($T36<>0,$T36<=CP$12),$T$12*$F36,IF(AND($P36<>0,$P36<=CP$12),$P$12*$F36,IF(AND($L36<>0,$L36<=CP$12),$L$12*$F36,IF(AND($I36<>0,$I36<=CP$12),$I$12*$F36,0))))) -> 0 | CQ36: =IF(AND($X36<>0,$X36<=CQ$12),$X$12*$F36,IF(AND($T36<>0,$T36<=CQ$12),$T$12*$F36,IF(AND($P36<>0,$P36<=CQ$12),$P$12*$F36,IF(AND($L36<>0,$L36<=CQ$12),$L$12*$F36,IF(AND($I36<>0,$I36<=CQ$12),$I$12*$F36,0))))) -> 0 | CR36: =IF(AND($X36<>0,$X36<=CR$12),$X$12*$F36,IF(AND($T36<>0,$T36<=CR$12),$T$12*$F36,IF(AND($P36<>0,$P36<=CR$12),$P$12*$F36,IF(AND($L36<>0,$L36<=CR$12),$L$12*$F36,IF(AND($I36<>0,$I36<=CR$12),$I$12*$F36,0))))) -> 0 | CS36: =IF(AND($X36<>0,$X36<=CS$12),$X$12*$F36,IF(AND($T36<>0,$T36<=CS$12),$T$12*$F36,IF(AND($P36<>0,$P36<=CS$12),$P$12*$F36,IF(AND($L36<>0,$L36<=CS$12),$L$12*$F36,IF(AND($I36<>0,$I36<=CS$12),$I$12*$F36,0))))) -> 0 | CT36: =IF(AND($X36<>0,$X36<=CT$12),$X$12*$F36,IF(AND($T36<>0,$T36<=CT$12),$T$12*$F36,IF(AND($P36<>0,$P36<=CT$12),$P$12*$F36,IF(AND($L36<>0,$L36<=CT$12),$L$12*$F36,IF(AND($I36<>0,$I36<=CT$12),$I$12*$F36,0))))) -> 0 | ... DG36: =IF(AND($X36<>0,$X36<=DG$12),$X$12*$F36,IF(AND($T36<>0,$T36<=DG$12),$T$12*$F36,IF(AND($P36<>0,$P36<=DG$12),$P$12*$F36,IF(AND($L36<>0,$L36<=DG$12),$L$12*$F36,IF(AND($I36<>0,$I36<=DG$12),$I$12*$F36,0))))) -> 0 | DL36: 0 | DM36: =IF(AND($Y36<>0,$Y36<=DM$12),$Y$12*$F36,IF(AND($U36<>0,$U36<=DM$12),$U$12*$F36,IF(AND($Q36<>0,$Q36<=DM$12),$Q$12*$F36,IF(AND($M36<>0,$M36<=DM$12),$M$12*$F36,IF(AND($J36<>0,$J36<=DM$12),$J$12*$F36,0))))) -> 0 | DN36: =IF(AND($Y36<>0,$Y36<=DN$12),$Y$12*$F36,IF(AND($U36<>0,$U36<=DN$12),$U$12*$F36,IF(AND($Q36<>0,$Q36<=DN$12),$Q$12*$F36,IF(AND($M36<>0,$M36<=DN$12),$M$12*$F36,IF(AND($J36<>0,$J36<=DN$12),$J$12*$F36,0))))) -> 0 | DO36: =IF(AND($Y36<>0,$Y36<=DO$12),$Y$12*$F36,IF(AND($U36<>0,$U36<=DO$12),$U$12*$F36,IF(AND($Q36<>0,$Q36<=DO$12),$Q$12*$F36,IF(AND($M36<>0,$M36<=DO$12),$M$12*$F36,IF(AND($J36<>0,$J36<=DO$12),$J$12*$F36,0))))) -> 0 | DP36: =IF(AND($Y36<>0,$Y36<=DP$12),$Y$12*$F36,IF(AND($U36<>0,$U36<=DP$12),$U$12*$F36,IF(AND($Q36<>0,$Q36<=DP$12),$Q$12*$F36,IF(AND($M36<>0,$M36<=DP$12),$M$12*$F36,IF(AND($J36<>0,$J36<=DP$12),$J$12*$F36,0))))) -> 0 | DQ36: =IF(AND($Y36<>0,$Y36<=DQ$12),$Y$12*$F36,IF(AND($U36<>0,$U36<=DQ$12),$U$12*$F36,IF(AND($Q36<>0,$Q36<=DQ$12),$Q$12*$F36,IF(AND($M36<>0,$M36<=DQ$12),$M$12*$F36,IF(AND($J36<>0,$J36<=DQ$12),$J$12*$F36,0))))) -> 0 | DR36: =IF(AND($Y36<>0,$Y36<=DR$12),$Y$12*$F36,IF(AND($U36<>0,$U36<=DR$12),$U$12*$F36,IF(AND($Q36<>0,$Q36<=DR$12),$Q$12*$F36,IF(AND($M36<>0,$M36<=DR$12),$M$12*$F36,IF(AND($J36<>0,$J36<=DR$12),$J$12*$F36,0))))) -> 0 | DS36: =IF(AND($Y36<>0,$Y36<=DS$12),$Y$12*$F36,IF(AND($U36<>0,$U36<=DS$12),$U$12*$F36,IF(AND($Q36<>0,$Q36<=DS$12),$Q$12*$F36,IF(AND($M36<>0,$M36<=DS$12),$M$12*$F36,IF(AND($J36<>0,$J36<=DS$12),$J$12*$F36,0))))) -> 0 | DT36: =IF(AND($Y36<>0,$Y36<=DT$12),$Y$12*$F36,IF(AND($U36<>0,$U36<=DT$12),$U$12*$F36,IF(AND($Q36<>0,$Q36<=DT$12),$Q$12*$F36,IF(AND($M36<>0,$M36<=DT$12),$M$12*$F36,IF(AND($J36<>0,$J36<=DT$12),$J$12*$F36,0))))) -> 0 | ... EG36: =IF(AND($Y36<>0,$Y36<=EG$12),$Y$12*$F36,IF(AND($U36<>0,$U36<=EG$12),$U$12*$F36,IF(AND($Q36<>0,$Q36<=EG$12),$Q$12*$F36,IF(AND($M36<>0,$M36<=EG$12),$M$12*$F36,IF(AND($J36<>0,$J36<=EG$12),$J$12*$F36,0))))) -> 0.0467
D38: OVERALL PROJECT | AE38: =SUM(AE16:AE37) -> 0.8667 | AG38: =BE38 -> 0.8316 | AH38: =AI38-AG38 -> 0.0351 | AI38: =BF38 -> 0.8667 | AJ38: =BH38 -> 0.85975 | AK38: =BJ38 -> 0.0309 | AL38: =AI38-AJ38 -> 0.00695 | AM38: =AI38-AK38 -> 0.8358 | AN38: =BF38 -> 0.8667 | AO38: =BH38 -> 0.85975 | AP38: =BJ38 -> 0.0309 | AQ38: =AN38-AO38 -> 0.00695 | BE38: =BE15 -> 0.8316 | BF38: =BF15 -> 0.8667 | BG38: =BG15 -> 0.754145 | BH38: =BH15 -> 0.85975 | BI38: =BI15 -> 0.0309 | BJ38: =BJ15 -> 0.0309
BL40: ACTIVITY | CK40: ACTIVITY | DK40: ACTIVITY
BL41: 1 | BM41: =BM16 -> 0 | BN41: =BN16 -> 0.04635 | BO41: =BO16 -> 0.069525 | BP41: =BP16 -> 0.0927 | BQ41: =BQ16 -> 0.0927 | BR41: =BR16 -> 0.0927 | BS41: =BS16 -> 0.0927 | BT41: =BT16 -> 0.0927 | ... CH41: =CH16 -> 0.0927 | CK41: 1 | CL41: =CL16 -> 0 | CM41: =CM16 -> 0 | CN41: =CN16 -> 0 | CO41: =CO16 -> 0 | CP41: =CP16 -> 0 | CQ41: =CQ16 -> 0 | CR41: =CR16 -> 0 | CS41: =CS16 -> 0 | ... DG41: =DG16 -> 0 | DK41: 1 | DL41: =DL16 -> 0 | DM41: =DM16 -> 0.069525 | DN41: =DN16 -> 0.0927 | DO41: =DO16 -> 0.0927 | DP41: =DP16 -> 0.0927 | DQ41: =DQ16 -> 0.0927 | DR41: =DR16 -> 0.0927 | DS41: =DS16 -> 0.0927 | ... EG41: =EG16 -> 0.0927
BL42: 2 | BM42: =BM19 -> 0 | BN42: =BN19 -> 0 | BO42: =BO19 -> 0 | BP42: =BP19 -> 0 | BQ42: =BQ19 -> 0 | BR42: =BR19 -> 0 | BS42: =BS19 -> 0.002575 | BT42: =BT19 -> 0.02575 | ... CH42: =CH19 -> 0.0515 | CK42: 2 | CL42: =CL19 -> 0 | CM42: =CM19 -> 0 | CN42: =CN19 -> 0 | CO42: =CO19 -> 0 | CP42: =CP19 -> 0 | CQ42: =CQ19 -> 0 | CR42: =CR19 -> 0 | CS42: =CS19 -> 0 | ... DG42: =DG19 -> 0.038625 | DK42: 2 | DL42: =DL19 -> 0 | DM42: =DM19 -> 0 | DN42: =DN19 -> 0 | DO42: =DO19 -> 0 | DP42: =DP19 -> 0 | DQ42: =DQ19 -> 0 | DR42: =DR19 -> 0 | DS42: =DS19 -> 0 | ... EG42: =EG19 -> 0
A43: PRD | B43: Procedure | BL43: 3 | BM43: =BM21 -> 0 | BN43: =BN21 -> 0.010825 | BO43: =BO21 -> 0.02165 | BP43: =BP21 -> 0.032475 | BQ43: =BQ21 -> 0.048925 | BR43: =BR21 -> 0.071425 | BS43: =BS21 -> 0.09955 | BT43: =BT21 -> 0.127675 | ... CH43: =CH21 -> 0.1733 | CK43: 3 | CL43: =CL21 -> 0 | CM43: =CM21 -> 0 | CN43: =CN21 -> 0 | CO43: =CO21 -> 0 | CP43: =CP21 -> 0 | CQ43: =CQ21 -> 0 | CR43: =CR21 -> 0 | CS43: =CS21 -> 0 | ... DG43: =DG21 -> 0 | DK43: 3 | DL43: =DL21 -> 0 | DM43: =DM21 -> 0.10185 | DN43: =DN21 -> 0.1733 | DO43: =DO21 -> 0.1733 | DP43: =DP21 -> 0.1733 | DQ43: =DQ21 -> 0.1733 | DR43: =DR21 -> 0.1733 | DS43: =DS21 -> 0.1733 | ... EG43: =EG21 -> 0.1733
A44: SPC | B44: Specification | BL44: 4 | BM44: =BM25 -> 0 | BN44: =BN25 -> 0 | BO44: =BO25 -> 0 | BP44: =BP25 -> 0 | BQ44: =BQ25 -> 0.007385 | BR44: =BR25 -> 0.018385 | BS44: =BS25 -> 0.050675 | BT44: =BT25 -> 0.0876 | ... CH44: =CH25 -> 0.1854 | CK44: 4 | CL44: =CL25 -> 0 | CM44: =CM25 -> 0 | CN44: =CN25 -> 0 | CO44: =CO25 -> 0 | CP44: =CP25 -> 0 | CQ44: =CQ25 -> 0 | CR44: =CR25 -> 0 | CS44: =CS25 -> 0 | ... DG44: =DG25 -> 0 | DK44: 4 | DL44: =DL25 -> 0 | DM44: =DM25 -> 0.04635 | DN44: =DN25 -> 0.0927 | DO44: =DO25 -> 0.10645 | DP44: =DP25 -> 0.10645 | DQ44: =DQ25 -> 0.10645 | DR44: =DR25 -> 0.10645 | DS44: =DS25 -> 0.115875 | ... EG44: =EG25 -> 0.1854
A45: DRW | B45: Drawing | BL45: 5 | BM45: =BM29 -> 0 | BN45: =BN29 -> 0.00618 | BO45: =BO29 -> 0.00927 | BP45: =BP29 -> 0.04635 | BQ45: =BQ29 -> 0.0618 | BR45: =BR29 -> 0.07725 | BS45: =BS29 -> 0.1236 | BT45: =BT29 -> 0.1236 | ... CH45: =CH29 -> 0.1854 | CK45: 5 | CL45: =CL29 -> 0 | CM45: =CM29 -> 0 | CN45: =CN29 -> 0 | CO45: =CO29 -> 0.0309 | CP45: =CP29 -> 0.0309 | CQ45: =CQ29 -> 0.0309 | CR45: =CR29 -> 0.0309 | CS45: =CS29 -> 0.0309 | ... DG45: =DG29 -> 0.0309 | DK45: 5 | DL45: =DL29 -> 0 | DM45: =DM29 -> 0 | DN45: =DN29 -> 0.00309 | DO45: =DO29 -> 0.04635 | DP45: =DP29 -> 0.0618 | DQ45: =DQ29 -> 0.07725 | DR45: =DR29 -> 0.1236 | DS45: =DS29 -> 0.1236 | ... EG45: =EG29 -> 0.1854
A46: RPT | B46: Reports | BL46: 6 | BM46: =BM32 -> 0 | BN46: =BN32 -> 0 | BO46: =BO32 -> 0 | BP46: =BP32 -> 0 | BQ46: =BQ32 -> 0.00331 | BR46: =BR32 -> 0.00331 | BS46: =BS32 -> 0.01655 | BT46: =BT32 -> 0.01655 | ... CH46: =CH32 -> 0.3117 | CK46: 6 | CL46: =CL32 -> 0 | CM46: =CM32 -> 0 | CN46: =CN32 -> 0 | CO46: =CO32 -> 0 | CP46: =CP32 -> 0 | CQ46: =CQ32 -> 0 | CR46: =CR32 -> 0 | CS46: =CS32 -> 0 | ... DG46: =DG32 -> 0 | DK46: 6 | DL46: =DL32 -> 0 | DM46: =DM32 -> 0 | DN46: =DN32 -> 0 | DO46: =DO32 -> 0 | DP46: =DP32 -> 0.00331 | DQ46: =DQ32 -> 0.00331 | DR46: =DR32 -> 0.01655 | DS46: =DS32 -> 0.01655 | ... EG46: =EG32 -> 0.2299
A47: BOQ | B47: Bill of Quantity | H47: Aktual | I47: Plan | BL47: OVERALL | BM47: =SUM(BM41:BM46) -> 0 | BN47: =SUM(BN41:BN46) -> 0.063355 | BO47: =SUM(BO41:BO46) -> 0.100445 | BP47: =SUM(BP41:BP46) -> 0.171525 | BQ47: =SUM(BQ41:BQ46) -> 0.21412 | BR47: =SUM(BR41:BR46) -> 0.26307 | BS47: =SUM(BS41:BS46) -> 0.38565 | BT47: =SUM(BT41:BT46) -> 0.473875 | ... CH47: =SUM(CH41:CH46) -> 1 | CK47: OVERALL | CL47: =SUM(CL41:CL46) -> 0 | CM47: =SUM(CM41:CM46) -> 0 | CN47: =SUM(CN41:CN46) -> 0 | CO47: =SUM(CO41:CO46) -> 0.0309 | CP47: =SUM(CP41:CP46) -> 0.0309 | CQ47: =SUM(CQ41:CQ46) -> 0.0309 | CR47: =SUM(CR41:CR46) -> 0.0309 | CS47: =SUM(CS41:CS46) -> 0.0309 | ... DG47: =SUM(DG41:DG46) -> 0.069525 | DK47: OVERALL | DL47: =SUM(DL41:DL46) -> 0 | DM47: =SUM(DM41:DM46) -> 0.217725 | DN47: =SUM(DN41:DN46) -> 0.36179 | DO47: =SUM(DO41:DO46) -> 0.4188 | DP47: =SUM(DP41:DP46) -> 0.43756 | DQ47: =SUM(DQ41:DQ46) -> 0.45301 | DR47: =SUM(DR41:DR46) -> 0.5126 | DS47: =SUM(DS41:DS46) -> 0.522025 | ... EG47: =SUM(EG41:EG46) -> 0.8667
A48: DSH | B48: Data Sheet | G48: 1.a | H48: =MAX(J17,M17,Q17,U17,Y17) -> 46131 | I48: =MAX(H17,K17,O17,S17,W17) -> 46133 | J48: 46131
A49: CALC | B49: Calculation | G49: 1.b | H49: =MAX(J18,M18,Q18,U18,Y18) -> 46131 | I49: =MAX(H18,K18,O18,S18,W18) -> 46133 | J49: 46131 | BK49: WF | BL49: ACTIVITY | CJ49: WF | CK49: ACTIVITY | DJ49: WF | DK49: ACTIVITY
A50: VDOC | B50: Vendor Document | G50: 2 | H50: =MAX(J19,M19,Q19,U19,Y19) -> 0 | I50: =MAX(H19,K19,O19,S19,W19) -> 0 | J50: 0 | BK50: =F16 -> 0.0927 | BL50: 1 | BM50: =BM41/$BK50 -> 0 | BN50: =BN41/$BK50 -> 0.5 | BO50: =BO41/$BK50 -> 0.75 | BP50: =BP41/$BK50 -> 1 | BQ50: =BQ41/$BK50 -> 1 | BR50: =BR41/$BK50 -> 1 | BS50: =BS41/$BK50 -> 1 | BT50: =BT41/$BK50 -> 1 | ... CH50: =CH41/$BK50 -> 1 | CJ50: =$BK50 -> 0.0927 | CK50: 1 | CL50: =CL41/$CJ50 -> 0 | CM50: =CM41/$CJ50 -> 0 | CN50: =CN41/$CJ50 -> 0 | CO50: =CO41/$CJ50 -> 0 | CP50: =CP41/$CJ50 -> 0 | CQ50: =CQ41/$CJ50 -> 0 | CR50: =CR41/$CJ50 -> 0 | CS50: =CS41/$CJ50 -> 0 | ... DG50: =DG41/$CJ50 -> 0 | DJ50: =$BK50 -> 0.0927 | DK50: 1 | DL50: =DL41/$DJ50 -> 0 | DM50: =DM41/$DJ50 -> 0.75 | DN50: =DN41/$DJ50 -> 1 | DO50: =DO41/$DJ50 -> 1 | DP50: =DP41/$DJ50 -> 1 | DQ50: =DQ41/$DJ50 -> 1 | DR50: =DR41/$DJ50 -> 1 | DS50: =DS41/$DJ50 -> 1 | ... EG50: =EG41/$DJ50 -> 1
G51: 2.a | H51: =MAX(J20,M20,Q20,U20,Y20) -> 0 | I51: =MAX(H20,K20,O20,S20,W20) -> 46173 | J51: 0 | BK51: =F19 -> 0.0515 | BL51: 2 | BM51: =BM42/$BK51 -> 0 | BN51: =BN42/$BK51 -> 0 | BO51: =BO42/$BK51 -> 0 | BP51: =BP42/$BK51 -> 0 | BQ51: =BQ42/$BK51 -> 0 | BR51: =BR42/$BK51 -> 0 | BS51: =BS42/$BK51 -> 0.05 | BT51: =BT42/$BK51 -> 0.5 | ... CH51: =CH42/$BK51 -> 1 | CJ51: =$BK51 -> 0.0515 | CK51: 2 | CL51: =CL42/$CJ51 -> 0 | CM51: =CM42/$CJ51 -> 0 | CN51: =CN42/$CJ51 -> 0 | CO51: =CO42/$CJ51 -> 0 | CP51: =CP42/$CJ51 -> 0 | CQ51: =CQ42/$CJ51 -> 0 | CR51: =CR42/$CJ51 -> 0 | CS51: =CS42/$CJ51 -> 0 | ... DG51: =DG42/$CJ51 -> 0.75 | DJ51: =$BK51 -> 0.0515 | DK51: 2 | DL51: =DL42/$DJ51 -> 0 | DM51: =DM42/$DJ51 -> 0 | DN51: =DN42/$DJ51 -> 0 | DO51: =DO42/$DJ51 -> 0 | DP51: =DP42/$DJ51 -> 0 | DQ51: =DQ42/$DJ51 -> 0 | DR51: =DR42/$DJ51 -> 0 | DS51: =DS42/$DJ51 -> 0 | ... EG51: =EG42/$DJ51 -> 0
G52: 3 | H52: =MAX(J21,M21,Q21,U21,Y21) -> 0 | I52: =MAX(H21,K21,O21,S21,W21) -> 0 | J52: 0 | BK52: =F21 -> 0.1733 | BL52: 3 | BM52: =BM43/$BK52 -> 0 | BN52: =BN43/$BK52 -> 0.062463935 | BO52: =BO43/$BK52 -> 0.12492787 | BP52: =BP43/$BK52 -> 0.18739181 | BQ52: =BQ43/$BK52 -> 0.28231391 | BR52: =BR43/$BK52 -> 0.41214657 | BS52: =BS43/$BK52 -> 0.57443739 | BT52: =BT43/$BK52 -> 0.73672822 | ... CH52: =CH43/$BK52 -> 1 | CJ52: =$BK52 -> 0.1733 | CK52: 3 | CL52: =CL43/$CJ52 -> 0 | CM52: =CM43/$CJ52 -> 0 | CN52: =CN43/$CJ52 -> 0 | CO52: =CO43/$CJ52 -> 0 | CP52: =CP43/$CJ52 -> 0 | CQ52: =CQ43/$CJ52 -> 0 | CR52: =CR43/$CJ52 -> 0 | CS52: =CS43/$CJ52 -> 0 | ... DG52: =DG43/$CJ52 -> 0 | DJ52: =$BK52 -> 0.1733 | DK52: 3 | DL52: =DL43/$DJ52 -> 0 | DM52: =DM43/$DJ52 -> 0.58770917 | DN52: =DN43/$DJ52 -> 1 | DO52: =DO43/$DJ52 -> 1 | DP52: =DP43/$DJ52 -> 1 | DQ52: =DQ43/$DJ52 -> 1 | DR52: =DR43/$DJ52 -> 1 | DS52: =DS43/$DJ52 -> 1 | ... EG52: =EG43/$DJ52 -> 1
G53: 3.a | H53: =MAX(J22,M22,Q22,U22,Y22) -> 46126 | I53: =MAX(H22,K22,O22,S22,W22) -> 46142 | J53: 46126 | BK53: =F25 -> 0.1854 | BL53: 4 | BM53: =BM44/$BK53 -> 0 | BN53: =BN44/$BK53 -> 0 | BO53: =BO44/$BK53 -> 0 | BP53: =BP44/$BK53 -> 0 | BQ53: =BQ44/$BK53 -> 0.039832794 | BR53: =BR44/$BK53 -> 0.09916397 | BS53: =BS44/$BK53 -> 0.27332794 | BT53: =BT44/$BK53 -> 0.47249191 | ... CH53: =CH44/$BK53 -> 1 | CJ53: =$BK53 -> 0.1854 | CK53: 4 | CL53: =CL44/$CJ53 -> 0 | CM53: =CM44/$CJ53 -> 0 | CN53: =CN44/$CJ53 -> 0 | CO53: =CO44/$CJ53 -> 0 | CP53: =CP44/$CJ53 -> 0 | CQ53: =CQ44/$CJ53 -> 0 | CR53: =CR44/$CJ53 -> 0 | CS53: =CS44/$CJ53 -> 0 | ... DG53: =DG44/$CJ53 -> 0 | DJ53: =$BK53 -> 0.1854 | DK53: 4 | DL53: =DL44/$DJ53 -> 0 | DM53: =DM44/$DJ53 -> 0.25 | DN53: =DN44/$DJ53 -> 0.5 | DO53: =DO44/$DJ53 -> 0.57416397 | DP53: =DP44/$DJ53 -> 0.57416397 | DQ53: =DQ44/$DJ53 -> 0.57416397 | DR53: =DR44/$DJ53 -> 0.57416397 | DS53: =DS44/$DJ53 -> 0.625 | ... EG53: =EG44/$DJ53 -> 1
G54: 3.b | H54: =MAX(J23,M23,Q23,U23,Y23) -> 46131 | I54: =MAX(H23,K23,O23,S23,W23) -> 46173 | J54: 46131 | BK54: =F29 -> 0.1854 | BL54: 5 | BM54: =BM45/$BK54 -> 0 | BN54: =BN45/$BK54 -> 0.033333333 | BO54: =BO45/$BK54 -> 0.05 | BP54: =BP45/$BK54 -> 0.25 | BQ54: =BQ45/$BK54 -> 0.33333333 | BR54: =BR45/$BK54 -> 0.41666667 | BS54: =BS45/$BK54 -> 0.66666667 | BT54: =BT45/$BK54 -> 0.66666667 | ... CH54: =CH45/$BK54 -> 1 | CJ54: =$BK54 -> 0.1854 | CK54: 5 | CL54: =CL45/$CJ54 -> 0 | CM54: =CM45/$CJ54 -> 0 | CN54: =CN45/$CJ54 -> 0 | CO54: =CO45/$CJ54 -> 0.16666667 | CP54: =CP45/$CJ54 -> 0.16666667 | CQ54: =CQ45/$CJ54 -> 0.16666667 | CR54: =CR45/$CJ54 -> 0.16666667 | CS54: =CS45/$CJ54 -> 0.16666667 | ... DG54: =DG45/$CJ54 -> 0.16666667 | DJ54: =$BK54 -> 0.1854 | DK54: 5 | DL54: =DL45/$DJ54 -> 0 | DM54: =DM45/$DJ54 -> 0 | DN54: =DN45/$DJ54 -> 0.016666667 | DO54: =DO45/$DJ54 -> 0.25 | DP54: =DP45/$DJ54 -> 0.33333333 | DQ54: =DQ45/$DJ54 -> 0.41666667 | DR54: =DR45/$DJ54 -> 0.66666667 | DS54: =DS45/$DJ54 -> 0.66666667 | ... EG54: =EG45/$DJ54 -> 1
G55: 3.c | H55: =MAX(J24,M24,Q24,U24,Y24) -> 46126 | I55: =MAX(H24,K24,O24,S24,W24) -> 46203 | J55: 46126 | BK55: =F32 -> 0.3117 | BL55: 6 | BM55: =BM46/$BK55 -> 0 | BN55: =BN46/$BK55 -> 0 | BO55: =BO46/$BK55 -> 0 | BP55: =BP46/$BK55 -> 0 | BQ55: =BQ46/$BK55 -> 0.010619185 | BR55: =BR46/$BK55 -> 0.010619185 | BS55: =BS46/$BK55 -> 0.053095926 | BT55: =BT46/$BK55 -> 0.053095926 | ... CH55: =CH46/$BK55 -> 1 | CJ55: =$BK55 -> 0.3117 | CK55: 6 | CL55: =CL46/$CJ55 -> 0 | CM55: =CM46/$CJ55 -> 0 | CN55: =CN46/$CJ55 -> 0 | CO55: =CO46/$CJ55 -> 0 | CP55: =CP46/$CJ55 -> 0 | CQ55: =CQ46/$CJ55 -> 0 | CR55: =CR46/$CJ55 -> 0 | CS55: =CS46/$CJ55 -> 0 | ... DG55: =DG46/$CJ55 -> 0 | DJ55: =$BK55 -> 0.3117 | DK55: 6 | DL55: =DL46/$DJ55 -> 0 | DM55: =DM46/$DJ55 -> 0 | DN55: =DN46/$DJ55 -> 0 | DO55: =DO46/$DJ55 -> 0 | DP55: =DP46/$DJ55 -> 0.010619185 | DQ55: =DQ46/$DJ55 -> 0.010619185 | DR55: =DR46/$DJ55 -> 0.053095926 | DS55: =DS46/$DJ55 -> 0.053095926 | ... EG55: =EG46/$DJ55 -> 0.73756817
G56: 4 | BK56: =SUM(BK50:BK55) -> 1 | BL56: OVERALL | BM56: =BM47/$BK56 -> 0 | BN56: =BN47/$BK56 -> 0.063355 | BO56: =BO47/$BK56 -> 0.100445 | BP56: =BP47/$BK56 -> 0.171525 | BQ56: =BQ47/$BK56 -> 0.21412 | BR56: =BR47/$BK56 -> 0.26307 | BS56: =BS47/$BK56 -> 0.38565 | BT56: =BT47/$BK56 -> 0.473875 | ... CH56: =CH47/$BK56 -> 1 | CJ56: =$BK56 -> 1 | CK56: OVERALL | CL56: =CL47/$CJ56 -> 0 | CM56: =CM47/$CJ56 -> 0 | CN56: =CN47/$CJ56 -> 0 | CO56: =CO47/$CJ56 -> 0.0309 | CP56: =CP47/$CJ56 -> 0.0309 | CQ56: =CQ47/$CJ56 -> 0.0309 | CR56: =CR47/$CJ56 -> 0.0309 | CS56: =CS47/$CJ56 -> 0.0309 | ... DG56: =DG47/$CJ56 -> 0.069525 | DJ56: =$BK56 -> 1 | DK56: OVERALL | DL56: =DL47/$DJ56 -> 0 | DM56: =DM47/$DJ56 -> 0.217725 | DN56: =DN47/$DJ56 -> 0.36179 | DO56: =DO47/$DJ56 -> 0.4188 | DP56: =DP47/$DJ56 -> 0.43756 | DQ56: =DQ47/$DJ56 -> 0.45301 | DR56: =DR47/$DJ56 -> 0.5126 | DS56: =DS47/$DJ56 -> 0.522025 | ... EG56: =EG47/$DJ56 -> 0.8667
G57: 4.a | H57: =MAX(J26,M26,Q26,U26,Y26) -> 46184 | I57: =MAX(H26,K26,O26,S26,W26) -> 46187 | J57: 46184
G58: 4.b | H58: =MAX(J27,M27,Q27,U27,Y27) -> 46173 | I58: =MAX(H27,K27,O27,S27,W27) -> 46173 | J58: 46173
G59: 4.c | H59: =MAX(J28,M28,Q28,U28,Y28) -> 46184 | I59: =MAX(H28,K28,O28,S28,W28) -> 46187 | J59: 46184
G60: 5
G61: 5.a | H61: =MAX(J30,M30,Q30,U30,Y30) -> 46156 | I61: =MAX(H30,K30,O30,S30,W30) -> 46156 | J61: 46156
G62: 5.b | H62: =MAX(J31,M31,Q31,U31,Y31) -> 46198 | I62: =MAX(H31,K31,O31,S31,W31) -> 46203 | J62: 46198
G63: 6
G64: 6.a | H64: =MAX(J33,M33,Q33,U33,Y33) -> 46187 | I64: =MAX(H33,K33,O33,S33,W33) -> 46194 | J64: 46187
G65: 6.b | H65: =MAX(J34,M34,Q34,U34,Y34) -> 46187 | I65: =MAX(H34,K34,O34,S34,W34) -> 46203 | J65: 46187
G66: 6.c | H66: =MAX(J35,M35,Q35,U35,Y35) -> 46204 | I66: =MAX(H35,K35,O35,S35,W35) -> 46233 | J66: 46192
G67: 6.d | H67: =MAX(J36,M36,Q36,U36,Y36) -> 46202 | I67: =MAX(H36,K36,O36,S36,W36) -> 46234 | J67: 46191

Sheet Appendix C
D1: =TOC!E1 -> PERTAMINA EP
D3: Project Title : | L3: Document Number :
D4: ='Cover Report'!Z1 -> Integrated Management Dashboard Production & Project Zona 13 | L4: ='Cover Report'!Z5 -> W2026I-DNGF-EM-100-PRG-WLY-0012
D5: Document Title: | L5: Appendix C
D6: =TOC!E6 -> Weekly Report
A27: APPENDIX C
A29: DOCUMENT SUBMITTED IN WEEK 11
R270: ELECTRICAL & INSTRUMENTATION ENGINEERING (as of 2 October)
J279: ELECTRICAL & INSTRUMENTATION ENGINEERING (as of 2 October)
AF350: 0.9176 | AG350: 0.8494
AG351: 1
AF357: 0.9121 | AG357: 0.8934
AG358: 0.685

Sheet Doc. Submitted
E1: =TOC!E1 -> PERTAMINA EP
E3: Project Title : | H3: Document Number : | K3: ='Cover Report'!Z5 -> W2026I-DNGF-EM-100-PRG-WLY-0012
E4: ='Cover Report'!Z1 -> Integrated Management Dashboard Production & Project Zona 13
E5: Document Title:
E6: =TOC!E6 -> Weekly Report
A8: ='Appendix C'!A29:P29 -> DOCUMENT SUBMITTED IN WEEK 11
A10: No | B10: Transmittal | E10: Doc./Dwg Number | H10: Deliverable | L10: Date Submission | M10: Status Document | N10: Remarks
A12: 1 | B12: TRM DWE-PHE ONWJ-350/001 | E12: FOXTROT-O-RPT-1102 | H12: Process Simulation Report | L12: 44463 | M12: IFR
A13: 2 | B13: TRM DWE-PHE ONWJ-350/002 | E13: FOXTROT-G-PHI-1101 | H13: Conceptual Design Basis & Design Philosophy | L13: 44463 | M13: IFR
A14: 1 | B14: TRM DWE-PHE ONWJ-350/003 | E14: FOXTROT-FXEA-P-PFD-6101 | H14: Process Flow Diagram (PFD) | L14: 44470 | M14: IFR
H15: FOXTROT-FXEA-P-PFD-6101~A-1 to 2 (Option 1~4)
H16: FOXTROT-FK-P-PFD-6001~82A (Option 1~4)
H17: FOXTROT-FK-P-PFD-6001D~82A (Demolition) (Option 1~4)
A19: 2 | B19: TRM DWE-PHE ONWJ-350/003 | E19: FOXTROT-FXEA-P-HMB-6101 | H19: Heat and Material Balance (HMB) | L19: 44470 | M19: IFR
H20: HMB FXEA (Option 1~4)
H21: HMB FK (Option 1~4)
A22: 1 | B22: TRM DWE-PHE ONWJ-350/004 | E22: FOXTROT-O-RPT-1104 | H22: Preliminary Line Sizing | L22: 44475 | M22: IFR
A23: 2 | B23: TRM DWE-PHE ONWJ-350/005 | E23: FOXTROT-O-RPT-1103 | H23: Adequacy Check FXEA Flatform | L23: 44477 | M23: IFR
A24: 1 | B24: TRM DWE-PHE ONWJ-350/006 | E24: FOXTROT-O-RPT-1101 | H24: Equipment Sizing Report | L24: 44480 | M24: IFR
A25: 2 | B25: TRM DWE-PHE ONWJ-350/006 | E25: FOXTROT-M-LST-1101 | H25: Equipment List for New Equipment | L25: 44480 | M25: IFR
A26: 3 | B26: TRM DWE-PHE ONWJ-350/007 | E26: FOXTROT-FXEA-M-EQL-5101 | H26: EQL for new platform (4 Option) | L26: 44482 | M26: IFR
A27: 1 | B27: ITS-PEP-IMDZ13-TR-2026-0011 | E27: W2026I-DNGF-EM-100-PRG-WLY-0011 | H27: Weekly Report | L27: 46205 | M27: IFR
G150: ELECTRICAL & INSTRUMENTATION ENGINEERING (as of 2 October)
O230: 0.9176 | P230: 0.8494
P231: 1
O237: 0.9121 | P237: 0.8934
P238: 0.685

Sheet Appendix D
D1: =TOC!E1 -> PERTAMINA EP
D3: Project Title : | L3: Document Number :
D4: ='Cover Report'!Z1 -> Integrated Management Dashboard Production & Project Zona 13 | L4: ='Cover Report'!Z5 -> W2026I-DNGF-EM-100-PRG-WLY-0012
D5: Document Title: | L5: Appendix C
D6: =TOC!E6 -> Weekly Report
A27: APPENDIX D
A29: ACTIVITY DOCUMENTATION WEEK 11

Sheet Activity Documentation
E1: =TOC!E1 -> PERTAMINA EP
E3: Project Title : | H3: Document Number : | K3: ='Cover Report'!Z5 -> W2026I-DNGF-EM-100-PRG-WLY-0012
E4: ='Cover Report'!Z1 -> Integrated Management Dashboard Production & Project Zona 13
E5: Document Title:
E6: =TOC!E6 -> Weekly Report
A8: ='Appendix D'!A29:P29 -> ACTIVITY DOCUMENTATION WEEK 11
B10: DATE | C10: ACTIVITY | E10: DOCUMENTATION
B11: 46201 | C11: Tim ITS telah menyelesaikan 8 menu dashboard sebagaimana pada gambar dibawah mencapai total keseluruhan ketercapaian menu dashboard 88.89%. Untuk 1 menu OSF – AIRMS sedang dalam proses.
